Workbook
Name CARTERA_2025: Tabla134[#All]
Name CARTERA_2025: CARTERA_2026[#All]
Name CARTERA_2025: Tabla13[#All]

Sheet CARTERA 2024
A1: RUT | B1: RAZON | C1: VENDEDOR | E1: =MID(A1, 1, 2) & "." & MID(A1, 3, 3) & "." & MID(A1, 6, 3) & "-" & RIGHT(A1, 1) -> RU.T.-T | F1: SN | I1: Nota: Se actualizo la cartera 2025, sin embargo, cartera de SANTIAGO III Y SUR III pasan a atencion telefonica ya que no tienen vendedor.
A2: 611020171 | B2: HOSPITAL NAVAL ALMIRANTE NEF | C2: C VALENZUELA | E2: =VALUE(MID(Tabla1[[#This Row],[RUT]],1,LEN(Tabla1[[#This Row],[RUT]])-1)) -> 61102017 | F2: ="CN"&E2 -> CN61102017
A3: 616020366 | B3: HOSPITAL SAN JUAN DE DIOS DE LOS ANDES | C3: C VALENZUELA | E3: =VALUE(MID(Tabla1[[#This Row],[RUT]],1,LEN(Tabla1[[#This Row],[RUT]])-1)) -> 61602036 | F3: ="CN"&E3 -> CN61602036
A4: 616020382 | B4: HOSPITAL SAN CAMILO DE SAN FELIPE | C4: C VALENZUELA | E4: =VALUE(MID(Tabla1[[#This Row],[RUT]],1,LEN(Tabla1[[#This Row],[RUT]])-1)) -> 61602038 | F4: ="CN"&E4 -> CN61602038
A5: 616020544 | B5: HOSPITAL CARLOS VAN BUREN | C5: C VALENZUELA | E5: =VALUE(MID(Tabla1[[#This Row],[RUT]],1,LEN(Tabla1[[#This Row],[RUT]])-1)) -> 61602054 | F5: ="CN"&E5 -> CN61602054
A6: 616020579 | B6: HOSPITAL EDUARDO PEREIRA | C6: C VALENZUELA | E6: =VALUE(MID(Tabla1[[#This Row],[RUT]],1,LEN(Tabla1[[#This Row],[RUT]])-1)) -> 61602057 | F6: ="CN"&E6 -> CN61602057
A7: 616021265 | B7: HOSPITAL CLAUDIO VICUÑA | C7: C VALENZUELA | E7: =VALUE(MID(Tabla1[[#This Row],[RUT]],1,LEN(Tabla1[[#This Row],[RUT]])-1)) -> 61602126 | F7: ="CN"&E7 -> CN61602126
A8: 616064029 | B8: HOSPITAL LA SERENA | C8: C VALENZUELA | E8: =VALUE(MID(Tabla1[[#This Row],[RUT]],1,LEN(Tabla1[[#This Row],[RUT]])-1)) -> 61606402 | F8: ="CN"&E8 -> CN61606402
A9: 616064037 | B9: HOSPITAL COQUIMBO | C9: C VALENZUELA | E9: =VALUE(MID(Tabla1[[#This Row],[RUT]],1,LEN(Tabla1[[#This Row],[RUT]])-1)) -> 61606403 | F9: ="CN"&E9 -> CN61606403
A10: 616064045 | B10: HOSPITAL OVALLE | C10: C VALENZUELA | E10: =VALUE(MID(Tabla1[[#This Row],[RUT]],1,LEN(Tabla1[[#This Row],[RUT]])-1)) -> 61606404 | F10: ="CN"&E10 -> CN61606404
A11: 616065009 | B11: SERVICIO DE SALUD VALPARAISO SAN ANTONIO | C11: C VALENZUELA | E11: =VALUE(MID(Tabla1[[#This Row],[RUT]],1,LEN(Tabla1[[#This Row],[RUT]])-1)) -> 61606500 | F11: ="CN"&E11 -> CN61606500
A12: 616066021 | B12: HOSPITAL DR. GUSTAVO FRICKE | C12: C VALENZUELA | E12: =VALUE(MID(Tabla1[[#This Row],[RUT]],1,LEN(Tabla1[[#This Row],[RUT]])-1)) -> 61606602 | F12: ="CN"&E12 -> CN61606602
A13: 616066048 | B13: HOSPITAL DE QUILPUE | C13: C VALENZUELA | E13: =VALUE(MID(Tabla1[[#This Row],[RUT]],1,LEN(Tabla1[[#This Row],[RUT]])-1)) -> 61606604 | F13: ="CN"&E13 -> CN61606604
... A42: 995736004 | B42: CLINICA RIO BLANCO S.A | C42: C VALENZUELA | E42: =VALUE(MID(Tabla1[[#This Row],[RUT]],1,LEN(Tabla1[[#This Row],[RUT]])-1)) -> 99573600 | F42: ="CN"&E42 -> CN99573600
A43: 61606603K | B43: HOSPITAL ADRIANA COUSIÑO DE QUINTERO | C43: A TELEFONICA | E43: =VALUE(MID(Tabla1[[#This Row],[RUT]],1,LEN(Tabla1[[#This Row],[RUT]])-1)) -> 61606603 | F43: ="CN"&E43 -> CN61606603
A44: 137714132 | B44: EVELYN ARANDA ARANDA | C44: A TELEFONICA | E44: =VALUE(MID(Tabla1[[#This Row],[RUT]],1,LEN(Tabla1[[#This Row],[RUT]])-1)) -> 13771413 | F44: ="CN"&E44 -> CN13771413
A45: 159017230 | B45: MIGUEL EDUARDO PEÑA PARRA | C45: A TELEFONICA | E45: =VALUE(MID(Tabla1[[#This Row],[RUT]],1,LEN(Tabla1[[#This Row],[RUT]])-1)) -> 15901723 | F45: ="CN"&E45 -> CN15901723
A46: 164793079 | B46: DANIEL ALEJANDRO PINO MARTINEZ | C46: A TELEFONICA | E46: =VALUE(MID(Tabla1[[#This Row],[RUT]],1,LEN(Tabla1[[#This Row],[RUT]])-1)) -> 16479307 | F46: ="CN"&E46 -> CN16479307
A47: 609110007 | B47: UNIVERSIDAD DE SANTIAGO DE CHILE | C47: A TELEFONICA | E47: =VALUE(MID(Tabla1[[#This Row],[RUT]],1,LEN(Tabla1[[#This Row],[RUT]])-1)) -> 60911000 | F47: ="CN"&E47 -> CN60911000
A48: 609210001 | B48: UNIVERSIDAD DE VALPARAISO | C48: A TELEFONICA | E48: =VALUE(MID(Tabla1[[#This Row],[RUT]],1,LEN(Tabla1[[#This Row],[RUT]])-1)) -> 60921000 | F48: ="CN"&E48 -> CN60921000
A49: 610040241 | B49: DIRECCION REGIONAL DE GENDARMERIA - VALPARAISO | C49: A TELEFONICA | E49: =VALUE(MID(Tabla1[[#This Row],[RUT]],1,LEN(Tabla1[[#This Row],[RUT]])-1)) -> 61004024 | F49: ="CN"&E49 -> CN61004024
A50: 611010311 | B50: CENTRAL ODONTOLÓGICA DEL EJÉRCITO - COE | C50: A TELEFONICA | E50: =VALUE(MID(Tabla1[[#This Row],[RUT]],1,LEN(Tabla1[[#This Row],[RUT]])-1)) -> 61101031 | F50: ="CN"&E50 -> CN61101031
A51: 611010826 | B51: CENTRO CLÍNICO MILITAR ARICA | C51: A TELEFONICA | E51: =VALUE(MID(Tabla1[[#This Row],[RUT]],1,LEN(Tabla1[[#This Row],[RUT]])-1)) -> 61101082 | F51: ="CN"&E51 -> CN61101082
A52: 611010869 | B52: HOSPITAL MILITAR DEL NORTE | C52: A TELEFONICA | E52: =VALUE(MID(Tabla1[[#This Row],[RUT]],1,LEN(Tabla1[[#This Row],[RUT]])-1)) -> 61101086 | F52: ="CN"&E52 -> CN61101086
A53: 611020295 | B53: HOSPITAL NAVAL CIRUJANO GUZMAN DE MAGALLANES | C53: A TELEFONICA | E53: =VALUE(MID(Tabla1[[#This Row],[RUT]],1,LEN(Tabla1[[#This Row],[RUT]])-1)) -> 61102029 | F53: ="CN"&E53 -> CN61102029
A54: 611020678 | B54: CENTRAL ODONTOLOGICA IIA ZONA NAVAL | C54: A TELEFONICA | E54: =VALUE(MID(Tabla1[[#This Row],[RUT]],1,LEN(Tabla1[[#This Row],[RUT]])-1)) -> 61102067 | F54: ="CN"&E54 -> CN61102067
A55: 611030193 | B55: ALA BASE N.1 | C55: A TELEFONICA | E55: =VALUE(MID(Tabla1[[#This Row],[RUT]],1,LEN(Tabla1[[#This Row],[RUT]])-1)) -> 61103019 | F55: ="CN"&E55 -> CN61103019
... A618: 995931702 | B618: CEGAMED CHILE S.A. | C618: A TELEFONICA | E618: =VALUE(MID(Tabla1[[#This Row],[RUT]],1,LEN(Tabla1[[#This Row],[RUT]])-1)) -> 99593170 | F618: ="CN"&E618 -> CN99593170
A619: 61004042K | B619: GENDARMERIA DE CHILE VI DIRECCION REGIONAL RANCAGUA | C619: A TELEFONICA | E619: =VALUE(MID(Tabla1[[#This Row],[RUT]],1,LEN(Tabla1[[#This Row],[RUT]])-1)) -> 61004042 | F619: ="CN"&E619 -> CN61004042
A620: 61108000K | B620: CAJA DE PREVISION DE LA DEFENSA NACIONAL | C620: A TELEFONICA | E620: =VALUE(MID(Tabla1[[#This Row],[RUT]],1,LEN(Tabla1[[#This Row],[RUT]])-1)) -> 61108000 | F620: ="CN"&E620 -> CN61108000
A621: 61601000K | B621: SUBSECRETARIA DE SALUD PUBLICA | C621: A TELEFONICA | E621: =VALUE(MID(Tabla1[[#This Row],[RUT]],1,LEN(Tabla1[[#This Row],[RUT]])-1)) -> 61601000 | F621: ="CN"&E621 -> CN61601000
A622: 61602132K | B622: HOSPITAL SANTA FILOMENA DE GRANEROS | C622: A TELEFONICA | E622: =VALUE(MID(Tabla1[[#This Row],[RUT]],1,LEN(Tabla1[[#This Row],[RUT]])-1)) -> 61602132 | F622: ="CN"&E622 -> CN61602132
A623: 61602146K | B623: HOSPITAL DE CHIMBARONGO | C623: A TELEFONICA | E623: =VALUE(MID(Tabla1[[#This Row],[RUT]],1,LEN(Tabla1[[#This Row],[RUT]])-1)) -> 61602146 | F623: ="CN"&E623 -> CN61602146
A624: 61602194K | B624: HOSPITAL DE COELEMU | C624: A TELEFONICA | E624: =VALUE(MID(Tabla1[[#This Row],[RUT]],1,LEN(Tabla1[[#This Row],[RUT]])-1)) -> 61602194 | F624: ="CN"&E624 -> CN61602194
A625: 61602244K | B625: HOSPITAL DE CUNCO | C625: A TELEFONICA | E625: =VALUE(MID(Tabla1[[#This Row],[RUT]],1,LEN(Tabla1[[#This Row],[RUT]])-1)) -> 61602244 | F625: ="CN"&E625 -> CN61602244
A626: 61602261K | B626: HOSPITAL DE PUERTO OCTAY | C626: A TELEFONICA | E626: =VALUE(MID(Tabla1[[#This Row],[RUT]],1,LEN(Tabla1[[#This Row],[RUT]])-1)) -> 61602261 | F626: ="CN"&E626 -> CN61602261
A627: 61602275K | B627: HOSPITAL DE CASTRO DR. AUGUSTO RIFFART | C627: M RUIZ | E627: =VALUE(MID(Tabla1[[#This Row],[RUT]],1,LEN(Tabla1[[#This Row],[RUT]])-1)) -> 61602275 | F627: ="CN"&E627 -> CN61602275
A628: 61602292K | B628: HOSPITAL COCHRANE | C628: A TELEFONICA | E628: =VALUE(MID(Tabla1[[#This Row],[RUT]],1,LEN(Tabla1[[#This Row],[RUT]])-1)) -> 61602292 | F628: ="CN"&E628 -> CN61602292
A629: 61602311K | B629: HOSPITAL CHAITEN | C629: A TELEFONICA | E629: =VALUE(MID(Tabla1[[#This Row],[RUT]],1,LEN(Tabla1[[#This Row],[RUT]])-1)) -> 61602311 | F629: ="CN"&E629 -> CN61602311
A630: 61606200K | B630: DIRECCIÓN SERVICIO DE SALUD ANTOFAGASTA | C630: A TELEFONICA | E630: =VALUE(MID(Tabla1[[#This Row],[RUT]],1,LEN(Tabla1[[#This Row],[RUT]])-1)) -> 61606200 | F630: ="CN"&E630 -> CN61606200
... A684: 96879440K | B684: SONORAD II S.A. | C684: A TELEFONICA | E684: =VALUE(MID(Tabla1[[#This Row],[RUT]],1,LEN(Tabla1[[#This Row],[RUT]])-1)) -> 96879440 | F684: ="CN"&E684 -> CN96879440
A685: 605057233 | B685: HOSPITAL DE CARABINEROS | C685: G MANNESCHI | E685: =VALUE(MID(Tabla1[[#This Row],[RUT]],1,LEN(Tabla1[[#This Row],[RUT]])-1)) -> 60505723 | F685: ="CN"&E685 -> CN60505723
A686: 605140009 | B686: FONDOS PARA HOSPITALES DE CARABINEROS DE CHILE | C686: G MANNESCHI | E686: =VALUE(MID(Tabla1[[#This Row],[RUT]],1,LEN(Tabla1[[#This Row],[RUT]])-1)) -> 60514000 | F686: ="CN"&E686 -> CN60514000
A687: 611010303 | B687: HOSPITAL MILITAR DE SANTIAGO | C687: G MANNESCHI | E687: =VALUE(MID(Tabla1[[#This Row],[RUT]],1,LEN(Tabla1[[#This Row],[RUT]])-1)) -> 61101030 | F687: ="CN"&E687 -> CN61101030
A688: 615130036 | B688: FONDOS PARA HOSPITALES DE CARABINEROS DE CHILE | C688: G MANNESCHI | E688: =VALUE(MID(Tabla1[[#This Row],[RUT]],1,LEN(Tabla1[[#This Row],[RUT]])-1)) -> 61513003 | F688: ="CN"&E688 -> CN61513003
A689: 616021176 | B689: INSTITUTO NAC. DE REHABILITACION PEDRO AGUIRRE | C689: A TELEFONICA | E689: =VALUE(MID(Tabla1[[#This Row],[RUT]],1,LEN(Tabla1[[#This Row],[RUT]])-1)) -> 61602117 | F689: ="CN"&E689 -> CN61602117
A690: 616021230 | B690: HOSPITAL DE MELIPILLA | C690: G MANNESCHI | E690: =VALUE(MID(Tabla1[[#This Row],[RUT]],1,LEN(Tabla1[[#This Row],[RUT]])-1)) -> 61602123 | F690: ="CN"&E690 -> CN61602123
A691: 616081071 | B691: HOSPITAL EL PINO | C691: G MANNESCHI | E691: =VALUE(MID(Tabla1[[#This Row],[RUT]],1,LEN(Tabla1[[#This Row],[RUT]])-1)) -> 61608107 | F691: ="CN"&E691 -> CN61608107
A692: 616082043 | B692: HOSPITAL SAN JUAN DE DIOS | C692: G MANNESCHI | E692: =VALUE(MID(Tabla1[[#This Row],[RUT]],1,LEN(Tabla1[[#This Row],[RUT]])-1)) -> 61608204 | F692: ="CN"&E692 -> CN61608204
A693: 616082051 | B693: HOSPITAL DR. FELIX BULNES CERDA | C693: G MANNESCHI | E693: =VALUE(MID(Tabla1[[#This Row],[RUT]],1,LEN(Tabla1[[#This Row],[RUT]])-1)) -> 61608205 | F693: ="CN"&E693 -> CN61608205
A694: 616085026 | B694: COMPLEJO ASISTENCIAL DR. SOTERO DEL RIO | C694: G MANNESCHI | E694: =VALUE(MID(Tabla1[[#This Row],[RUT]],1,LEN(Tabla1[[#This Row],[RUT]])-1)) -> 61608502 | F694: ="CN"&E694 -> CN61608502
A695: 616086022 | B695: HOSPITAL DE URGENCIA ASISTENCIA PUBLICA | C695: G MANNESCHI | E695: =VALUE(MID(Tabla1[[#This Row],[RUT]],1,LEN(Tabla1[[#This Row],[RUT]])-1)) -> 61608602 | F695: ="CN"&E695 -> CN61608602
A696: 619532007 | B696: CRS DE PEÑALOLEN CORDILLERA ORIENTE | C696: A TELEFONICA | E696: =VALUE(MID(Tabla1[[#This Row],[RUT]],1,LEN(Tabla1[[#This Row],[RUT]])-1)) -> 61953200 | F696: ="CN"&E696 -> CN61953200
... A709: 995734907 | B709: UC CHRISTUS SERVICIOS CLÍNICOS SPA. | C709: G MANNESCHI | E709: =VALUE(MID(Tabla1[[#This Row],[RUT]],1,LEN(Tabla1[[#This Row],[RUT]])-1)) -> 99573490 | F709: ="CN"&E709 -> CN99573490
A710: 61103007K | B710: HOSPITAL CLINICO GENERAL DR. RAUL YAZIGI J. | C710: G MANNESCHI | E710: =VALUE(MID(Tabla1[[#This Row],[RUT]],1,LEN(Tabla1[[#This Row],[RUT]])-1)) -> 61103007 | F710: ="CN"&E710 -> CN61103007
A711: 703601006 | B711: ASOCIACION CHILENA DE SEGURIDAD | C711: A TELEFONICA | E711: =VALUE(MID(Tabla1[[#This Row],[RUT]],1,LEN(Tabla1[[#This Row],[RUT]])-1)) -> 70360100 | F711: ="CN"&E711 -> CN70360100
A712: 761988220 | B712: EMPRESA DE SERVICIOS EXTERNOS ASOCIACION CHILENA DE SEGURIDAD TRANSPOR | C712: A TELEFONICA | E712: =VALUE(MID(Tabla1[[#This Row],[RUT]],1,LEN(Tabla1[[#This Row],[RUT]])-1)) -> 76198822 | F712: ="CN"&E712 -> CN76198822
A713: 995792605 | B713: EMPRESA DE SERV. EXTERNOS ACHS S.A. | C713: A TELEFONICA | E713: =VALUE(MID(Tabla1[[#This Row],[RUT]],1,LEN(Tabla1[[#This Row],[RUT]])-1)) -> 99579260 | F713: ="CN"&E713 -> CN99579260
A714: 76481620K | B714: CENTRO MÉDICO HTS SPA | C714: A TELEFONICA | E714: =VALUE(MID(Tabla1[[#This Row],[RUT]],1,LEN(Tabla1[[#This Row],[RUT]])-1)) -> 76481620 | F714: ="CN"&E714 -> CN76481620
A715: 531258509 | B715: HOSPITAL CLINICO DEL PROFESOR | C715: M RAMOS | E715: =VALUE(MID(Tabla1[[#This Row],[RUT]],1,LEN(Tabla1[[#This Row],[RUT]])-1)) -> 53125850 | F715: ="CN"&E715 -> CN53125850
A716: 609100001 | B716: UNIVERSIDAD DE CHILE | C716: M RAMOS | E716: =VALUE(MID(Tabla1[[#This Row],[RUT]],1,LEN(Tabla1[[#This Row],[RUT]])-1)) -> 60910000 | F716: ="CN"&E716 -> CN60910000
A717: 616080024 | B717: HOSPITAL SAN JOSE | C717: M RAMOS | E717: =VALUE(MID(Tabla1[[#This Row],[RUT]],1,LEN(Tabla1[[#This Row],[RUT]])-1)) -> 61608002 | F717: ="CN"&E717 -> CN61608002
A718: 616080032 | B718: INSTITUTO PSIQUIÁTRICO DR. JOSÉ HORWITZ B. | C718: M RAMOS | E718: =VALUE(MID(Tabla1[[#This Row],[RUT]],1,LEN(Tabla1[[#This Row],[RUT]])-1)) -> 61608003 | F718: ="CN"&E718 -> CN61608003
A719: 616080040 | B719: HOSPITAL DE NIÑOS ROBERTO DEL RIO | C719: M RAMOS | E719: =VALUE(MID(Tabla1[[#This Row],[RUT]],1,LEN(Tabla1[[#This Row],[RUT]])-1)) -> 61608004 | F719: ="CN"&E719 -> CN61608004
A720: 616081012 | B720: HOSPITAL BARROS LUCO TRUDEAU | C720: M RAMOS | E720: =VALUE(MID(Tabla1[[#This Row],[RUT]],1,LEN(Tabla1[[#This Row],[RUT]])-1)) -> 61608101 | F720: ="CN"&E720 -> CN61608101
A721: 616081020 | B721: HOSPITAL DR. EXEQUIEL GONZALEZ CORTES | C721: M RAMOS | E721: =VALUE(MID(Tabla1[[#This Row],[RUT]],1,LEN(Tabla1[[#This Row],[RUT]])-1)) -> 61608102 | F721: ="CN"&E721 -> CN61608102
A722: 616081047 | B722: S.S. METROPOLITANO SUR HOSPITAL LUCIO CORDOVA | C722: M RAMOS | E722: =VALUE(MID(Tabla1[[#This Row],[RUT]],1,LEN(Tabla1[[#This Row],[RUT]])-1)) -> 61608104 | F722: ="CN"&E722 -> CN61608104
A723: 616082035 | B723: SERVICIO DE SALUD OCCIDENTE INSTITUTO TRAUMATOLOGICO DE SANTIAGO | C723: M RAMOS | E723: =VALUE(MID(Tabla1[[#This Row],[RUT]],1,LEN(Tabla1[[#This Row],[RUT]])-1)) -> 61608203 | F723: ="CN"&E723 -> CN61608203
A724: 616084046 | B724: INSTITUTO NACIONAL DEL CANCER | C724: M RAMOS | E724: =VALUE(MID(Tabla1[[#This Row],[RUT]],1,LEN(Tabla1[[#This Row],[RUT]])-1)) -> 61608404 | F724: ="CN"&E724 -> CN61608404
A725: 616084062 | B725: HOSPITAL DEL SALVADOR | C725: M RAMOS | E725: =VALUE(MID(Tabla1[[#This Row],[RUT]],1,LEN(Tabla1[[#This Row],[RUT]])-1)) -> 61608406 | F725: ="CN"&E725 -> CN61608406
A726: 616086049 | B726: HOSPITAL CLINICO SAN BORJA ARRIARAN | C726: M RAMOS | E726: =VALUE(MID(Tabla1[[#This Row],[RUT]],1,LEN(Tabla1[[#This Row],[RUT]])-1)) -> 61608604 | F726: ="CN"&E726 -> CN61608604
... A767: 968859404 | B767: CLINICA BIO BIO SPA | C767: R ARAYA | E767: =VALUE(MID(Tabla1[[#This Row],[RUT]],1,LEN(Tabla1[[#This Row],[RUT]])-1)) -> 96885940 | F767: ="CN"&E767 -> CN96885940
A768: 61602213K | B768: HOSPITAL CAÑETE | C768: R ARAYA | E768: =VALUE(MID(Tabla1[[#This Row],[RUT]],1,LEN(Tabla1[[#This Row],[RUT]])-1)) -> 61602213 | F768: ="CN"&E768 -> CN61602213
A769: 61607301K | B769: HOSPITAL BASE DR. VICTOR RIOS RUIZ | C769: R ARAYA | E769: =VALUE(MID(Tabla1[[#This Row],[RUT]],1,LEN(Tabla1[[#This Row],[RUT]])-1)) -> 61607301 | F769: ="CN"&E769 -> CN61607301
A770: 69264400K | B770: MUNICIPALIDAD DE HUALPEN | C770: R ARAYA | E770: =VALUE(MID(Tabla1[[#This Row],[RUT]],1,LEN(Tabla1[[#This Row],[RUT]])-1)) -> 69264400 | F770: ="CN"&E770 -> CN69264400
A771: 69270200K | B771: ILUSTRE MUNICIPALIDAD DE CHILLAN DPTO SALUD | C771: R ARAYA | E771: =VALUE(MID(Tabla1[[#This Row],[RUT]],1,LEN(Tabla1[[#This Row],[RUT]])-1)) -> 69270200 | F771: ="CN"&E771 -> CN69270200
A772: 96662020K | B772: CLINICA LOS ANDES DE LOS ANGELES | C772: R ARAYA | E772: =VALUE(MID(Tabla1[[#This Row],[RUT]],1,LEN(Tabla1[[#This Row],[RUT]])-1)) -> 96662020 | F772: ="CN"&E772 -> CN96662020
A773: 616022296 | B773: HOSPITAL VICTORIA | C773: M RUIZ | E773: =VALUE(MID(Tabla1[[#This Row],[RUT]],1,LEN(Tabla1[[#This Row],[RUT]])-1)) -> 61602229 | F773: ="CN"&E773 -> CN61602229
A774: 616022326 | B774: HOSPITAL DOCTOR HERNAN HENRIQUEZ ARAVENA | C774: M RUIZ | E774: =VALUE(MID(Tabla1[[#This Row],[RUT]],1,LEN(Tabla1[[#This Row],[RUT]])-1)) -> 61602232 | F774: ="CN"&E774 -> CN61602232
A775: 616022369 | B775: HOSPITAL DR. ABRAHAM GODOY PEÑA | C775: M RUIZ | E775: =VALUE(MID(Tabla1[[#This Row],[RUT]],1,LEN(Tabla1[[#This Row],[RUT]])-1)) -> 61602236 | F775: ="CN"&E775 -> CN61602236
A776: 616022385 | B776: HOSPITAL PITRUFQUÉN | C776: M RUIZ | E776: =VALUE(MID(Tabla1[[#This Row],[RUT]],1,LEN(Tabla1[[#This Row],[RUT]])-1)) -> 61602238 | F776: ="CN"&E776 -> CN61602238
A777: 616022482 | B777: HOSPITAL VILLARRICA | C777: M RUIZ | E777: =VALUE(MID(Tabla1[[#This Row],[RUT]],1,LEN(Tabla1[[#This Row],[RUT]])-1)) -> 61602248 | F777: ="CN"&E777 -> CN61602248
A778: 616022601 | B778: HOSPITAL BASE OSORNO | C778: M RUIZ | E778: =VALUE(MID(Tabla1[[#This Row],[RUT]],1,LEN(Tabla1[[#This Row],[RUT]])-1)) -> 61602260 | F778: ="CN"&E778 -> CN61602260
A779: 616022733 | B779: HOSPITAL CALBUCO | C779: M RUIZ | E779: =VALUE(MID(Tabla1[[#This Row],[RUT]],1,LEN(Tabla1[[#This Row],[RUT]])-1)) -> 61602273 | F779: ="CN"&E779 -> CN61602273
A780: 616074016 | B780: HOSPITAL NUEVA IMPERIAL | C780: M RUIZ | E780: =VALUE(MID(Tabla1[[#This Row],[RUT]],1,LEN(Tabla1[[#This Row],[RUT]])-1)) -> 61607401 | F780: ="CN"&E780 -> CN61607401
A781: 616075020 | B781: HOSPITAL VALDIVIA | C781: M RUIZ | E781: =VALUE(MID(Tabla1[[#This Row],[RUT]],1,LEN(Tabla1[[#This Row],[RUT]])-1)) -> 61607502 | F781: ="CN"&E781 -> CN61607502
A782: 616075039 | B782: HOSPITAL DE LA UNION | C782: M RUIZ | E782: =VALUE(MID(Tabla1[[#This Row],[RUT]],1,LEN(Tabla1[[#This Row],[RUT]])-1)) -> 61607503 | F782: ="CN"&E782 -> CN61607503
A783: 619550005 | B783: MUNICIPALIDAD DE PADRE LAS CASAS | C783: M RUIZ | E783: =VALUE(MID(Tabla1[[#This Row],[RUT]],1,LEN(Tabla1[[#This Row],[RUT]])-1)) -> 61955000 | F783: ="CN"&E783 -> CN61955000
A784: 619751000 | B784: HOSPITAL DE PUERTO MONTT | C784: M RUIZ | E784: =VALUE(MID(Tabla1[[#This Row],[RUT]],1,LEN(Tabla1[[#This Row],[RUT]])-1)) -> 61975100 | F784: ="CN"&E784 -> CN61975100
... A803: 967745804 | B803: INMOBILIARIA INVERSALUD SPA | C803: M RUIZ | E803: =VALUE(MID(Tabla1[[#This Row],[RUT]],1,LEN(Tabla1[[#This Row],[RUT]])-1)) -> 96774580 | F803: ="CN"&E803 -> CN96774580
A804: 53335808K | B804: CONS EXTERNO VALDIVIA | C804: M RUIZ | E804: =VALUE(MID(Tabla1[[#This Row],[RUT]],1,LEN(Tabla1[[#This Row],[RUT]])-1)) -> 53335808 | F804: ="CN"&E804 -> CN53335808
A805: 69191500K | B805: I MUNICIPALIDAD DE VILLARRICA | C805: M RUIZ | E805: =VALUE(MID(Tabla1[[#This Row],[RUT]],1,LEN(Tabla1[[#This Row],[RUT]])-1)) -> 69191500 | F805: ="CN"&E805 -> CN69191500
A806: 610040004 | B806: GENDARMERIA DE CHILE | C806: A TELEFONICA | E806: =VALUE(MID(Tabla1[[#This Row],[RUT]],1,LEN(Tabla1[[#This Row],[RUT]])-1)) -> 61004000 | F806: ="CN"&E806 -> CN61004000
A807: 616022245 | B807: HOSPITAL PUREN | C807: A TELEFONICA | E807: =VALUE(MID(Tabla1[[#This Row],[RUT]],1,LEN(Tabla1[[#This Row],[RUT]])-1)) -> 61602224 | F807: ="CN"&E807 -> CN61602224
A808: 616022741 | B808: HOSPITAL FUTALEUFU | C808: A TELEFONICA | E808: =VALUE(MID(Tabla1[[#This Row],[RUT]],1,LEN(Tabla1[[#This Row],[RUT]])-1)) -> 61602274 | F808: ="CN"&E808 -> CN61602274
A809: 616022814 | B809: HOSPITAL CHILE CHICO | C809: A TELEFONICA | E809: =VALUE(MID(Tabla1[[#This Row],[RUT]],1,LEN(Tabla1[[#This Row],[RUT]])-1)) -> 61602281 | F809: ="CN"&E809 -> CN61602281
A810: 616023128 | B810: HOSPITAL ALTO PALENA | C810: A TELEFONICA | E810: =VALUE(MID(Tabla1[[#This Row],[RUT]],1,LEN(Tabla1[[#This Row],[RUT]])-1)) -> 61602312 | F810: ="CN"&E810 -> CN61602312
A811: 616066072 | B811: HOSPITAL GERIATRICO LA PAZ DE TARDE | C811: A TELEFONICA | E811: =VALUE(MID(Tabla1[[#This Row],[RUT]],1,LEN(Tabla1[[#This Row],[RUT]])-1)) -> 61606607 | F811: ="CN"&E811 -> CN61606607
A812: 616073044 | B812: HOSPITAL SANTA BARBARA | C812: A TELEFONICA | E812: =VALUE(MID(Tabla1[[#This Row],[RUT]],1,LEN(Tabla1[[#This Row],[RUT]])-1)) -> 61607304 | F812: ="CN"&E812 -> CN61607304
A813: 616075004 | B813: SERVICIO DE SALUD LOS RIOS | C813: A TELEFONICA | E813: =VALUE(MID(Tabla1[[#This Row],[RUT]],1,LEN(Tabla1[[#This Row],[RUT]])-1)) -> 61607500 | F813: ="CN"&E813 -> CN61607500
...

Sheet visitas ricardo
A1: VENDEDOR | B1: RICARDO ENRIQUE ARAYA GONZÁLEZ
A3: Etiquetas de fila | C3: 45756 | D3: 45757 | E3: 45758 | F3: 45761 | G3: 45762 | H3: 45763 | I3: 45764 | J3: 45768 | K3: 45769 | L3: 45770 | M3: 45771 | N3: 45772 | O3: 45775 | P3: 45776 | Q3: 45777
A4: CENTRO DE SALUD DR. VICTOR RIOS M. FERNANDEZ | R4: =SUM(C4:Q4) -> 0
A5: CLINICA ANDES SALUD CHILLAN S.A | N5: 1 | O5: 1 | Q5: 1 | R5: =SUM(C5:Q5) -> 3
A6: CLINICA ANDES SALUD CONCEPCION S.A | R6: =SUM(C6:Q6) -> 0
A7: CLINICA BIO BIO SPA | K7: 1 | R7: =SUM(C7:Q7) -> 1
A8: CLINICA LAS AMAPOLAS LIMITADA | F8: 1 | L8: 1 | O8: 1 | Q8: 1 | R8: =SUM(C8:Q8) -> 4
A9: CLINICA LOS ANDES DE LOS ANGELES | E9: 1 | K9: 1 | R9: =SUM(C9:Q9) -> 2
A10: CLINICA SANATORIO ALEMAN S.A | K10: 1 | R10: =SUM(C10:Q10) -> 1
A11: CONSULTORIO GENERAL URBANO VIOLETA PARRA | R11: =SUM(C11:Q11) -> 0
A12: CORPORACION IGLESIA ADVENTISTA DEL 7Â° DIA | R12: =SUM(C12:Q12) -> 0
A13: DIRECCION DE SALUD MUNICIPAL DE TOME | D13: 1 | R13: =SUM(C13:Q13) -> 1
A14: DIRECCION DE SALUD SAN PEDRO DE LA PAZ | R14: =SUM(C14:Q14) -> 0
A15: HOSPITAL ANGOL | G15: 1 | R15: =SUM(C15:Q15) -> 1
A16: HOSPITAL ARAUCO | C16: 1 | R16: =SUM(C16:Q16) -> 1
A17: HOSPITAL BASE DR. VICTOR RIOS RUIZ | R17: =SUM(C17:Q17) -> 0
A18: HOSPITAL CAÑETE | C18: 1 | R18: =SUM(C18:Q18) -> 1
A19: HOSPITAL CLINICO DEL SUR | R19: =SUM(C19:Q19) -> 0
A20: HOSPITAL CLINICO HERMINDA MARTIN | H20: 1 | R20: =SUM(C20:Q20) -> 1
A21: HOSPITAL DE CURANILAHUE | C21: 1 | R21: =SUM(C21:Q21) -> 1
A22: HOSPITAL DE PENCO | D22: 1 | R22: =SUM(C22:Q22) -> 1
A23: HOSPITAL DE SAN CARLOS | J23: 1 | R23: =SUM(C23:Q23) -> 1
A24: HOSPITAL DE TOME | D24: 1 | R24: =SUM(C24:Q24) -> 1
A25: HOSPITAL GUILLERMO GRANT BENAVENTE | R25: =SUM(C25:Q25) -> 0
A26: HOSPITAL LAS HIGUERAS | D26: 1 | P26: 1 | R26: =SUM(C26:Q26) -> 2
A27: HOSPITAL LEBU | C27: 1 | R27: =SUM(C27:Q27) -> 1
A28: HOSPITAL LOTA | M28: 1 | R28: =SUM(C28:Q28) -> 1
A29: HOSPITAL NAVAL TALCAHUANO A.A. | P29: 1 | R29: =SUM(C29:Q29) -> 1
A30: HOSPITAL SAN JOSE DE CORONEL | M30: 1 | R30: =SUM(C30:Q30) -> 1
A31: HOSPITAL TRAUMATOLOGICO DE CONCEPCION | R31: =SUM(C31:Q31) -> 0
A32: I MUNICIPALIDAD DE ANGOL | G32: 1 | R32: =SUM(C32:Q32) -> 1
A33: I MUNICIPALIDAD DE CABRERO DEPARTAMENTO DE SALUD | G33: 1 | R33: =SUM(C33:Q33) -> 1
A34: I MUNICIPALIDAD DE CORONEL DPTO ADMINIST | M34: 1 | R34: =SUM(C34:Q34) -> 1
A35: I MUNICIPALIDAD DE LOTA DEPARTAMENTO DE SALUD | M35: 1 | R35: =SUM(C35:Q35) -> 1
A36: I MUNICIPALIDAD DE TALCAHUANO | P36: 1 | R36: =SUM(C36:Q36) -> 1
A37: ILUSTRE MUNICIPALIDAD DE CHIGUAYANTE | K37: 1 | R37: =SUM(C37:Q37) -> 1
A38: ILUSTRE MUNICIPALIDAD DE CHILLAN DPTO SALUD | F38: 1 | R38: =SUM(C38:Q38) -> 1
A39: ILUSTRE MUNICIPALIDAD DE CHILLAN VIEJO | E39: 1 | H39: 2 | I39: 1 | R39: =SUM(C39:Q39) -> 4
A40: MUNICIPALIDAD DE CONCEPCION | R40: =SUM(C40:Q40) -> 0
A41: MUNICIPALIDAD DE HUALPEN | P41: 1 | R41: =SUM(C41:Q41) -> 1
A42: MUNICIPALIDAD DE LOS ANGELES | R42: =SUM(C42:Q42) -> 0
A43: Total general | C43: =SUM(C4:C42) -> 4 | D43: =SUM(D4:D42) -> 4 | E43: =SUM(E4:E42) -> 2 | F43: =SUM(F4:F42) -> 2 | G43: =SUM(G4:G42) -> 3 | H43: =SUM(H4:H42) -> 3 | I43: =SUM(I4:I42) -> 1 | J43: =SUM(J4:J42) -> 1 | ... Q43: =SUM(Q4:Q42) -> 2 | R43: =SUM(C43:Q43) -> 38

Sheet clientes no en sap
A1: 45008673 | B1: CLAUDIO ALVAREZ URRA | C1: SANTIAGO | D1: 13 | E1: ATENCION TELEFONICA | F1: ="CN"&LEFT(Tabla13[[#This Row],[RUT]],LEN(Tabla13[[#This Row],[RUT]]-1)) -> #VALUE! | G1: PRIVADO | H1: ATEL | I1: REGIÓN DE METROPOLITANA DE SANTIAGO
A2: 118464397 | B2: CARLOS IGNACIO ARANCIBIA BARRENECHEA | C2: SANTIAGO | D2: 13 | E2: ATENCION TELEFONICA | F2: ="CN"&LEFT(Tabla13[[#This Row],[RUT]],LEN(Tabla13[[#This Row],[RUT]])-1) -> CN3517865 | G2: PRIVADO | H2: ATEL | I2: REGIÓN DE METROPOLITANA DE SANTIAGO
A3: 602020002 | B3: CAMARA DE DIPUTADOS DE CHILE | C3: VALPARAÍSO | D3: 5 | E3: ATENCION TELEFONICA | F3: ="CN"&LEFT(Tabla13[[#This Row],[RUT]],LEN(Tabla13[[#This Row],[RUT]])-1) -> CN3753123 | G3: PÚBLICO | H3: ATEL | I3: REGIÓN DE VALPARAÍSO
A4: 611021275 | B4: CENTRO DE INSTRUCCION Y CAPACITACION MARITIMA | C4: VALPARAÍSO | D4: 5 | E4: ATENCION TELEFONICA | F4: ="CN"&LEFT(Tabla13[[#This Row],[RUT]],LEN(Tabla13[[#This Row],[RUT]])-1) -> CN4500867 | G4: PRIVADO | H4: ATEL | I4: REGIÓN DE VALPARAÍSO
A5: 611030215 | B5: Ivª Brigada Aérea | C5: PUNTA ARENAS | D5: 12 | E5: ATENCION TELEFONICA | F5: ="CN"&LEFT(Tabla13[[#This Row],[RUT]],LEN(Tabla13[[#This Row],[RUT]])-1) -> CN5077288 | G5: PÚBLICO | H5: ATEL | I5: REGIÓN DE MAGALLANES Y DE LA ANTÁRTICA CHILENA
A6: 619742001 | B6: EJERCITO DE CHILE | C6: SANTIAGO | D6: 13 | E6: ATENCION TELEFONICA | F6: ="CN"&LEFT(Tabla13[[#This Row],[RUT]],LEN(Tabla13[[#This Row],[RUT]])-1) -> CN5320819 | G6: PÚBLICO | H6: ATEL | I6: REGIÓN DE METROPOLITANA DE SANTIAGO
A7: 619992806 | B7: CENTRO DE FORMACION TECNICA DE LA REGION DE COQUIMBO | C7: COQUIMBO | D7: 4 | E7: ATENCION TELEFONICA | F7: ="CN"&LEFT(Tabla13[[#This Row],[RUT]],LEN(Tabla13[[#This Row],[RUT]])-1) -> CN6389002 | G7: PRIVADO | H7: ATEL | I7: REGIÓN DE COQUIMBO
A8: 620008907 | B8: Servicio Nacional De Protección Especializada A La Niñez Y Adolescenci | C8: CONCEPCIÓN | D8: 8 | E8: ATENCION TELEFONICA | F8: ="CN"&LEFT(Tabla13[[#This Row],[RUT]],LEN(Tabla13[[#This Row],[RUT]])-1) -> CN6412721 | G8: PÚBLICO | H8: ATEL | I8: REGIÓN DE BIOBÍO
A9: 651455669 | B9: COLEGIO AMERICANO CE | C9: LA SERENA | D9: 4 | E9: ATENCION TELEFONICA | F9: ="CN"&LEFT(Tabla13[[#This Row],[RUT]],LEN(Tabla13[[#This Row],[RUT]])-1) -> CN6490320 | G9: PRIVADO | H9: ATEL | I9: REGIÓN DE COQUIMBO
A10: 651543983 | B10: CENTRO DE FORMACION TECNICA DE LA REGION DE TARAPA | C10: IQUIQUE | D10: 1 | E10: ATENCION TELEFONICA | F10: ="CN"&LEFT(Tabla13[[#This Row],[RUT]],LEN(Tabla13[[#This Row],[RUT]])-1) -> CN7303109 | G10: PRIVADO | H10: ATEL | I10: REGIÓN DE TARAPACÁ
A11: 651654114 | B11: CENTRO DE FORMACION TECNICA ESTATAL DE LA REGION DE VALPARAISO | C11: VIÑA DEL MAR | D11: 5 | E11: ATENCION TELEFONICA | F11: ="CN"&LEFT(Tabla13[[#This Row],[RUT]],LEN(Tabla13[[#This Row],[RUT]])-1) -> CN7918692 | G11: PÚBLICO | H11: ATEL | I11: REGIÓN DE VALPARAÍSO
A12: 654556504 | B12: Ejercito De Chile | C12: ANTOFAGASTA | D12: 2 | E12: ATENCION TELEFONICA | F12: ="CN"&LEFT(Tabla13[[#This Row],[RUT]],LEN(Tabla13[[#This Row],[RUT]])-1) -> CN8181832 | G12: PÚBLICO | H12: ATEL | I12: REGIÓN DE ANTOFAGASTA
A13: 692532007 | B13: I Municipalidad De Sierra Gorda | C13: SIERRA GORDA | D13: 2 | E13: ATENCION TELEFONICA | F13: ="CN"&LEFT(Tabla13[[#This Row],[RUT]],LEN(Tabla13[[#This Row],[RUT]])-1) -> CN8185029 | G13: PÚBLICO | H13: ATEL | I13: REGIÓN DE ANTOFAGASTA
... A32: 995240300 | B32: CENTRO RENAL SPA | C32: QUILPUÉ | D32: 5 | E32: ATENCION TELEFONICA | F32: ="CN"&LEFT(Tabla13[[#This Row],[RUT]],LEN(Tabla13[[#This Row],[RUT]])-1) -> CN23645146 | G32: PRIVADO | H32: ATEL | I32: REGIÓN DE VALPARAÍSO
A33: 61102004K | B33: Dirección De Abastecimiento De La Armada | C33: ALGARROBO | D33: 5 | E33: ATENCION TELEFONICA | F33: ="CN"&LEFT(Tabla13[[#This Row],[RUT]],LEN(Tabla13[[#This Row],[RUT]])-1) -> CN25952636 | G33: PRIVADO | H33: ATEL | I33: REGIÓN DE VALPARAÍSO
A34: 77326113K | B34: CLINICA DENTAL ROJOS SPA | C34: COPIAPÓ | D34: 3 | E34: ATENCION TELEFONICA | F34: ="CN"&LEFT(Tabla13[[#This Row],[RUT]],LEN(Tabla13[[#This Row],[RUT]])-1) -> CN59077290 | G34: PRIVADO | H34: ATEL | I34: REGIÓN DE ATACAMA
A35: 77849650K | B35: CLINICA Y CENTRO MEDICO DELGADO LTDA | C35: SANTIAGO | D35: 13 | E35: ATENCION TELEFONICA | F35: ="CN"&LEFT(Tabla13[[#This Row],[RUT]],LEN(Tabla13[[#This Row],[RUT]])-1) -> CN60103000 | G35: PRIVADO | H35: ATEL | I35: REGIÓN DE METROPOLITANA DE SANTIAGO
A36: 78464300K | B36: COMERCIAL SERVICOPIER SPA | C36: SANTIAGO | D36: 13 | E36: ATENCION TELEFONICA | F36: ="CN"&LEFT(Tabla13[[#This Row],[RUT]],LEN(Tabla13[[#This Row],[RUT]])-1) -> CN60202000 | G36: PRIVADO | H36: ATEL | I36: REGIÓN DE METROPOLITANA DE SANTIAGO
A37: 774097899 | B37: CALEMA SPA | C37: SANTIAGO | D37: 13 | E37: ATENCION TELEFONICA | F37: ="CN"&LEFT(Tabla13[[#This Row],[RUT]],LEN(Tabla13[[#This Row],[RUT]])-1) -> CN60506000 | G37: PRIVADO | H37: ATEL | I37: REGIÓN DE METROPOLITANA DE SANTIAGO

Sheet CARTERA 2025
A1: RUT | B1: RAZON | C1: COMUNA | D1: REGION | E1: VENDEDOR | F1: COD CLIENTE | G1: INDUSTRIA | H1: SECTOR | I1: CARTERA | J1: REGION NOMBRE
A2: 35178651 | B2: FRANCISCO CAMPOS SANHUEZA | D2: 13 | E2: ATENCION TELEFONICA | F2: CN3517865 | I2: =IF(Tabla13[[#This Row],[RUT]]=774097899,"DIST",_xlfn.XLOOKUP(Tabla13[[#This Row],[VENDEDOR]],dimensiones!$C$21:$C$28,dimensiones!$D$21:$D$28,"")) -> ATEL | J2: =_xlfn.XLOOKUP(Tabla13[[#This Row],[REGION]],dimensiones!C:C,dimensiones!D:D,"") -> Región de Metropolitana de Santiago
A3: 37531235 | B3: ANA ABURDENE | D3: 16 | E3: ATENCION TELEFONICA | F3: CN3753123 | I3: =IF(Tabla13[[#This Row],[RUT]]=774097899,"DIST",_xlfn.XLOOKUP(Tabla13[[#This Row],[VENDEDOR]],dimensiones!$C$21:$C$28,dimensiones!$D$21:$D$28,"")) -> ATEL | J3: =_xlfn.XLOOKUP(Tabla13[[#This Row],[REGION]],dimensiones!C:C,dimensiones!D:D,"") -> Región de Ñuble
A4: 45008673 | B4: CLAUDIO ALVAREZ URRA | C4: SANTIAGO | D4: 13 | E4: ATENCION TELEFONICA | F4: CN4500867 | H4: PRIVADO | I4: =IF(Tabla13[[#This Row],[RUT]]=774097899,"DIST",_xlfn.XLOOKUP(Tabla13[[#This Row],[VENDEDOR]],dimensiones!$C$21:$C$28,dimensiones!$D$21:$D$28,"")) -> ATEL | J4: =_xlfn.XLOOKUP(Tabla13[[#This Row],[REGION]],dimensiones!C:C,dimensiones!D:D,"") -> Región de Metropolitana de Santiago
A5: 50772888 | B5: TERESA DE JESUS ANDRADE ZELADA | D5: 13 | E5: ATENCION TELEFONICA | F5: CN5077288 | I5: =IF(Tabla13[[#This Row],[RUT]]=774097899,"DIST",_xlfn.XLOOKUP(Tabla13[[#This Row],[VENDEDOR]],dimensiones!$C$21:$C$28,dimensiones!$D$21:$D$28,"")) -> ATEL | J5: =_xlfn.XLOOKUP(Tabla13[[#This Row],[REGION]],dimensiones!C:C,dimensiones!D:D,"") -> Región de Metropolitana de Santiago
A6: 53208193 | B6: BELARMINO SEGUNDO DONOSO FUENTES | D6: 13 | E6: ATENCION TELEFONICA | F6: CN5320819 | I6: =IF(Tabla13[[#This Row],[RUT]]=774097899,"DIST",_xlfn.XLOOKUP(Tabla13[[#This Row],[VENDEDOR]],dimensiones!$C$21:$C$28,dimensiones!$D$21:$D$28,"")) -> ATEL | J6: =_xlfn.XLOOKUP(Tabla13[[#This Row],[REGION]],dimensiones!C:C,dimensiones!D:D,"") -> Región de Metropolitana de Santiago
A7: 63890022 | B7: ELIAS CORDOVA RUIZ | D7: 4 | E7: ATENCION TELEFONICA | F7: CN6389002 | I7: =IF(Tabla13[[#This Row],[RUT]]=774097899,"DIST",_xlfn.XLOOKUP(Tabla13[[#This Row],[VENDEDOR]],dimensiones!$C$21:$C$28,dimensiones!$D$21:$D$28,"")) -> ATEL | J7: =_xlfn.XLOOKUP(Tabla13[[#This Row],[REGION]],dimensiones!C:C,dimensiones!D:D,"") -> Región de Coquimbo
A8: 64127217 | B8: DOCTOR SERGIO MAYORGA CIOCCA | D8: 13 | E8: ATENCION TELEFONICA | F8: CN6412721 | I8: =IF(Tabla13[[#This Row],[RUT]]=774097899,"DIST",_xlfn.XLOOKUP(Tabla13[[#This Row],[VENDEDOR]],dimensiones!$C$21:$C$28,dimensiones!$D$21:$D$28,"")) -> ATEL | J8: =_xlfn.XLOOKUP(Tabla13[[#This Row],[REGION]],dimensiones!C:C,dimensiones!D:D,"") -> Región de Metropolitana de Santiago
A9: 64903209 | B9: VICTOR MANUEL BORJE ARAYA | D9: 13 | E9: ATENCION TELEFONICA | F9: CN6490320 | I9: =IF(Tabla13[[#This Row],[RUT]]=774097899,"DIST",_xlfn.XLOOKUP(Tabla13[[#This Row],[VENDEDOR]],dimensiones!$C$21:$C$28,dimensiones!$D$21:$D$28,"")) -> ATEL | J9: =_xlfn.XLOOKUP(Tabla13[[#This Row],[REGION]],dimensiones!C:C,dimensiones!D:D,"") -> Región de Metropolitana de Santiago
A10: 73031095 | B10: JUAN A. RAMIREZ CASTILLO | D10: 9 | E10: ATENCION TELEFONICA | F10: CN7303109 | I10: =IF(Tabla13[[#This Row],[RUT]]=774097899,"DIST",_xlfn.XLOOKUP(Tabla13[[#This Row],[VENDEDOR]],dimensiones!$C$21:$C$28,dimensiones!$D$21:$D$28,"")) -> ATEL | J10: =_xlfn.XLOOKUP(Tabla13[[#This Row],[REGION]],dimensiones!C:C,dimensiones!D:D,"") -> Región de La Araucanía
A11: 79186929 | B11: MANUEL EDUARDO VIDAL BARRIA | D11: 8 | E11: ATENCION TELEFONICA | F11: CN7918692 | I11: =IF(Tabla13[[#This Row],[RUT]]=774097899,"DIST",_xlfn.XLOOKUP(Tabla13[[#This Row],[VENDEDOR]],dimensiones!$C$21:$C$28,dimensiones!$D$21:$D$28,"")) -> ATEL | J11: =_xlfn.XLOOKUP(Tabla13[[#This Row],[REGION]],dimensiones!C:C,dimensiones!D:D,"") -> Región de Biobío
A12: 81818320 | B12: LEOCADIA GONZALEZ TORO | D12: 14 | E12: ATENCION TELEFONICA | F12: CN8181832 | I12: =IF(Tabla13[[#This Row],[RUT]]=774097899,"DIST",_xlfn.XLOOKUP(Tabla13[[#This Row],[VENDEDOR]],dimensiones!$C$21:$C$28,dimensiones!$D$21:$D$28,"")) -> ATEL | J12: =_xlfn.XLOOKUP(Tabla13[[#This Row],[REGION]],dimensiones!C:C,dimensiones!D:D,"") -> Región de Los Ríos
A13: 81850291 | B13: ISABEL LEIVA FUENTEALBA | D13: 16 | E13: ATENCION TELEFONICA | F13: CN8185029 | I13: =IF(Tabla13[[#This Row],[RUT]]=774097899,"DIST",_xlfn.XLOOKUP(Tabla13[[#This Row],[VENDEDOR]],dimensiones!$C$21:$C$28,dimensiones!$D$21:$D$28,"")) -> ATEL | J13: =_xlfn.XLOOKUP(Tabla13[[#This Row],[REGION]],dimensiones!C:C,dimensiones!D:D,"") -> Región de Ñuble
A14: 81853363 | B14: ARTURO GUTIERREZ RUBILAR | D14: 9 | E14: ATENCION TELEFONICA | F14: CN8185336 | I14: =IF(Tabla13[[#This Row],[RUT]]=774097899,"DIST",_xlfn.XLOOKUP(Tabla13[[#This Row],[VENDEDOR]],dimensiones!$C$21:$C$28,dimensiones!$D$21:$D$28,"")) -> ATEL | J14: =_xlfn.XLOOKUP(Tabla13[[#This Row],[REGION]],dimensiones!C:C,dimensiones!D:D,"") -> Región de La Araucanía
A15: 88248228 | B15: ERIKA IVONNE CACERES PAVEZ | D15: 13 | E15: ATENCION TELEFONICA | F15: CN8824822 | I15: =IF(Tabla13[[#This Row],[RUT]]=774097899,"DIST",_xlfn.XLOOKUP(Tabla13[[#This Row],[VENDEDOR]],dimensiones!$C$21:$C$28,dimensiones!$D$21:$D$28,"")) -> ATEL | J15: =_xlfn.XLOOKUP(Tabla13[[#This Row],[REGION]],dimensiones!C:C,dimensiones!D:D,"") -> Región de Metropolitana de Santiago
A16: 91511959 | B16: FRANCISCO JAVIER PARDO QUIROZ | D16: 13 | E16: ATENCION TELEFONICA | F16: CN9151195 | I16: =IF(Tabla13[[#This Row],[RUT]]=774097899,"DIST",_xlfn.XLOOKUP(Tabla13[[#This Row],[VENDEDOR]],dimensiones!$C$21:$C$28,dimensiones!$D$21:$D$28,"")) -> ATEL | J16: =_xlfn.XLOOKUP(Tabla13[[#This Row],[REGION]],dimensiones!C:C,dimensiones!D:D,"") -> Región de Metropolitana de Santiago
... A19: 106711038 | B19: ROSA BURGOS DOMINGUEZ | D19: 3 | E19: ATENCION TELEFONICA | F19: CN10671103 | I19: =IF(Tabla13[[#This Row],[RUT]]=774097899,"DIST",_xlfn.XLOOKUP(Tabla13[[#This Row],[VENDEDOR]],dimensiones!$C$21:$C$28,dimensiones!$D$21:$D$28,"")) -> ATEL | J19: =_xlfn.XLOOKUP(Tabla13[[#This Row],[REGION]],dimensiones!C:C,dimensiones!D:D,"") -> Región de Atacama
A20: 118464397 | B20: CARLOS IGNACIO ARANCIBIA BARRENECHEA | C20: SANTIAGO | D20: 13 | E20: ATENCION TELEFONICA | F20: CN11846439 | H20: PRIVADO | I20: =IF(Tabla13[[#This Row],[RUT]]=774097899,"DIST",_xlfn.XLOOKUP(Tabla13[[#This Row],[VENDEDOR]],dimensiones!$C$21:$C$28,dimensiones!$D$21:$D$28,"")) -> ATEL | J20: =_xlfn.XLOOKUP(Tabla13[[#This Row],[REGION]],dimensiones!C:C,dimensiones!D:D,"") -> Región de Metropolitana de Santiago
A21: 118726197 | B21: PAULA ANDREA RIVERA BRUNET | D21: 8 | E21: ATENCION TELEFONICA | F21: CN11872619 | I21: =IF(Tabla13[[#This Row],[RUT]]=774097899,"DIST",_xlfn.XLOOKUP(Tabla13[[#This Row],[VENDEDOR]],dimensiones!$C$21:$C$28,dimensiones!$D$21:$D$28,"")) -> ATEL | J21: =_xlfn.XLOOKUP(Tabla13[[#This Row],[REGION]],dimensiones!C:C,dimensiones!D:D,"") -> Región de Biobío
A22: 121317834 | B22: HECTOR CARRENO BAEZA | D22: 13 | E22: ATENCION TELEFONICA | F22: CN12131783 | I22: =IF(Tabla13[[#This Row],[RUT]]=774097899,"DIST",_xlfn.XLOOKUP(Tabla13[[#This Row],[VENDEDOR]],dimensiones!$C$21:$C$28,dimensiones!$D$21:$D$28,"")) -> ATEL | J22: =_xlfn.XLOOKUP(Tabla13[[#This Row],[REGION]],dimensiones!C:C,dimensiones!D:D,"") -> Región de Metropolitana de Santiago
A23: 122836576 | B23: MARGARITA RAILEN | D23: 13 | E23: ATENCION TELEFONICA | F23: CN12283657 | I23: =IF(Tabla13[[#This Row],[RUT]]=774097899,"DIST",_xlfn.XLOOKUP(Tabla13[[#This Row],[VENDEDOR]],dimensiones!$C$21:$C$28,dimensiones!$D$21:$D$28,"")) -> ATEL | J23: =_xlfn.XLOOKUP(Tabla13[[#This Row],[REGION]],dimensiones!C:C,dimensiones!D:D,"") -> Región de Metropolitana de Santiago
A24: 150855403 | B24: ANDRES REYES | D24: 5 | E24: ATENCION TELEFONICA | F24: CN15085540 | I24: =IF(Tabla13[[#This Row],[RUT]]=774097899,"DIST",_xlfn.XLOOKUP(Tabla13[[#This Row],[VENDEDOR]],dimensiones!$C$21:$C$28,dimensiones!$D$21:$D$28,"")) -> ATEL | J24: =_xlfn.XLOOKUP(Tabla13[[#This Row],[REGION]],dimensiones!C:C,dimensiones!D:D,"") -> Región de Valparaíso
A25: 161447579 | B25: IVAN CARLOS CANDIA ALDAY | D25: 13 | E25: ATENCION TELEFONICA | F25: CN16144757 | I25: =IF(Tabla13[[#This Row],[RUT]]=774097899,"DIST",_xlfn.XLOOKUP(Tabla13[[#This Row],[VENDEDOR]],dimensiones!$C$21:$C$28,dimensiones!$D$21:$D$28,"")) -> ATEL | J25: =_xlfn.XLOOKUP(Tabla13[[#This Row],[REGION]],dimensiones!C:C,dimensiones!D:D,"") -> Región de Metropolitana de Santiago
A26: 165289676 | B26: MARCO ANTONIO ALBORNOZ SOTO | D26: 6 | E26: ATENCION TELEFONICA | F26: CN16528967 | I26: =IF(Tabla13[[#This Row],[RUT]]=774097899,"DIST",_xlfn.XLOOKUP(Tabla13[[#This Row],[VENDEDOR]],dimensiones!$C$21:$C$28,dimensiones!$D$21:$D$28,"")) -> ATEL | J26: =_xlfn.XLOOKUP(Tabla13[[#This Row],[REGION]],dimensiones!C:C,dimensiones!D:D,"") -> Región de Libertador General Bernardo O'Higgins
A27: 173054734 | B27: ANDREA LUPAYANTE LUPAYÀNTE | D27: 13 | E27: ATENCION TELEFONICA | F27: CN17305473 | I27: =IF(Tabla13[[#This Row],[RUT]]=774097899,"DIST",_xlfn.XLOOKUP(Tabla13[[#This Row],[VENDEDOR]],dimensiones!$C$21:$C$28,dimensiones!$D$21:$D$28,"")) -> ATEL | J27: =_xlfn.XLOOKUP(Tabla13[[#This Row],[REGION]],dimensiones!C:C,dimensiones!D:D,"") -> Región de Metropolitana de Santiago
A28: 176056827 | B28: JUAN ANDRES DIAZ GOMEZ | D28: 8 | E28: ATENCION TELEFONICA | F28: CN17605682 | I28: =IF(Tabla13[[#This Row],[RUT]]=774097899,"DIST",_xlfn.XLOOKUP(Tabla13[[#This Row],[VENDEDOR]],dimensiones!$C$21:$C$28,dimensiones!$D$21:$D$28,"")) -> ATEL | J28: =_xlfn.XLOOKUP(Tabla13[[#This Row],[REGION]],dimensiones!C:C,dimensiones!D:D,"") -> Región de Biobío
A29: 176445467 | B29: HUMBERTO MIERES MORALES | D29: 13 | E29: ATENCION TELEFONICA | F29: CN17644546 | I29: =IF(Tabla13[[#This Row],[RUT]]=774097899,"DIST",_xlfn.XLOOKUP(Tabla13[[#This Row],[VENDEDOR]],dimensiones!$C$21:$C$28,dimensiones!$D$21:$D$28,"")) -> ATEL | J29: =_xlfn.XLOOKUP(Tabla13[[#This Row],[REGION]],dimensiones!C:C,dimensiones!D:D,"") -> Región de Metropolitana de Santiago
A30: 180567933 | B30: LEONARDO QUEZADA VERGARA | D30: 13 | E30: ATENCION TELEFONICA | F30: CN18056793 | I30: =IF(Tabla13[[#This Row],[RUT]]=774097899,"DIST",_xlfn.XLOOKUP(Tabla13[[#This Row],[VENDEDOR]],dimensiones!$C$21:$C$28,dimensiones!$D$21:$D$28,"")) -> ATEL | J30: =_xlfn.XLOOKUP(Tabla13[[#This Row],[REGION]],dimensiones!C:C,dimensiones!D:D,"") -> Región de Metropolitana de Santiago
A31: 188563619 | B31: JAVIER EDUARDO FLORES GOMEZ | D31: 3 | E31: ATENCION TELEFONICA | F31: CN18856361 | I31: =IF(Tabla13[[#This Row],[RUT]]=774097899,"DIST",_xlfn.XLOOKUP(Tabla13[[#This Row],[VENDEDOR]],dimensiones!$C$21:$C$28,dimensiones!$D$21:$D$28,"")) -> ATEL | J31: =_xlfn.XLOOKUP(Tabla13[[#This Row],[REGION]],dimensiones!C:C,dimensiones!D:D,"") -> Región de Atacama
A32: 236451461 | B32: ANA MARIA TICONA APANA | D32: 13 | E32: ATENCION TELEFONICA | F32: CN23645146 | I32: =IF(Tabla13[[#This Row],[RUT]]=774097899,"DIST",_xlfn.XLOOKUP(Tabla13[[#This Row],[VENDEDOR]],dimensiones!$C$21:$C$28,dimensiones!$D$21:$D$28,"")) -> ATEL | J32: =_xlfn.XLOOKUP(Tabla13[[#This Row],[REGION]],dimensiones!C:C,dimensiones!D:D,"") -> Región de Metropolitana de Santiago
... A35: 601030004 | B35: SUBSECRETARIA DE SERVICIOS SOCIALES | D35: 13 | E35: ATENCION TELEFONICA | F35: CN60103000 | I35: =IF(Tabla13[[#This Row],[RUT]]=774097899,"DIST",_xlfn.XLOOKUP(Tabla13[[#This Row],[VENDEDOR]],dimensiones!$C$21:$C$28,dimensiones!$D$21:$D$28,"")) -> ATEL | J35: =_xlfn.XLOOKUP(Tabla13[[#This Row],[REGION]],dimensiones!C:C,dimensiones!D:D,"") -> Región de Metropolitana de Santiago
A36: 602020002 | B36: CAMARA DE DIPUTADOS DE CHILE | C36: VALPARAÍSO | D36: 5 | E36: ATENCION TELEFONICA | F36: CN60202000 | H36: PÚBLICO | I36: =IF(Tabla13[[#This Row],[RUT]]=774097899,"DIST",_xlfn.XLOOKUP(Tabla13[[#This Row],[VENDEDOR]],dimensiones!$C$21:$C$28,dimensiones!$D$21:$D$28,"")) -> ATEL | J36: =_xlfn.XLOOKUP(Tabla13[[#This Row],[REGION]],dimensiones!C:C,dimensiones!D:D,"") -> Región de Valparaíso
A37: 605060005 | B37: POLICIA DE INVESTIGACIONES DE CHILE | D37: 10 | E37: ATENCION TELEFONICA | F37: CN60506000 | I37: =IF(Tabla13[[#This Row],[RUT]]=774097899,"DIST",_xlfn.XLOOKUP(Tabla13[[#This Row],[VENDEDOR]],dimensiones!$C$21:$C$28,dimensiones!$D$21:$D$28,"")) -> ATEL | J37: =_xlfn.XLOOKUP(Tabla13[[#This Row],[REGION]],dimensiones!C:C,dimensiones!D:D,"") -> Región de Los Lagos
A38: 605060129 | B38: ESCUELA DE INVESTIGACIONES POLICIALES (ESCIPOL) | D38: 13 | E38: ATENCION TELEFONICA | F38: CN60506012 | I38: =IF(Tabla13[[#This Row],[RUT]]=774097899,"DIST",_xlfn.XLOOKUP(Tabla13[[#This Row],[VENDEDOR]],dimensiones!$C$21:$C$28,dimensiones!$D$21:$D$28,"")) -> ATEL | J38: =_xlfn.XLOOKUP(Tabla13[[#This Row],[REGION]],dimensiones!C:C,dimensiones!D:D,"") -> Región de Metropolitana de Santiago
A39: 605111300 | B39: INTENDENCIA REGION METROPOLITANA | D39: 13 | E39: ATENCION TELEFONICA | F39: CN60511130 | I39: =IF(Tabla13[[#This Row],[RUT]]=774097899,"DIST",_xlfn.XLOOKUP(Tabla13[[#This Row],[VENDEDOR]],dimensiones!$C$21:$C$28,dimensiones!$D$21:$D$28,"")) -> ATEL | J39: =_xlfn.XLOOKUP(Tabla13[[#This Row],[REGION]],dimensiones!C:C,dimensiones!D:D,"") -> Región de Metropolitana de Santiago
A40: 609020636 | B40: ILUSTRE MUNICIPALIDAD DE LINARES | D40: 7 | E40: ATENCION TELEFONICA | F40: CN60902063 | I40: =IF(Tabla13[[#This Row],[RUT]]=774097899,"DIST",_xlfn.XLOOKUP(Tabla13[[#This Row],[VENDEDOR]],dimensiones!$C$21:$C$28,dimensiones!$D$21:$D$28,"")) -> ATEL | J40: =_xlfn.XLOOKUP(Tabla13[[#This Row],[REGION]],dimensiones!C:C,dimensiones!D:D,"") -> Región de Maule
A41: 609050004 | B41: SERVICIO NACIONAL DEL PATRIMONIO CULTURAL | D41: 4 | E41: ATENCION TELEFONICA | F41: CN60905000 | I41: =IF(Tabla13[[#This Row],[RUT]]=774097899,"DIST",_xlfn.XLOOKUP(Tabla13[[#This Row],[VENDEDOR]],dimensiones!$C$21:$C$28,dimensiones!$D$21:$D$28,"")) -> ATEL | J41: =_xlfn.XLOOKUP(Tabla13[[#This Row],[REGION]],dimensiones!C:C,dimensiones!D:D,"") -> Región de Coquimbo
A42: 609100478 | B42: UNIVERSIDAD METROPOLITANA DE CIENCIAS DE LA EDUCACION | D42: 13 | E42: ATENCION TELEFONICA | F42: CN60910047 | I42: =IF(Tabla13[[#This Row],[RUT]]=774097899,"DIST",_xlfn.XLOOKUP(Tabla13[[#This Row],[VENDEDOR]],dimensiones!$C$21:$C$28,dimensiones!$D$21:$D$28,"")) -> ATEL | J42: =_xlfn.XLOOKUP(Tabla13[[#This Row],[REGION]],dimensiones!C:C,dimensiones!D:D,"") -> Región de Metropolitana de Santiago
A43: 609110066 | B43: UNIVERSIDAD DEL BIO BIO | D43: 8 | E43: ATENCION TELEFONICA | F43: CN60911006 | I43: =IF(Tabla13[[#This Row],[RUT]]=774097899,"DIST",_xlfn.XLOOKUP(Tabla13[[#This Row],[VENDEDOR]],dimensiones!$C$21:$C$28,dimensiones!$D$21:$D$28,"")) -> ATEL | J43: =_xlfn.XLOOKUP(Tabla13[[#This Row],[REGION]],dimensiones!C:C,dimensiones!D:D,"") -> Región de Biobío
A44: 610040071 | B44: DIRECCION REGIONAL DE GENDARMERIA - ANTOFAGASTA | D44: 2 | E44: ATENCION TELEFONICA | F44: CN61004007 | I44: =IF(Tabla13[[#This Row],[RUT]]=774097899,"DIST",_xlfn.XLOOKUP(Tabla13[[#This Row],[VENDEDOR]],dimensiones!$C$21:$C$28,dimensiones!$D$21:$D$28,"")) -> ATEL | J44: =_xlfn.XLOOKUP(Tabla13[[#This Row],[REGION]],dimensiones!C:C,dimensiones!D:D,"") -> Región de Antofagasta
A45: 610040519 | B45: DIRECCION REGIONAL DE GENDARMERIA VII REGION DEL MAULE | D45: 7 | E45: ATENCION TELEFONICA | F45: CN61004051 | I45: =IF(Tabla13[[#This Row],[RUT]]=774097899,"DIST",_xlfn.XLOOKUP(Tabla13[[#This Row],[VENDEDOR]],dimensiones!$C$21:$C$28,dimensiones!$D$21:$D$28,"")) -> ATEL | J45: =_xlfn.XLOOKUP(Tabla13[[#This Row],[REGION]],dimensiones!C:C,dimensiones!D:D,"") -> Región de Maule
A46: 610040985 | B46: DIRECCION REGIONAL DE GENDARMERIA - PUERTO MONTT | D46: 10 | E46: ATENCION TELEFONICA | F46: CN61004098 | I46: =IF(Tabla13[[#This Row],[RUT]]=774097899,"DIST",_xlfn.XLOOKUP(Tabla13[[#This Row],[VENDEDOR]],dimensiones!$C$21:$C$28,dimensiones!$D$21:$D$28,"")) -> ATEL | J46: =_xlfn.XLOOKUP(Tabla13[[#This Row],[REGION]],dimensiones!C:C,dimensiones!D:D,"") -> Región de Los Lagos
A47: 611010176 | B47: ESCUELA MILITAR -ESCMIL | D47: 13 | E47: ATENCION TELEFONICA | F47: CN61101017 | I47: =IF(Tabla13[[#This Row],[RUT]]=774097899,"DIST",_xlfn.XLOOKUP(Tabla13[[#This Row],[VENDEDOR]],dimensiones!$C$21:$C$28,dimensiones!$D$21:$D$28,"")) -> ATEL | J47: =_xlfn.XLOOKUP(Tabla13[[#This Row],[REGION]],dimensiones!C:C,dimensiones!D:D,"") -> Región de Metropolitana de Santiago
A48: 611021275 | B48: CENTRO DE INSTRUCCION Y CAPACITACION MARITIMA | C48: VALPARAÍSO | D48: 5 | E48: ATENCION TELEFONICA | F48: CN61102127 | H48: PRIVADO | I48: =IF(Tabla13[[#This Row],[RUT]]=774097899,"DIST",_xlfn.XLOOKUP(Tabla13[[#This Row],[VENDEDOR]],dimensiones!$C$21:$C$28,dimensiones!$D$21:$D$28,"")) -> ATEL | J48: =_xlfn.XLOOKUP(Tabla13[[#This Row],[REGION]],dimensiones!C:C,dimensiones!D:D,"") -> Región de Valparaíso
A49: 611030207 | B49: FUERZA AEREA DE CHILE | D49: 10 | E49: ATENCION TELEFONICA | F49: CN61103020 | I49: =IF(Tabla13[[#This Row],[RUT]]=774097899,"DIST",_xlfn.XLOOKUP(Tabla13[[#This Row],[VENDEDOR]],dimensiones!$C$21:$C$28,dimensiones!$D$21:$D$28,"")) -> ATEL | J49: =_xlfn.XLOOKUP(Tabla13[[#This Row],[REGION]],dimensiones!C:C,dimensiones!D:D,"") -> Región de Los Lagos
A50: 611030215 | B50: IVª BRIGADA AEREA | C50: PUNTA ARENAS | E50: ATENCION TELEFONICA | F50: CN61103021 | H50: PÚBLICO | I50: =IF(Tabla13[[#This Row],[RUT]]=774097899,"DIST",_xlfn.XLOOKUP(Tabla13[[#This Row],[VENDEDOR]],dimensiones!$C$21:$C$28,dimensiones!$D$21:$D$28,"")) -> ATEL | J50: =_xlfn.XLOOKUP(Tabla13[[#This Row],[REGION]],dimensiones!C:C,dimensiones!D:D,"")
A51: 611030223 | B51: REGIMIENTO DE ARTILLERIA ANTIAEREA Y FUERZAS ESPECIALES | D51: 5 | E51: ATENCION TELEFONICA | F51: CN61103022 | I51: =IF(Tabla13[[#This Row],[RUT]]=774097899,"DIST",_xlfn.XLOOKUP(Tabla13[[#This Row],[VENDEDOR]],dimensiones!$C$21:$C$28,dimensiones!$D$21:$D$28,"")) -> ATEL | J51: =_xlfn.XLOOKUP(Tabla13[[#This Row],[REGION]],dimensiones!C:C,dimensiones!D:D,"") -> Región de Valparaíso
A52: 611030231 | B52: 1A BRIGADA AEREA | D52: 1 | E52: ATENCION TELEFONICA | F52: CN61103023 | I52: =IF(Tabla13[[#This Row],[RUT]]=774097899,"DIST",_xlfn.XLOOKUP(Tabla13[[#This Row],[VENDEDOR]],dimensiones!$C$21:$C$28,dimensiones!$D$21:$D$28,"")) -> ATEL | J52: =_xlfn.XLOOKUP(Tabla13[[#This Row],[REGION]],dimensiones!C:C,dimensiones!D:D,"") -> Región de Tarapacá
A53: 611030320 | B53: FUERZA AEREA DE CHILE COMANDANCIA EN JEFE COMANDO DE PERSONAL | D53: 13 | E53: ATENCION TELEFONICA | F53: CN61103032 | I53: =IF(Tabla13[[#This Row],[RUT]]=774097899,"DIST",_xlfn.XLOOKUP(Tabla13[[#This Row],[VENDEDOR]],dimensiones!$C$21:$C$28,dimensiones!$D$21:$D$28,"")) -> ATEL | J53: =_xlfn.XLOOKUP(Tabla13[[#This Row],[REGION]],dimensiones!C:C,dimensiones!D:D,"") -> Región de Metropolitana de Santiago
A54: 611090005 | B54: DEFENSA CIVIL DE CHILE | D54: 13 | E54: ATENCION TELEFONICA | F54: CN61109000 | I54: =IF(Tabla13[[#This Row],[RUT]]=774097899,"DIST",_xlfn.XLOOKUP(Tabla13[[#This Row],[VENDEDOR]],dimensiones!$C$21:$C$28,dimensiones!$D$21:$D$28,"")) -> ATEL | J54: =_xlfn.XLOOKUP(Tabla13[[#This Row],[REGION]],dimensiones!C:C,dimensiones!D:D,"") -> Región de Metropolitana de Santiago
A55: 612020000 | B55: MINISTERIO DE OBRAS PUBLICAS DIREC CION GRAL DE OO PP DCYF | D55: 13 | E55: ATENCION TELEFONICA | F55: CN61202000 | I55: =IF(Tabla13[[#This Row],[RUT]]=774097899,"DIST",_xlfn.XLOOKUP(Tabla13[[#This Row],[VENDEDOR]],dimensiones!$C$21:$C$28,dimensiones!$D$21:$D$28,"")) -> ATEL | J55: =_xlfn.XLOOKUP(Tabla13[[#This Row],[REGION]],dimensiones!C:C,dimensiones!D:D,"") -> Región de Metropolitana de Santiago
A56: 615330000 | B56: INSTITUTO DE SEGURIDAD LABORAL | D56: 13 | E56: ATENCION TELEFONICA | F56: CN61533000 | I56: =IF(Tabla13[[#This Row],[RUT]]=774097899,"DIST",_xlfn.XLOOKUP(Tabla13[[#This Row],[VENDEDOR]],dimensiones!$C$21:$C$28,dimensiones!$D$21:$D$28,"")) -> ATEL | J56: =_xlfn.XLOOKUP(Tabla13[[#This Row],[REGION]],dimensiones!C:C,dimensiones!D:D,"") -> Región de Metropolitana de Santiago
A57: 616050001 | B57: INSTITUTO DE SALUD PUBLICA | D57: 13 | E57: ATENCION TELEFONICA | F57: CN61605000 | I57: =IF(Tabla13[[#This Row],[RUT]]=774097899,"DIST",_xlfn.XLOOKUP(Tabla13[[#This Row],[VENDEDOR]],dimensiones!$C$21:$C$28,dimensiones!$D$21:$D$28,"")) -> ATEL | J57: =_xlfn.XLOOKUP(Tabla13[[#This Row],[REGION]],dimensiones!C:C,dimensiones!D:D,"") -> Región de Metropolitana de Santiago
A58: 616074008 | B58: SERVICIO DE SALUD ARAUCANIA SUR | D58: 9 | E58: ATENCION TELEFONICA | F58: CN61607400 | I58: =IF(Tabla13[[#This Row],[RUT]]=774097899,"DIST",_xlfn.XLOOKUP(Tabla13[[#This Row],[VENDEDOR]],dimensiones!$C$21:$C$28,dimensiones!$D$21:$D$28,"")) -> ATEL | J58: =_xlfn.XLOOKUP(Tabla13[[#This Row],[REGION]],dimensiones!C:C,dimensiones!D:D,"") -> Región de La Araucanía
A59: 616080008 | B59: SERVICIO DE SALUD METROPOLITANO NORTE | D59: 13 | E59: ATENCION TELEFONICA | F59: CN61608000 | I59: =IF(Tabla13[[#This Row],[RUT]]=774097899,"DIST",_xlfn.XLOOKUP(Tabla13[[#This Row],[VENDEDOR]],dimensiones!$C$21:$C$28,dimensiones!$D$21:$D$28,"")) -> ATEL | J59: =_xlfn.XLOOKUP(Tabla13[[#This Row],[REGION]],dimensiones!C:C,dimensiones!D:D,"") -> Región de Metropolitana de Santiago
A60: 618210006 | B60: SERVIU IX REGION | D60: 9 | E60: ATENCION TELEFONICA | F60: CN61821000 | I60: =IF(Tabla13[[#This Row],[RUT]]=774097899,"DIST",_xlfn.XLOOKUP(Tabla13[[#This Row],[VENDEDOR]],dimensiones!$C$21:$C$28,dimensiones!$D$21:$D$28,"")) -> ATEL | J60: =_xlfn.XLOOKUP(Tabla13[[#This Row],[REGION]],dimensiones!C:C,dimensiones!D:D,"") -> Región de La Araucanía
A61: 619232003 | B61: GOBIERNO REGIONAL METROPOLITANO DE SANTIAGO | D61: 13 | E61: ATENCION TELEFONICA | F61: CN61923200 | I61: =IF(Tabla13[[#This Row],[RUT]]=774097899,"DIST",_xlfn.XLOOKUP(Tabla13[[#This Row],[VENDEDOR]],dimensiones!$C$21:$C$28,dimensiones!$D$21:$D$28,"")) -> ATEL | J61: =_xlfn.XLOOKUP(Tabla13[[#This Row],[REGION]],dimensiones!C:C,dimensiones!D:D,"") -> Región de Metropolitana de Santiago
A62: 619551001 | B62: SERVICIO DE SALUD ARAUCANIA NORTE | D62: 9 | E62: ATENCION TELEFONICA | F62: CN61955100 | I62: =IF(Tabla13[[#This Row],[RUT]]=774097899,"DIST",_xlfn.XLOOKUP(Tabla13[[#This Row],[VENDEDOR]],dimensiones!$C$21:$C$28,dimensiones!$D$21:$D$28,"")) -> ATEL | J62: =_xlfn.XLOOKUP(Tabla13[[#This Row],[REGION]],dimensiones!C:C,dimensiones!D:D,"") -> Región de La Araucanía
... A69: 619991605 | B69: EJERCITO DE CHILE | D69: 1 | E69: ATENCION TELEFONICA | F69: CN61999160 | I69: =IF(Tabla13[[#This Row],[RUT]]=774097899,"DIST",_xlfn.XLOOKUP(Tabla13[[#This Row],[VENDEDOR]],dimensiones!$C$21:$C$28,dimensiones!$D$21:$D$28,"")) -> ATEL | J69: =_xlfn.XLOOKUP(Tabla13[[#This Row],[REGION]],dimensiones!C:C,dimensiones!D:D,"") -> Región de Tarapacá
A70: 619992806 | B70: CENTRO DE FORMACION TECNICA DE LA REGION DE COQUIMBO | C70: COQUIMBO | D70: 4 | E70: ATENCION TELEFONICA | F70: CN61999280 | H70: PRIVADO | I70: =IF(Tabla13[[#This Row],[RUT]]=774097899,"DIST",_xlfn.XLOOKUP(Tabla13[[#This Row],[VENDEDOR]],dimensiones!$C$21:$C$28,dimensiones!$D$21:$D$28,"")) -> ATEL | J70: =_xlfn.XLOOKUP(Tabla13[[#This Row],[REGION]],dimensiones!C:C,dimensiones!D:D,"") -> Región de Coquimbo
A71: 619993306 | B71: SERVICIO LOCAL DE EDUCACION PUBLICA DE HUASCO | D71: 3 | E71: ATENCION TELEFONICA | F71: CN61999330 | I71: =IF(Tabla13[[#This Row],[RUT]]=774097899,"DIST",_xlfn.XLOOKUP(Tabla13[[#This Row],[VENDEDOR]],dimensiones!$C$21:$C$28,dimensiones!$D$21:$D$28,"")) -> ATEL | J71: =_xlfn.XLOOKUP(Tabla13[[#This Row],[REGION]],dimensiones!C:C,dimensiones!D:D,"") -> Región de Atacama
A72: 620008001 | B72: SERVICIO LOCAL DE EDUCACION PUBLICA DE LLANQUIHUE | D72: 10 | E72: ATENCION TELEFONICA | F72: CN62000800 | I72: =IF(Tabla13[[#This Row],[RUT]]=774097899,"DIST",_xlfn.XLOOKUP(Tabla13[[#This Row],[VENDEDOR]],dimensiones!$C$21:$C$28,dimensiones!$D$21:$D$28,"")) -> ATEL | J72: =_xlfn.XLOOKUP(Tabla13[[#This Row],[REGION]],dimensiones!C:C,dimensiones!D:D,"") -> Región de Los Lagos
A73: 620008907 | B73: SERVICIO NACIONAL DE PROTECCION ESPECIALIZADA A LA NIÑEZ Y ADOLESCENCI | C73: CONCEPCIÓN | E73: ATENCION TELEFONICA | F73: CN62000890 | H73: PÚBLICO | I73: =IF(Tabla13[[#This Row],[RUT]]=774097899,"DIST",_xlfn.XLOOKUP(Tabla13[[#This Row],[VENDEDOR]],dimensiones!$C$21:$C$28,dimensiones!$D$21:$D$28,"")) -> ATEL | J73: =_xlfn.XLOOKUP(Tabla13[[#This Row],[REGION]],dimensiones!C:C,dimensiones!D:D,"")
A74: 650778332 | B74: ASOCIACION DE MUNICIPALIDADES NAHUELBUTA | D74: 9 | E74: ATENCION TELEFONICA | F74: CN65077833 | I74: =IF(Tabla13[[#This Row],[RUT]]=774097899,"DIST",_xlfn.XLOOKUP(Tabla13[[#This Row],[VENDEDOR]],dimensiones!$C$21:$C$28,dimensiones!$D$21:$D$28,"")) -> ATEL | J74: =_xlfn.XLOOKUP(Tabla13[[#This Row],[REGION]],dimensiones!C:C,dimensiones!D:D,"") -> Región de La Araucanía
A75: 651429811 | B75: CORPORACION EDUCACIONAL JESUS ANGEL GAZO | D75: 13 | E75: ATENCION TELEFONICA | F75: CN65142981 | I75: =IF(Tabla13[[#This Row],[RUT]]=774097899,"DIST",_xlfn.XLOOKUP(Tabla13[[#This Row],[VENDEDOR]],dimensiones!$C$21:$C$28,dimensiones!$D$21:$D$28,"")) -> ATEL | J75: =_xlfn.XLOOKUP(Tabla13[[#This Row],[REGION]],dimensiones!C:C,dimensiones!D:D,"") -> Región de Metropolitana de Santiago
A76: 651455669 | B76: COLEGIO AMERICANO CE | C76: LA SERENA | D76: 4 | E76: ATENCION TELEFONICA | F76: CN65145566 | H76: PRIVADO | I76: =IF(Tabla13[[#This Row],[RUT]]=774097899,"DIST",_xlfn.XLOOKUP(Tabla13[[#This Row],[VENDEDOR]],dimensiones!$C$21:$C$28,dimensiones!$D$21:$D$28,"")) -> ATEL | J76: =_xlfn.XLOOKUP(Tabla13[[#This Row],[REGION]],dimensiones!C:C,dimensiones!D:D,"") -> Región de Coquimbo
A77: 651536049 | B77: FUNDACION EDUCACIONAL MARGNOL | D77: 8 | E77: ATENCION TELEFONICA | F77: CN65153604 | I77: =IF(Tabla13[[#This Row],[RUT]]=774097899,"DIST",_xlfn.XLOOKUP(Tabla13[[#This Row],[VENDEDOR]],dimensiones!$C$21:$C$28,dimensiones!$D$21:$D$28,"")) -> ATEL | J77: =_xlfn.XLOOKUP(Tabla13[[#This Row],[REGION]],dimensiones!C:C,dimensiones!D:D,"") -> Región de Biobío
A78: 651543983 | B78: CENTRO DE FORMACION TECNICA DE LA REGION DE TARAPA | C78: IQUIQUE | D78: 1 | E78: ATENCION TELEFONICA | F78: CN65154398 | H78: PRIVADO | I78: =IF(Tabla13[[#This Row],[RUT]]=774097899,"DIST",_xlfn.XLOOKUP(Tabla13[[#This Row],[VENDEDOR]],dimensiones!$C$21:$C$28,dimensiones!$D$21:$D$28,"")) -> ATEL | J78: =_xlfn.XLOOKUP(Tabla13[[#This Row],[REGION]],dimensiones!C:C,dimensiones!D:D,"") -> Región de Tarapacá
A79: 651643511 | B79: FUNDACION BIEN COMUN | D79: 15 | E79: ATENCION TELEFONICA | F79: CN65164351 | I79: =IF(Tabla13[[#This Row],[RUT]]=774097899,"DIST",_xlfn.XLOOKUP(Tabla13[[#This Row],[VENDEDOR]],dimensiones!$C$21:$C$28,dimensiones!$D$21:$D$28,"")) -> ATEL | J79: =_xlfn.XLOOKUP(Tabla13[[#This Row],[REGION]],dimensiones!C:C,dimensiones!D:D,"") -> Región de Arica y Parinacota
A80: 651654114 | B80: CENTRO DE FORMACION TECNICA ESTATAL DE LA REGION DE VALPARAISO | C80: VIÑA DEL MAR | D80: 5 | E80: ATENCION TELEFONICA | F80: CN65165411 | H80: PÚBLICO | I80: =IF(Tabla13[[#This Row],[RUT]]=774097899,"DIST",_xlfn.XLOOKUP(Tabla13[[#This Row],[VENDEDOR]],dimensiones!$C$21:$C$28,dimensiones!$D$21:$D$28,"")) -> ATEL | J80: =_xlfn.XLOOKUP(Tabla13[[#This Row],[REGION]],dimensiones!C:C,dimensiones!D:D,"") -> Región de Valparaíso
A81: 654556504 | B81: EJERCITO DE CHILE | C81: ANTOFAGASTA | E81: ATENCION TELEFONICA | F81: CN65455650 | H81: PÚBLICO | I81: =IF(Tabla13[[#This Row],[RUT]]=774097899,"DIST",_xlfn.XLOOKUP(Tabla13[[#This Row],[VENDEDOR]],dimensiones!$C$21:$C$28,dimensiones!$D$21:$D$28,"")) -> ATEL | J81: =_xlfn.XLOOKUP(Tabla13[[#This Row],[REGION]],dimensiones!C:C,dimensiones!D:D,"")
A82: 655525408 | B82: JUZGADO DE FAMILIA DE VILLA ALEMANA | D82: 5 | E82: ATENCION TELEFONICA | F82: CN65552540 | I82: =IF(Tabla13[[#This Row],[RUT]]=774097899,"DIST",_xlfn.XLOOKUP(Tabla13[[#This Row],[VENDEDOR]],dimensiones!$C$21:$C$28,dimensiones!$D$21:$D$28,"")) -> ATEL | J82: =_xlfn.XLOOKUP(Tabla13[[#This Row],[REGION]],dimensiones!C:C,dimensiones!D:D,"") -> Región de Valparaíso
A83: 690702002 | B83: I MUNICIPALIDAD DE CONCHALI | D83: 13 | E83: ATENCION TELEFONICA | F83: CN69070200 | I83: =IF(Tabla13[[#This Row],[RUT]]=774097899,"DIST",_xlfn.XLOOKUP(Tabla13[[#This Row],[VENDEDOR]],dimensiones!$C$21:$C$28,dimensiones!$D$21:$D$28,"")) -> ATEL | J83: =_xlfn.XLOOKUP(Tabla13[[#This Row],[REGION]],dimensiones!C:C,dimensiones!D:D,"") -> Región de Metropolitana de Santiago
A84: 690703009 | B84: I MUNICIPALIDAD DE PROVIDENCIA | D84: 13 | E84: ATENCION TELEFONICA | F84: CN69070300 | I84: =IF(Tabla13[[#This Row],[RUT]]=774097899,"DIST",_xlfn.XLOOKUP(Tabla13[[#This Row],[VENDEDOR]],dimensiones!$C$21:$C$28,dimensiones!$D$21:$D$28,"")) -> ATEL | J84: =_xlfn.XLOOKUP(Tabla13[[#This Row],[REGION]],dimensiones!C:C,dimensiones!D:D,"") -> Región de Metropolitana de Santiago
A85: 690711001 | B85: ILUSTRE MUNICIPALIDAD DE PUDAHUEL | D85: 13 | E85: ATENCION TELEFONICA | F85: CN69071100 | I85: =IF(Tabla13[[#This Row],[RUT]]=774097899,"DIST",_xlfn.XLOOKUP(Tabla13[[#This Row],[VENDEDOR]],dimensiones!$C$21:$C$28,dimensiones!$D$21:$D$28,"")) -> ATEL | J85: =_xlfn.XLOOKUP(Tabla13[[#This Row],[REGION]],dimensiones!C:C,dimensiones!D:D,"") -> Región de Metropolitana de Santiago
A86: 690718014 | B86: CORPORACION MUNIC DE EDUC SALUD ATENCION | D86: 13 | E86: ATENCION TELEFONICA | F86: CN69071801 | I86: =IF(Tabla13[[#This Row],[RUT]]=774097899,"DIST",_xlfn.XLOOKUP(Tabla13[[#This Row],[VENDEDOR]],dimensiones!$C$21:$C$28,dimensiones!$D$21:$D$28,"")) -> ATEL | J86: =_xlfn.XLOOKUP(Tabla13[[#This Row],[REGION]],dimensiones!C:C,dimensiones!D:D,"") -> Región de Metropolitana de Santiago
A87: 690729008 | B87: ILUSTRE MUNICIPALIDAD DE MELIPILLA | D87: 13 | E87: ATENCION TELEFONICA | F87: CN69072900 | I87: =IF(Tabla13[[#This Row],[RUT]]=774097899,"DIST",_xlfn.XLOOKUP(Tabla13[[#This Row],[VENDEDOR]],dimensiones!$C$21:$C$28,dimensiones!$D$21:$D$28,"")) -> ATEL | J87: =_xlfn.XLOOKUP(Tabla13[[#This Row],[REGION]],dimensiones!C:C,dimensiones!D:D,"") -> Región de Metropolitana de Santiago
A88: 690739003 | B88: ILUSTRE MUNICIPALIDAD DE CURACAVI | D88: 13 | E88: ATENCION TELEFONICA | F88: CN69073900 | I88: =IF(Tabla13[[#This Row],[RUT]]=774097899,"DIST",_xlfn.XLOOKUP(Tabla13[[#This Row],[VENDEDOR]],dimensiones!$C$21:$C$28,dimensiones!$D$21:$D$28,"")) -> ATEL | J88: =_xlfn.XLOOKUP(Tabla13[[#This Row],[REGION]],dimensiones!C:C,dimensiones!D:D,"") -> Región de Metropolitana de Santiago
A89: 690803003 | B89: I MUNICIPALIDAD DE GRANEROS | D89: 6 | E89: ATENCION TELEFONICA | F89: CN69080300 | I89: =IF(Tabla13[[#This Row],[RUT]]=774097899,"DIST",_xlfn.XLOOKUP(Tabla13[[#This Row],[VENDEDOR]],dimensiones!$C$21:$C$28,dimensiones!$D$21:$D$28,"")) -> ATEL | J89: =_xlfn.XLOOKUP(Tabla13[[#This Row],[REGION]],dimensiones!C:C,dimensiones!D:D,"") -> Región de Libertador General Bernardo O'Higgins
A90: 690912015 | B90: ILUSTRE MUNICIPALIDAD DE PICHILEMU | D90: 6 | E90: ATENCION TELEFONICA | F90: CN69091201 | I90: =IF(Tabla13[[#This Row],[RUT]]=774097899,"DIST",_xlfn.XLOOKUP(Tabla13[[#This Row],[VENDEDOR]],dimensiones!$C$21:$C$28,dimensiones!$D$21:$D$28,"")) -> ATEL | J90: =_xlfn.XLOOKUP(Tabla13[[#This Row],[REGION]],dimensiones!C:C,dimensiones!D:D,"") -> Región de Libertador General Bernardo O'Higgins
A91: 691407004 | B91: I. MUNICIPALIDAD DE SAN FABIAN | D91: 8 | E91: ATENCION TELEFONICA | F91: CN69140700 | I91: =IF(Tabla13[[#This Row],[RUT]]=774097899,"DIST",_xlfn.XLOOKUP(Tabla13[[#This Row],[VENDEDOR]],dimensiones!$C$21:$C$28,dimensiones!$D$21:$D$28,"")) -> ATEL | J91: =_xlfn.XLOOKUP(Tabla13[[#This Row],[REGION]],dimensiones!C:C,dimensiones!D:D,"") -> Región de Biobío
A92: 691408000 | B92: ILUSTRE MUNICIPALIDAD DE SAN NICOLAS | D92: 16 | E92: ATENCION TELEFONICA | F92: CN69140800 | I92: =IF(Tabla13[[#This Row],[RUT]]=774097899,"DIST",_xlfn.XLOOKUP(Tabla13[[#This Row],[VENDEDOR]],dimensiones!$C$21:$C$28,dimensiones!$D$21:$D$28,"")) -> ATEL | J92: =_xlfn.XLOOKUP(Tabla13[[#This Row],[REGION]],dimensiones!C:C,dimensiones!D:D,"") -> Región de Ñuble
A93: 691511022 | B93: ILUSTRE MUNICIPALIDAD DE SAN ROSENDO - SALUD | D93: 8 | E93: ATENCION TELEFONICA | F93: CN69151102 | I93: =IF(Tabla13[[#This Row],[RUT]]=774097899,"DIST",_xlfn.XLOOKUP(Tabla13[[#This Row],[VENDEDOR]],dimensiones!$C$21:$C$28,dimensiones!$D$21:$D$28,"")) -> ATEL | J93: =_xlfn.XLOOKUP(Tabla13[[#This Row],[REGION]],dimensiones!C:C,dimensiones!D:D,"") -> Región de Biobío
... A96: 692403002 | B96: I MUNICIPALIDAD DE COYHAIQUE | D96: 11 | E96: ATENCION TELEFONICA | F96: CN69240300 | I96: =IF(Tabla13[[#This Row],[RUT]]=774097899,"DIST",_xlfn.XLOOKUP(Tabla13[[#This Row],[VENDEDOR]],dimensiones!$C$21:$C$28,dimensiones!$D$21:$D$28,"")) -> ATEL | J96: =_xlfn.XLOOKUP(Tabla13[[#This Row],[REGION]],dimensiones!C:C,dimensiones!D:D,"") -> Región de Aysén del General Carlos Ibáñez del Campo
A97: 692532007 | B97: I MUNICIPALIDAD DE SIERRA GORDA | C97: SIERRA GORDA | E97: ATENCION TELEFONICA | F97: CN69253200 | H97: PÚBLICO | I97: =IF(Tabla13[[#This Row],[RUT]]=774097899,"DIST",_xlfn.XLOOKUP(Tabla13[[#This Row],[VENDEDOR]],dimensiones!$C$21:$C$28,dimensiones!$D$21:$D$28,"")) -> ATEL | J97: =_xlfn.XLOOKUP(Tabla13[[#This Row],[REGION]],dimensiones!C:C,dimensiones!D:D,"")
A98: 707291001 | B98: UNIVERSIDAD TECNOLOGICA | D98: 13 | E98: ATENCION TELEFONICA | F98: CN70729100 | I98: =IF(Tabla13[[#This Row],[RUT]]=774097899,"DIST",_xlfn.XLOOKUP(Tabla13[[#This Row],[VENDEDOR]],dimensiones!$C$21:$C$28,dimensiones!$D$21:$D$28,"")) -> ATEL | J98: =_xlfn.XLOOKUP(Tabla13[[#This Row],[REGION]],dimensiones!C:C,dimensiones!D:D,"") -> Región de Metropolitana de Santiago
A99: 707721006 | B99: UNIVERSIDAD DE LOS LAGOS | D99: 10 | E99: ATENCION TELEFONICA | F99: CN70772100 | I99: =IF(Tabla13[[#This Row],[RUT]]=774097899,"DIST",_xlfn.XLOOKUP(Tabla13[[#This Row],[VENDEDOR]],dimensiones!$C$21:$C$28,dimensiones!$D$21:$D$28,"")) -> ATEL | J99: =_xlfn.XLOOKUP(Tabla13[[#This Row],[REGION]],dimensiones!C:C,dimensiones!D:D,"") -> Región de Los Lagos
A100: 712367008 | B100: UNIVERSIDAD DE ATACAMA | D100: 3 | E100: ATENCION TELEFONICA | F100: CN71236700 | I100: =IF(Tabla13[[#This Row],[RUT]]=774097899,"DIST",_xlfn.XLOOKUP(Tabla13[[#This Row],[VENDEDOR]],dimensiones!$C$21:$C$28,dimensiones!$D$21:$D$28,"")) -> ATEL | J100: =_xlfn.XLOOKUP(Tabla13[[#This Row],[REGION]],dimensiones!C:C,dimensiones!D:D,"") -> Región de Atacama
A101: 713098000 | B101: CORPORACION MUNICIPAL DE SERVICIOS Y DESARROLLO MAIPU | D101: 13 | E101: ATENCION TELEFONICA | F101: CN71309800 | I101: =IF(Tabla13[[#This Row],[RUT]]=774097899,"DIST",_xlfn.XLOOKUP(Tabla13[[#This Row],[VENDEDOR]],dimensiones!$C$21:$C$28,dimensiones!$D$21:$D$28,"")) -> ATEL | J101: =_xlfn.XLOOKUP(Tabla13[[#This Row],[REGION]],dimensiones!C:C,dimensiones!D:D,"") -> Región de Metropolitana de Santiago
A102: 723960002 | B102: CORP NACIONAL DE DESARROLLO INDIGENA | D102: 9 | E102: ATENCION TELEFONICA | F102: CN72396000 | I102: =IF(Tabla13[[#This Row],[RUT]]=774097899,"DIST",_xlfn.XLOOKUP(Tabla13[[#This Row],[VENDEDOR]],dimensiones!$C$21:$C$28,dimensiones!$D$21:$D$28,"")) -> ATEL | J102: =_xlfn.XLOOKUP(Tabla13[[#This Row],[REGION]],dimensiones!C:C,dimensiones!D:D,"") -> Región de La Araucanía
A103: 739238005 | B103: ZONA BIENESTAR VALPARAISO" BIENESTAR SOCIAL" | D103: 8 | E103: ATENCION TELEFONICA | F103: CN73923800 | I103: =IF(Tabla13[[#This Row],[RUT]]=774097899,"DIST",_xlfn.XLOOKUP(Tabla13[[#This Row],[VENDEDOR]],dimensiones!$C$21:$C$28,dimensiones!$D$21:$D$28,"")) -> ATEL | J103: =_xlfn.XLOOKUP(Tabla13[[#This Row],[REGION]],dimensiones!C:C,dimensiones!D:D,"") -> Región de Biobío
A104: 748229000 | B104: FUND CENTRO DE EDUCACION Y CAPACITACION DE LA UCN | D104: 4 | E104: ATENCION TELEFONICA | F104: CN74822900 | I104: =IF(Tabla13[[#This Row],[RUT]]=774097899,"DIST",_xlfn.XLOOKUP(Tabla13[[#This Row],[VENDEDOR]],dimensiones!$C$21:$C$28,dimensiones!$D$21:$D$28,"")) -> ATEL | J104: =_xlfn.XLOOKUP(Tabla13[[#This Row],[REGION]],dimensiones!C:C,dimensiones!D:D,"") -> Región de Coquimbo
A105: 760163058 | B105: SOCIEDAD RADIOLOGICA CHILLAN S.A. | D105: 16 | E105: ATENCION TELEFONICA | F105: CN76016305 | I105: =IF(Tabla13[[#This Row],[RUT]]=774097899,"DIST",_xlfn.XLOOKUP(Tabla13[[#This Row],[VENDEDOR]],dimensiones!$C$21:$C$28,dimensiones!$D$21:$D$28,"")) -> ATEL | J105: =_xlfn.XLOOKUP(Tabla13[[#This Row],[REGION]],dimensiones!C:C,dimensiones!D:D,"") -> Región de Ñuble
A106: 760286885 | B106: LOGISCARGO CHILE ALEJANDRO SAN MARTIN CARRASCO E.I.R.L | D106: 13 | E106: ATENCION TELEFONICA | F106: CN76028688 | I106: =IF(Tabla13[[#This Row],[RUT]]=774097899,"DIST",_xlfn.XLOOKUP(Tabla13[[#This Row],[VENDEDOR]],dimensiones!$C$21:$C$28,dimensiones!$D$21:$D$28,"")) -> ATEL | J106: =_xlfn.XLOOKUP(Tabla13[[#This Row],[REGION]],dimensiones!C:C,dimensiones!D:D,"") -> Región de Metropolitana de Santiago
A107: 760449598 | B107: ARLAB S.A. | D107: 13 | E107: ATENCION TELEFONICA | F107: CN76044959 | I107: =IF(Tabla13[[#This Row],[RUT]]=774097899,"DIST",_xlfn.XLOOKUP(Tabla13[[#This Row],[VENDEDOR]],dimensiones!$C$21:$C$28,dimensiones!$D$21:$D$28,"")) -> ATEL | J107: =_xlfn.XLOOKUP(Tabla13[[#This Row],[REGION]],dimensiones!C:C,dimensiones!D:D,"") -> Región de Metropolitana de Santiago
A108: 760700339 | B108: ARAMA NATURAL PRODUCTS DISTRIBUIDORA LIMITADA | D108: 13 | E108: ATENCION TELEFONICA | F108: CN76070033 | I108: =IF(Tabla13[[#This Row],[RUT]]=774097899,"DIST",_xlfn.XLOOKUP(Tabla13[[#This Row],[VENDEDOR]],dimensiones!$C$21:$C$28,dimensiones!$D$21:$D$28,"")) -> ATEL | J108: =_xlfn.XLOOKUP(Tabla13[[#This Row],[REGION]],dimensiones!C:C,dimensiones!D:D,"") -> Región de Metropolitana de Santiago
A109: 760742163 | B109: RESONANCIA MAGNETICA DEL NORTE S.A. | D109: 4 | E109: ATENCION TELEFONICA | F109: CN76074216 | I109: =IF(Tabla13[[#This Row],[RUT]]=774097899,"DIST",_xlfn.XLOOKUP(Tabla13[[#This Row],[VENDEDOR]],dimensiones!$C$21:$C$28,dimensiones!$D$21:$D$28,"")) -> ATEL | J109: =_xlfn.XLOOKUP(Tabla13[[#This Row],[REGION]],dimensiones!C:C,dimensiones!D:D,"") -> Región de Coquimbo
... A112: 761108921 | B112: JORGE SEPULVEDA GONZAÑEZ DD, E.I.R.L | D112: 13 | E112: ATENCION TELEFONICA | F112: CN76110892 | I112: =IF(Tabla13[[#This Row],[RUT]]=774097899,"DIST",_xlfn.XLOOKUP(Tabla13[[#This Row],[VENDEDOR]],dimensiones!$C$21:$C$28,dimensiones!$D$21:$D$28,"")) -> ATEL | J112: =_xlfn.XLOOKUP(Tabla13[[#This Row],[REGION]],dimensiones!C:C,dimensiones!D:D,"") -> Región de Metropolitana de Santiago
A113: 761111132 | B113: CLINICAL MARKET S.A | C113: SANTIAGO | D113: 13 | E113: ATENCION TELEFONICA | F113: CN76111113 | H113: PRIVADO | I113: =IF(Tabla13[[#This Row],[RUT]]=774097899,"DIST",_xlfn.XLOOKUP(Tabla13[[#This Row],[VENDEDOR]],dimensiones!$C$21:$C$28,dimensiones!$D$21:$D$28,"")) -> ATEL | J113: =_xlfn.XLOOKUP(Tabla13[[#This Row],[REGION]],dimensiones!C:C,dimensiones!D:D,"") -> Región de Metropolitana de Santiago
A114: 761162209 | B114: BARRIA Y CONTRERAS LTDA | D114: 10 | E114: ATENCION TELEFONICA | F114: CN76116220 | I114: =IF(Tabla13[[#This Row],[RUT]]=774097899,"DIST",_xlfn.XLOOKUP(Tabla13[[#This Row],[VENDEDOR]],dimensiones!$C$21:$C$28,dimensiones!$D$21:$D$28,"")) -> ATEL | J114: =_xlfn.XLOOKUP(Tabla13[[#This Row],[REGION]],dimensiones!C:C,dimensiones!D:D,"") -> Región de Los Lagos
...

Sheet CARTERA 2025 (2)
A1: RUT | B1: RAZON | C1: VENDEDOR | D1: CARTERA | E1: COMUNA | F1: REGION | G1: COD CLIENTE | H1: RUT SD | I1: SECTOR | J1: prueba | L1: Nota: Se actualizo la cartera 2025, sin embargo, cartera de SANTIAGO III Y SUR III pasan a atencion telefonica ya que no tienen vendedor.
A2: 616080024 | B2: HOSPITAL SAN JOSE | C2: M RAMOS | D2: SANTIAGO II | E2: INDEPENDENCIA | F2: REGIÓN DE METROPOLITANA DE SANTIAGO | G2: CN61608002 | H2: 61608002 | I2: PUBLICO | J2: MAURICIO RAMOS MORENO
A3: 703601006 | B3: ASOCIACION CHILENA DE SEGURIDAD | C3: A TELEFONICA | D3: A TELEFONICA | E3: PROVIDENCIA | F3: REGIÓN DE METROPOLITANA DE SANTIAGO | G3: CN70360100 | H3: 70360100 | I3: PRIVADO | J3: ATENCION TELEFONICA
A4: 616086022 | B4: HOSPITAL DE URGENCIA ASISTENCIA PUBLICA | C4: G MANNESCHI | D4: SANTIAGO I | E4: SANTIAGO | F4: REGIÓN DE METROPOLITANA DE SANTIAGO | G4: CN61608602 | H4: 61608602 | I4: PUBLICO | J4: GIANCARLO MANNESCHI GALLARDO
A5: 619751000 | B5: HOSPITAL DE PUERTO MONTT | C5: M RUIZ | D5: SUR II | E5: PUERTO MONTT | F5: REGIÓN DE LOS LAGOS | G5: CN61975100 | H5: 61975100 | I5: PUBLICO | J5: MARCELO RUIZ
A6: 616021893 | B6: HOSPITAL GUILLERMO GRANT BENAVENTE | C6: R ARAYA | D6: SUR I | E6: HUALPÉN | F6: REGIÓN DE BIOBÍO | G6: CN61602189 | H6: 61602189 | I6: PUBLICO | J6: RICARDO ENRIQUE ARAYA GONZÁLEZ
A7: 616020544 | B7: HOSPITAL CARLOS VAN BUREN | C7: C VALENZUELA | D7: NORTE I | E7: VALPARAÍSO | F7: REGIÓN DE VALPARAÍSO | G7: CN61602054 | H7: 61602054 | I7: PUBLICO | J7: CONSTANZA VALENZUELA
A8: 616082043 | B8: HOSPITAL SAN JUAN DE DIOS | C8: G MANNESCHI | D8: SANTIAGO I | E8: SANTIAGO | F8: REGIÓN DE METROPOLITANA DE SANTIAGO | G8: CN61608204 | H8: 61608204 | I8: PUBLICO | J8: GIANCARLO MANNESCHI GALLARDO
A9: 619803205 | B9: HOSPITAL CLINICO METROPOLITANO EL CARMEN DOCTOR LUIS VALENTIN FERRADA | C9: G MANNESCHI | D9: SANTIAGO I | E9: MAIPÚ | F9: REGIÓN DE METROPOLITANA DE SANTIAGO | G9: CN61980320 | H9: 61980320 | I9: PUBLICO | J9: GIANCARLO MANNESCHI GALLARDO
A10: 616086049 | B10: HOSPITAL CLINICO SAN BORJA ARRIARAN | C10: M RAMOS | D10: SANTIAGO II | E10: SANTIAGO | F10: REGIÓN DE METROPOLITANA DE SANTIAGO | G10: CN61608604 | H10: 61608604 | I10: PUBLICO | J10: MAURICIO RAMOS MORENO
A11: 616085026 | B11: COMPLEJO ASISTENCIAL DR. SOTERO DEL RIO | C11: G MANNESCHI | D11: SANTIAGO I | E11: PUENTE ALTO | F11: REGIÓN DE METROPOLITANA DE SANTIAGO | G11: CN61608502 | H11: 61608502 | I11: PUBLICO | J11: GIANCARLO MANNESCHI GALLARDO
A12: 616082051 | B12: HOSPITAL DR. FELIX BULNES CERDA | C12: G MANNESCHI | D12: SANTIAGO I | E12: CERRO NAVIA | F12: REGIÓN DE METROPOLITANA DE SANTIAGO | G12: CN61608205 | H12: 61608205 | I12: PUBLICO | J12: GIANCARLO MANNESCHI GALLARDO
A13: 616066080 | B13: HOSPITAL SAN MARTIN DE QUILLOTA | C13: C VALENZUELA | D13: NORTE I | E13: QUILLOTA | F13: REGIÓN DE VALPARAÍSO | G13: CN61606608 | H13: 61606608 | I13: PUBLICO | J13: CONSTANZA VALENZUELA
... A17: 967701009 | B17: CLINICA ALEMANA | C17: G MANNESCHI | D17: SANTIAGO I | E17: VITACURA | F17: REGIÓN DE METROPOLITANA DE SANTIAGO | G17: CN96770100 | H17: 96770100 | I17: PRIVADO | J17: GIANCARLO MANNESCHI GALLARDO
A18: 61607301K | B18: HOSPITAL BASE DR. VICTOR RIOS RUIZ | C18: R ARAYA | D18: SUR I | E18: LOS ANGELES | F18: REGIÓN DE BIOBÍO | G18: CN61607301 | H18: 61607301 | I18: PUBLICO | J18: RICARDO ENRIQUE ARAYA GONZÁLEZ
A19: 616072021 | B19: HOSPITAL LAS HIGUERAS | C19: R ARAYA | D19: SUR I | E19: TALCAHUANO | F19: REGIÓN DE BIOBÍO | G19: CN61607202 | H19: 61607202 | I19: PUBLICO | J19: RICARDO ENRIQUE ARAYA GONZÁLEZ
A20: 965304703 | B20: CLINICA DAVILA Y SERVICIOS MEDICOS SPA | C20: G MANNESCHI | D20: SANTIAGO I | E20: RECOLETA | F20: REGIÓN DE METROPOLITANA DE SANTIAGO | G20: CN96530470 | H20: 96530470 | I20: PRIVADO | J20: GIANCARLO MANNESCHI GALLARDO
A21: 61103007K | B21: HOSPITAL CLINICO GENERAL DR. RAUL YAZIGI J. | C21: G MANNESCHI | D21: SANTIAGO I | E21: LAS CONDES | F21: REGIÓN DE METROPOLITANA DE SANTIAGO | G21: CN61103007 | H21: 61103007 | I21: PUBLICO | J21: GIANCARLO MANNESCHI GALLARDO
A22: 619598008 | B22: HOSPITAL SANTIAGO ORIENTE DR. LUIS TISNE BROUSSE | C22: G MANNESCHI | D22: SANTIAGO I | E22: PEÑALOLÉN | F22: REGIÓN DE METROPOLITANA DE SANTIAGO | G22: CN61959800 | H22: 61959800 | I22: PUBLICO | J22: GIANCARLO MANNESCHI GALLARDO
A23: 616021230 | B23: HOSPITAL DE MELIPILLA | C23: G MANNESCHI | D23: SANTIAGO I | E23: MELIPILLA | F23: REGIÓN DE METROPOLITANA DE SANTIAGO | G23: CN61602123 | H23: 61602123 | I23: PUBLICO | J23: GIANCARLO MANNESCHI GALLARDO
A24: 616022113 | B24: HOSPITAL DE CURANILAHUE | C24: R ARAYA | D24: SUR I | E24: CURANILAHUE | F24: REGIÓN DE BIOBÍO | G24: CN61602211 | H24: 61602211 | I24: PUBLICO | J24: RICARDO ENRIQUE ARAYA GONZÁLEZ
A25: 616066021 | B25: HOSPITAL DR. GUSTAVO FRICKE | C25: C VALENZUELA | D25: NORTE I | E25: VIÑA DEL MAR | F25: REGIÓN DE VALPARAÍSO | G25: CN61606602 | H25: 61606602 | I25: PUBLICO | J25: CONSTANZA VALENZUELA
A26: 616064029 | B26: HOSPITAL LA SERENA | C26: C VALENZUELA | D26: NORTE I | E26: LA SERENA | F26: REGIÓN DE COQUIMBO | G26: CN61606402 | H26: 61606402 | I26: PUBLICO | J26: CONSTANZA VALENZUELA
A27: 616022326 | B27: HOSPITAL DOCTOR HERNAN HENRIQUEZ ARAVENA | C27: M RUIZ | D27: SUR II | E27: TEMUCO | F27: REGIÓN DE LA ARAUCANÍA | G27: CN61602232 | H27: 61602232 | I27: PUBLICO | J27: MARCELO RUIZ
A28: 609100001 | B28: UNIVERSIDAD DE CHILE | C28: M RAMOS | D28: SANTIAGO II | E28: INDEPENDENCIA | F28: REGIÓN DE METROPOLITANA DE SANTIAGO | G28: CN60910000 | H28: 60910000 | I28: PUBLICO | J28: MAURICIO RAMOS MORENO
A29: 650754859 | B29: HOSPITAL CLINICO METROPOLITANA LA FLORIDA DRA ELOISA DIAZ INSUNZA | C29: M RAMOS | D29: SANTIAGO II | E29: LA FLORIDA | F29: REGIÓN DE METROPOLITANA DE SANTIAGO | G29: CN65075485 | H29: 65075485 | I29: PUBLICO | J29: MAURICIO RAMOS MORENO
A30: 616069179 | B30: HOSPITAL LINARES | C30: SUR III | D30: SUR III | E30: LINARES | F30: REGIÓN DE MAULE | G30: CN61606917 | H30: 61606917 | I30: PUBLICO | J30: ATENCION TELEFONICA
A31: 616070010 | B31: HOSPITAL CLINICO HERMINDA MARTIN | C31: R ARAYA | D31: SUR I | E31: CHILLÁN | F31: REGIÓN DE ÑUBLE | G31: CN61607001 | H31: 61607001 | I31: PUBLICO | J31: RICARDO ENRIQUE ARAYA GONZÁLEZ
A32: 907530000 | B32: CLINICA SANTA MARIA SPA | C32: M MARINAO | D32: SANTIAGO III | E32: PROVIDENCIA | F32: REGIÓN DE METROPOLITANA DE SANTIAGO | G32: CN90753000 | H32: 90753000 | I32: PRIVADO | J32: ATENCION TELEFONICA
A33: 61608402K | B33: INSTITUTO NACIONAL DEL TORAX | C33: M MARINAO | D33: SANTIAGO III | E33: PROVIDENCIA | F33: REGIÓN DE METROPOLITANA DE SANTIAGO | G33: CN61608402 | H33: 61608402 | I33: PUBLICO | J33: ATENCION TELEFONICA
A34: 710142009 | B34: CORMUN RANCAGUA - ADMINISTRACIÓN CENTRA | C34: SUR III | D34: SUR III | E34: RANCAGUA | F34: REGIÓN DE LIBERTADOR GENERAL BERNARDO O'HIGGINS | G34: CN71014200 | H34: 71014200 | I34: PUBLICO | J34: ATENCION TELEFONICA
A35: 616086057 | B35: DIRECCION ATENCION PRIMARIA, SERVICIO DE SALUD METROPOLITANO CENTRAL | C35: M MARINAO | D35: SANTIAGO III | E35: SANTIAGO | F35: REGIÓN DE METROPOLITANA DE SANTIAGO | G35: CN61608605 | H35: 61608605 | I35: PUBLICO | J35: ATENCION TELEFONICA
A36: 611020171 | B36: HOSPITAL NAVAL ALMIRANTE NEF | C36: C VALENZUELA | D36: NORTE I | E36: VIÑA DEL MAR | F36: REGIÓN DE VALPARAÍSO | G36: CN61102017 | H36: 61102017 | I36: PUBLICO | J36: CONSTANZA VALENZUELA
A37: 616021389 | B37: HOSPITAL REGIONAL RANCAGUA | C37: SUR III | D37: SUR III | E37: RANCAGUA | F37: REGIÓN DE LIBERTADOR GENERAL BERNARDO O'HIGGINS | G37: CN61602138 | H37: 61602138 | I37: PUBLICO | J37: ATENCION TELEFONICA
A38: 620008303 | B38: HOSPITAL COMPLEJO ASISTENCIAL PADRE LAS CASAS | C38: M RUIZ | D38: SUR II | E38: PADRE LAS CASAS | F38: REGIÓN DE LA ARAUCANÍA | G38: CN62000830 | H38: 62000830 | I38: PUBLICO | J38: MARCELO RUIZ
A39: 616062018 | B39: HOSPITAL REGIONAL DE ANTOFAGASTA | C39: M MARINAO | D39: SANTIAGO III | E39: ANTOFAGASTA | F39: REGIÓN DE ANTOFAGASTA | G39: CN61606201 | H39: 61606201 | I39: PUBLICO | J39: ATENCION TELEFONICA
A40: 691508005 | B40: I MUNICIPALIDAD DE TALCAHUANO | C40: R ARAYA | D40: SUR I | E40: TALCAHUANO | F40: REGIÓN DE BIOBÍO | G40: CN69150800 | H40: 69150800 | I40: PUBLICO | J40: RICARDO ENRIQUE ARAYA GONZÁLEZ
A41: 765150701 | B41: CLINICA ANDES SALUD CHILLAN S.A | C41: R ARAYA | D41: SUR I | E41: CHILLÁN | F41: REGIÓN DE ÑUBLE | G41: CN76515070 | H41: 76515070 | I41: PRIVADO | J41: RICARDO ENRIQUE ARAYA GONZÁLEZ
A42: 619585003 | B42: HOSPITAL PADRE ALBERTO HURTADO | C42: G MANNESCHI | D42: SANTIAGO I | E42: SAN RAMÓN | F42: REGIÓN DE METROPOLITANA DE SANTIAGO | G42: CN61958500 | H42: 61958500 | I42: PUBLICO | J42: GIANCARLO MANNESCHI GALLARDO
A43: 691809005 | B43: ILUSTRE MUNICIPALIDAD DE VICTORIA | C43: M RUIZ | D43: SUR II | E43: VICTORIA | F43: REGIÓN DE LA ARAUCANÍA | G43: CN69180900 | H43: 69180900 | I43: PUBLICO | J43: MARCELO RUIZ
A44: 703774008 | B44: FUNDACION ARTURO LOPEZ PEREZ | C44: M MARINAO | D44: SANTIAGO III | E44: PROVIDENCIA | F44: REGIÓN DE METROPOLITANA DE SANTIAGO | G44: CN70377400 | H44: 70377400 | I44: PRIVADO | J44: ATENCION TELEFONICA
A45: 616022954 | B45: HOSPITAL TRAUMATOLOGICO DE CONCEPCION | C45: R ARAYA | D45: SUR I | E45: CONCEPCIÓN | F45: REGIÓN DE BIOBÍO | G45: CN61602295 | H45: 61602295 | I45: PUBLICO | J45: RICARDO ENRIQUE ARAYA GONZÁLEZ
... A51: 742696006 | B51: DIRECCION DE SALUD SAN PEDRO DE LA PAZ | C51: R ARAYA | D51: SUR I | E51: SAN PEDRO DE LA PAZ | F51: REGIÓN DE BIOBÍO | G51: CN74269600 | H51: 74269600 | I51: PUBLICO | J51: RICARDO ENRIQUE ARAYA GONZÁLEZ
A52: 69270200K | B52: ILUSTRE MUNICIPALIDAD DE CHILLAN DPTO SALUD | C52: R ARAYA | D52: SUR I | E52: CHILLÁN | F52: REGIÓN DE ÑUBLE | G52: CN69270200 | H52: 69270200 | I52: PUBLICO | J52: RICARDO ENRIQUE ARAYA GONZÁLEZ
A53: 616084089 | B53: HOSPITAL DR. LUIS CALVO MACKENNA | C53: M MARINAO | D53: SANTIAGO III | E53: PROVIDENCIA | F53: REGIÓN DE METROPOLITANA DE SANTIAGO | G53: CN61608408 | H53: 61608408 | I53: PUBLICO | J53: ATENCION TELEFONICA
A54: 763360393 | B54: CLINICA MEDS | C54: G MANNESCHI | D54: SANTIAGO I | E54: QUILICURA | F54: REGIÓN DE METROPOLITANA DE SANTIAGO | G54: CN76336039 | H54: 76336039 | I54: PRIVADO | J54: GIANCARLO MANNESCHI GALLARDO
A55: 690407000 | B55: I. MUNICIPALIDAD DE OVALLE | C55: C VALENZUELA | D55: NORTE I | E55: OVALLE | F55: REGIÓN DE COQUIMBO | G55: CN69040700 | H55: 69040700 | I55: PUBLICO | J55: CONSTANZA VALENZUELA
A56: 616022032 | B56: HOSPITAL LOTA | C56: R ARAYA | D56: SUR I | E56: LOTA | F56: REGIÓN DE BIOBÍO | G56: CN61602203 | H56: 61602203 | I56: PUBLICO | J56: RICARDO ENRIQUE ARAYA GONZÁLEZ
A57: 968859307 | B57: CLINICA BICENTENARIO S.A. | C57: M RAMOS | D57: SANTIAGO II | E57: ESTACIÓN CENTRAL | F57: REGIÓN DE METROPOLITANA DE SANTIAGO | G57: CN96885930 | H57: 96885930 | I57: PRIVADO | J57: MAURICIO RAMOS MORENO
A58: 616064045 | B58: HOSPITAL OVALLE | C58: C VALENZUELA | D58: NORTE I | E58: OVALLE | F58: REGIÓN DE COQUIMBO | G58: CN61606404 | H58: 61606404 | I58: PUBLICO | J58: CONSTANZA VALENZUELA
A59: 691512029 | B59: I MUNICIPALIDAD DE CORONEL DPTO ADMINIST | C59: R ARAYA | D59: SUR I | E59: CORONEL | F59: REGIÓN DE BIOBÍO | G59: CN69151202 | H59: 69151202 | I59: PUBLICO | J59: RICARDO ENRIQUE ARAYA GONZÁLEZ
A60: 713286001 | B60: CORP MUNICIPAL SAN FERNANDO PARA LA ATENCION MENORES Y LAS A DE E Y S | C60: SUR III | D60: SUR III | E60: SAN FERNANDO | F60: REGIÓN DE LIBERTADOR GENERAL BERNARDO O'HIGGINS | G60: CN71328600 | H60: 71328600 | I60: PUBLICO | J60: ATENCION TELEFONICA
A61: 765558700 | B61: CLINICA ALEMANA DE VALDIVIA | C61: M RUIZ | D61: SUR II | E61: VALDIVIA | F61: REGIÓN DE LOS RÍOS | G61: CN76555870 | H61: 76555870 | I61: PRIVADO | J61: MARCELO RUIZ
A62: 616022806 | B62: HOSPITAL COYHAIQUE | C62: A TELEFONICA | D62: A TELEFONICA | E62: COIHAIQUE | F62: REGIÓN DE AYSÉN DEL GENERAL CARLOS IBÁÑEZ DEL CAMPO | G62: CN61602280 | H62: 61602280 | I62: PUBLICO | J62: ATENCION TELEFONICA
A63: 813380005 | B63: INMED S.A | C63: A TELEFONICA | D63: A TELEFONICA | E63: PUDAHUEL | F63: REGIÓN DE METROPOLITANA DE SANTIAGO | G63: CN81338000 | H63: 81338000 | I63: PRIVADO | J63: ATENCION TELEFONICA
A64: 708352004 | B64: CORP MUNIC DE PUDAHUEL | C64: M MARINAO | D64: SANTIAGO III | E64: PUDAHUEL | F64: REGIÓN DE METROPOLITANA DE SANTIAGO | G64: CN70835200 | H64: 70835200 | I64: PUBLICO | J64: ATENCION TELEFONICA
... A77: 760579041 | B77: HOSPITAL CLINICO DEL SUR | C77: R ARAYA | D77: SUR I | E77: CONCEPCIÓN | F77: REGIÓN DE BIOBÍO | G77: CN76057904 | H77: 76057904 | I77: PRIVADO | J77: RICARDO ENRIQUE ARAYA GONZÁLEZ
A78: 61602275K | B78: HOSPITAL DE CASTRO DR. AUGUSTO RIFFART | C78: M RUIZ | D78: SUR II | E78: CASTRO | F78: REGIÓN DE LOS LAGOS | G78: CN61602275 | H78: 61602275 | I78: PUBLICO | J78: MARCELO RUIZ
A79: 616062026 | B79: HOSPITAL CARLOS CISTERNAS DE CALAMA | C79: M MARINAO | D79: SANTIAGO III | E79: CALAMA | F79: REGIÓN DE ANTOFAGASTA | G79: CN61606202 | H79: 61606202 | I79: PUBLICO | J79: ATENCION TELEFONICA
A80: 616021265 | B80: HOSPITAL CLAUDIO VICUÑA | C80: C VALENZUELA | D80: NORTE I | E80: SAN ANTONIO | F80: REGIÓN DE VALPARAÍSO | G80: CN61602126 | H80: 61602126 | I80: PUBLICO | J80: CONSTANZA VALENZUELA
A81: 616082035 | B81: SERVICIO DE SALUD OCCIDENTE INSTITUTO TRAUMATOLOGICO DE SANTIAGO | C81: M RAMOS | D81: SANTIAGO II | E81: SANTIAGO | F81: REGIÓN DE METROPOLITANA DE SANTIAGO | G81: CN61608203 | H81: 61608203 | I81: PUBLICO | J81: MAURICIO RAMOS MORENO
A82: 691501027 | B82: DIRECCION DE SALUD MUNICIPAL | C82: R ARAYA | D82: SUR I | E82: TOMÉ | F82: REGIÓN DE BIOBÍO | G82: CN69150102 | H82: 69150102 | I82: PUBLICO | J82: RICARDO ENRIQUE ARAYA GONZÁLEZ
A83: 619806204 | B83: CRS HOSPITAL PROVINCIA CORDILLERA | C83: G MANNESCHI | D83: SANTIAGO I | E83: PUENTE ALTO | F83: REGIÓN DE METROPOLITANA DE SANTIAGO | G83: CN61980620 | H83: 61980620 | I83: PUBLICO | J83: GIANCARLO MANNESCHI GALLARDO
A84: 616021982 | B84: HOSPITAL DE PENCO | C84: R ARAYA | D84: SUR I | E84: PENCO | F84: REGIÓN DE BIOBÍO | G84: CN61602198 | H84: 61602198 | I84: PUBLICO | J84: RICARDO ENRIQUE ARAYA GONZÁLEZ
A85: 615130036 | B85: FONDOS PARA HOSPITALES DE CARABINEROS DE CHILE | C85: G MANNESCHI | D85: SANTIAGO I | E85: LAS CONDES | F85: REGIÓN DE METROPOLITANA DE SANTIAGO | G85: CN61513003 | H85: 61513003 | I85: PUBLICO | J85: GIANCARLO MANNESCHI GALLARDO
A86: 616075020 | B86: HOSPITAL VALDIVIA | C86: M RUIZ | D86: SUR II | E86: VALDIVIA | F86: REGIÓN DE LOS RÍOS | G86: CN61607502 | H86: 61607502 | I86: PUBLICO | J86: MARCELO RUIZ
A87: 690726009 | B87: I MUNICIPALIDAD DE PAINE | C87: A TELEFONICA | D87: A TELEFONICA | E87: PAINE | F87: REGIÓN DE METROPOLITANA DE SANTIAGO | G87: CN69072600 | H87: 69072600 | I87: PUBLICO | J87: ATENCION TELEFONICA
A88: 939300007 | B88: CLINICA LAS CONDES S.A. | C88: G MANNESCHI | D88: SANTIAGO I | E88: LAS CONDES | F88: REGIÓN DE METROPOLITANA DE SANTIAGO | G88: CN93930000 | H88: 93930000 | I88: PRIVADO | J88: GIANCARLO MANNESCHI GALLARDO
A89: 616022369 | B89: HOSPITAL DR. ABRAHAM GODOY PEÑA | C89: M RUIZ | D89: SUR II | E89: LAUTARO | F89: REGIÓN DE LA ARAUCANÍA | G89: CN61602236 | H89: 61602236 | I89: PUBLICO | J89: MARCELO RUIZ
A90: 616081071 | B90: HOSPITAL EL PINO | C90: G MANNESCHI | D90: SANTIAGO I | E90: SAN BERNARDO | F90: REGIÓN DE METROPOLITANA DE SANTIAGO | G90: CN61608107 | H90: 61608107 | I90: PUBLICO | J90: GIANCARLO MANNESCHI GALLARDO
A91: 708564001 | B91: CORP MUNIC EDUC SALUD Y AT MEN PTE ALTO | C91: A TELEFONICA | D91: A TELEFONICA | E91: PUENTE ALTO | F91: REGIÓN DE METROPOLITANA DE SANTIAGO | G91: CN70856400 | H91: 70856400 | I91: PUBLICO | J91: ATENCION TELEFONICA
A92: 69191500K | B92: I MUNICIPALIDAD DE VILLARRICA | C92: M RUIZ | D92: SUR II | E92: VILLARRICA | F92: REGIÓN DE LA ARAUCANÍA | G92: CN69191500 | H92: 69191500 | I92: PUBLICO | J92: MARCELO RUIZ
A93: 616063073 | B93: HOSPITAL DE COPIAPO | C93: A TELEFONICA | D93: A TELEFONICA | E93: COPIAPÓ | F93: REGIÓN DE ATACAMA | G93: CN61606307 | H93: 61606307 | I93: PUBLICO | J93: ATENCION TELEFONICA
A94: 616080040 | B94: HOSPITAL DE NIÑOS ROBERTO DEL RIO | C94: M RAMOS | D94: SANTIAGO II | E94: INDEPENDENCIA | F94: REGIÓN DE METROPOLITANA DE SANTIAGO | G94: CN61608004 | H94: 61608004 | I94: PUBLICO | J94: MAURICIO RAMOS MORENO
A95: 70931100K | B95: CORP MUNIC DE RENCA | C95: A TELEFONICA | D95: A TELEFONICA | E95: RENCA | F95: REGIÓN DE METROPOLITANA DE SANTIAGO | G95: CN70931100 | H95: 70931100 | I95: PUBLICO | J95: ATENCION TELEFONICA
A96: 616069012 | B96: HOSPITAL TALCA | C96: SUR III | D96: SUR III | E96: TALCA | F96: REGIÓN DE MAULE | G96: CN61606901 | H96: 61606901 | I96: PUBLICO | J96: ATENCION TELEFONICA
A97: 69081000K | B97: Municipalidad de San Vicente de Tagua Tagua | C97: SUR III | D97: SUR III | E97: SAN VICENTE | F97: REGIÓN DE LIBERTADOR GENERAL BERNARDO O'HIGGINS | G97: CN69081000 | H97: 69081000 | I97: PUBLICO | J97: ATENCION TELEFONICA
A98: 709255002 | B98: CORPORACION MUNICIPAL SAN BERNARDO | C98: A TELEFONICA | D98: A TELEFONICA | E98: SAN BERNARDO | F98: REGIÓN DE METROPOLITANA DE SANTIAGO | G98: CN70925500 | H98: 70925500 | I98: PUBLICO | J98: ATENCION TELEFONICA
A99: 886116004 | B99: CLINICA SANATORIO ALEMAN S.A | C99: R ARAYA | D99: SUR I | E99: CONCEPCIÓN | F99: REGIÓN DE BIOBÍO | G99: CN88611600 | H99: 88611600 | I99: PRIVADO | J99: RICARDO ENRIQUE ARAYA GONZÁLEZ
A100: 774328483 | B100: PACIFIC HEALTH CARE LTDA | C100: A TELEFONICA | D100: A TELEFONICA | E100: QUINTERO | F100: REGIÓN DE VALPARAÍSO | G100: CN77432848 | H100: 77432848 | I100: PRIVADO | J100: ATENCION TELEFONICA
A101: 692538005 | B101: MUNICIPALIDAD LA PINTANA | C101: A TELEFONICA | D101: A TELEFONICA | E101: LA PINTANA | F101: REGIÓN DE METROPOLITANA DE SANTIAGO | G101: CN69253800 | H101: 69253800 | I101: PUBLICO | J101: ATENCION TELEFONICA
A102: 690805006 | B102: I MUNICIPALIDAD DE MOSTAZAL | C102: SUR III | D102: SUR III | E102: MOSTAZAL | F102: REGIÓN DE LIBERTADOR GENERAL BERNARDO O'HIGGINS | G102: CN69080500 | H102: 69080500 | I102: PUBLICO | J102: ATENCION TELEFONICA
A103: 616022229 | B103: HOSPITAL ANGOL | C103: R ARAYA | D103: SUR I | E103: ANGOL | F103: REGIÓN DE LA ARAUCANÍA | G103: CN61602222 | H103: 61602222 | I103: PUBLICO | J103: RICARDO ENRIQUE ARAYA GONZÁLEZ
A104: 692553004 | B104: I. MUNICIPALIDAD DE LA COMUNA DEL BOSQUE | C104: A TELEFONICA | D104: A TELEFONICA | E104: EL BOSQUE | F104: REGIÓN DE METROPOLITANA DE SANTIAGO | G104: CN69255300 | H104: 69255300 | I104: PUBLICO | J104: ATENCION TELEFONICA
A105: 820318005 | B105: FUNDACION HOSPITAL PARROQUIAL SAN BERNARDO | C105: G MANNESCHI | D105: SANTIAGO I | E105: SAN BERNARDO | F105: REGIÓN DE METROPOLITANA DE SANTIAGO | G105: CN82031800 | H105: 82031800 | I105: PRIVADO | J105: GIANCARLO MANNESCHI GALLARDO
A106: 616022016 | B106: HOSPITAL SAN JOSE DE CORONEL | C106: R ARAYA | D106: SUR I | E106: CORONEL | F106: REGIÓN DE BIOBÍO | G106: CN61602201 | H106: 61602201 | I106: PUBLICO | J106: RICARDO ENRIQUE ARAYA GONZÁLEZ
A107: 616081055 | B107: HOSPITAL SAN LUIS | C107: A TELEFONICA | D107: A TELEFONICA | E107: BUIN | F107: REGIÓN DE METROPOLITANA DE SANTIAGO | G107: CN61608105 | H107: 61608105 | I107: PUBLICO | J107: ATENCION TELEFONICA
A108: 995337908 | B108: CLINICA REGIONAL DEL ELQUI SPA | C108: C VALENZUELA | D108: NORTE I | E108: LA SERENA | F108: REGIÓN DE COQUIMBO | G108: CN99533790 | H108: 99533790 | I108: PRIVADO | J108: CONSTANZA VALENZUELA
A109: 760871168 | B109: CMA COSTANERA CMA | C109: M RUIZ | D109: SUR II | E109: VALDIVIA | F109: REGIÓN DE LOS RÍOS | G109: CN76087116 | H109: 76087116 | I109: PRIVADO | J109: MARCELO RUIZ
... A117: 768426007 | B117: CLINICA REGIONAL LIRCAY SPA | C117: SUR III | D117: SUR III | E117: TALCA | F117: REGIÓN DE MAULE | G117: CN76842600 | H117: 76842600 | I117: PRIVADO | J117: ATENCION TELEFONICA
A118: 61979270K | B118: HOSPITAL HANGA ROA | C118: A TELEFONICA | D118: A TELEFONICA | E118: ISLA DE PASCUA | F118: REGIÓN DE VALPARAÍSO | G118: CN61979270 | H118: 61979270 | I118: PUBLICO | J118: ATENCION TELEFONICA
A119: 770253160 | B119: INGENIERIA, SOPORTE Y CADENA DE SUMINISTRO SPA | C119: A TELEFONICA | D119: A TELEFONICA | E119: LAS CONDES | F119: REGIÓN DE METROPOLITANA DE SANTIAGO | G119: CN77025316 | H119: 77025316 | I119: PRIVADO | J119: ATENCION TELEFONICA
A120: 772087233 | B120: B BROTHERS SPA | C120: A TELEFONICA | D120: A TELEFONICA | E120: SANTIAGO | F120: REGIÓN DE METROPOLITANA DE SANTIAGO | G120: CN77208723 | H120: 77208723 | I120: PRIVADO | J120: ATENCION TELEFONICA
A121: 611020252 | B121: HOSPITAL NAVAL TALCAHUANO A.A. | C121: R ARAYA | D121: SUR I | E121: TALCAHUANO | F121: REGIÓN DE BIOBÍO | G121: CN61102025 | H121: 61102025 | I121: PUBLICO | J121: RICARDO ENRIQUE ARAYA GONZÁLEZ
A122: 616063030 | B122: HOSPITAL PROVINCIAL DEL HUASCO MONS FERNANDO ARIZTIA R. | C122: A TELEFONICA | D122: A TELEFONICA | E122: VALLENAR | F122: REGIÓN DE ATACAMA | G122: CN61606303 | H122: 61606303 | I122: PUBLICO | J122: ATENCION TELEFONICA
A123: 716140008 | B123: CLINICA UNIVERSIDAD DE LOS ANDES | C123: G MANNESCHI | D123: SANTIAGO I | E123: LAS CONDES | F123: REGIÓN DE METROPOLITANA DE SANTIAGO | G123: CN71614000 | H123: 71614000 | I123: PRIVADO | J123: GIANCARLO MANNESCHI GALLARDO
A124: 691303012 | B124: ILUSTRE MUNICIPALIDAD DE LINARES | C124: SUR III | D124: SUR III | E124: LINARES | F124: REGIÓN DE MAULE | G124: CN69130301 | H124: 69130301 | I124: PUBLICO | J124: ATENCION TELEFONICA
A125: 966067500 | B125: CLINICA ALEMANA DE TEMUCO S A | C125: M RUIZ | D125: SUR II | E125: TEMUCO | F125: REGIÓN DE LA ARAUCANÍA | G125: CN96606750 | H125: 96606750 | I125: PRIVADO | J125: MARCELO RUIZ
A126: 692651006 | B126: MUNICIPALIDAD DE ALTO HOSPICIO | C126: M RAMOS | D126: SANTIAGO II | E126: ALTO HOSPICIO | F126: REGIÓN DE TARAPACÁ | G126: CN69265100 | H126: 69265100 | I126: PUBLICO | J126: MAURICIO RAMOS MORENO
A127: 692549007 | B127: I. MUNICIPALIDAD PEDRO AGUIRRE CERDA | C127: A TELEFONICA | D127: A TELEFONICA | E127: PEDRO AGUIRRE CERDA | F127: REGIÓN DE METROPOLITANA DE SANTIAGO | G127: CN69254900 | H127: 69254900 | I127: PUBLICO | J127: ATENCION TELEFONICA
...

Sheet CARTERA 2026
A1: RUT | B1: RAZON | C1: COMUNA | D1: REGION | E1: VENDEDOR | F1: COD CLIENTE | G1: INDUSTRIA | H1: SECTOR | I1: CARTERA | J1: REGION NOMBRE
A2: 35178651 | B2: FRANCISCO CAMPOS SANHUEZA | D2: 13 | E2: ATENCION TELEFONICA | F2: CN3517865 | I2: =IF(CARTERA_2026[[#This Row],[RUT]]=774097899,"DIST",_xlfn.XLOOKUP(CARTERA_2026[[#This Row],[VENDEDOR]],dimensiones!$C$21:$C$28,dimensiones!$D$21:$D$28,"")) -> ATEL | J2: =_xlfn.XLOOKUP(CARTERA_2026[[#This Row],[REGION]],dimensiones!C:C,dimensiones!D:D,"") -> Región de Metropolitana de Santiago
A3: 37531235 | B3: ANA ABURDENE | D3: 16 | E3: ATENCION TELEFONICA | F3: CN3753123 | I3: =IF(CARTERA_2026[[#This Row],[RUT]]=774097899,"DIST",_xlfn.XLOOKUP(CARTERA_2026[[#This Row],[VENDEDOR]],dimensiones!$C$21:$C$28,dimensiones!$D$21:$D$28,"")) -> ATEL | J3: =_xlfn.XLOOKUP(CARTERA_2026[[#This Row],[REGION]],dimensiones!C:C,dimensiones!D:D,"") -> Región de Ñuble
A4: 45008673 | B4: CLAUDIO ALVAREZ URRA | C4: SANTIAGO | D4: 13 | E4: ATENCION TELEFONICA | F4: CN4500867 | H4: PRIVADO | I4: =IF(CARTERA_2026[[#This Row],[RUT]]=774097899,"DIST",_xlfn.XLOOKUP(CARTERA_2026[[#This Row],[VENDEDOR]],dimensiones!$C$21:$C$28,dimensiones!$D$21:$D$28,"")) -> ATEL | J4: =_xlfn.XLOOKUP(CARTERA_2026[[#This Row],[REGION]],dimensiones!C:C,dimensiones!D:D,"") -> Región de Metropolitana de Santiago
A5: 50772888 | B5: TERESA DE JESUS ANDRADE ZELADA | D5: 13 | E5: ATENCION TELEFONICA | F5: CN5077288 | I5: =IF(CARTERA_2026[[#This Row],[RUT]]=774097899,"DIST",_xlfn.XLOOKUP(CARTERA_2026[[#This Row],[VENDEDOR]],dimensiones!$C$21:$C$28,dimensiones!$D$21:$D$28,"")) -> ATEL | J5: =_xlfn.XLOOKUP(CARTERA_2026[[#This Row],[REGION]],dimensiones!C:C,dimensiones!D:D,"") -> Región de Metropolitana de Santiago
A6: 53208193 | B6: BELARMINO SEGUNDO DONOSO FUENTES | D6: 13 | E6: ATENCION TELEFONICA | F6: CN5320819 | I6: =IF(CARTERA_2026[[#This Row],[RUT]]=774097899,"DIST",_xlfn.XLOOKUP(CARTERA_2026[[#This Row],[VENDEDOR]],dimensiones!$C$21:$C$28,dimensiones!$D$21:$D$28,"")) -> ATEL | J6: =_xlfn.XLOOKUP(CARTERA_2026[[#This Row],[REGION]],dimensiones!C:C,dimensiones!D:D,"") -> Región de Metropolitana de Santiago
A7: 63890022 | B7: ELIAS CORDOVA RUIZ | D7: 4 | E7: ATENCION TELEFONICA | F7: CN6389002 | I7: =IF(CARTERA_2026[[#This Row],[RUT]]=774097899,"DIST",_xlfn.XLOOKUP(CARTERA_2026[[#This Row],[VENDEDOR]],dimensiones!$C$21:$C$28,dimensiones!$D$21:$D$28,"")) -> ATEL | J7: =_xlfn.XLOOKUP(CARTERA_2026[[#This Row],[REGION]],dimensiones!C:C,dimensiones!D:D,"") -> Región de Coquimbo
A8: 64127217 | B8: DOCTOR SERGIO MAYORGA CIOCCA | D8: 13 | E8: ATENCION TELEFONICA | F8: CN6412721 | I8: =IF(CARTERA_2026[[#This Row],[RUT]]=774097899,"DIST",_xlfn.XLOOKUP(CARTERA_2026[[#This Row],[VENDEDOR]],dimensiones!$C$21:$C$28,dimensiones!$D$21:$D$28,"")) -> ATEL | J8: =_xlfn.XLOOKUP(CARTERA_2026[[#This Row],[REGION]],dimensiones!C:C,dimensiones!D:D,"") -> Región de Metropolitana de Santiago
A9: 64903209 | B9: VICTOR MANUEL BORJE ARAYA | D9: 13 | E9: ATENCION TELEFONICA | F9: CN6490320 | I9: =IF(CARTERA_2026[[#This Row],[RUT]]=774097899,"DIST",_xlfn.XLOOKUP(CARTERA_2026[[#This Row],[VENDEDOR]],dimensiones!$C$21:$C$28,dimensiones!$D$21:$D$28,"")) -> ATEL | J9: =_xlfn.XLOOKUP(CARTERA_2026[[#This Row],[REGION]],dimensiones!C:C,dimensiones!D:D,"") -> Región de Metropolitana de Santiago
A10: 73031095 | B10: JUAN A. RAMIREZ CASTILLO | D10: 9 | E10: ATENCION TELEFONICA | F10: CN7303109 | I10: =IF(CARTERA_2026[[#This Row],[RUT]]=774097899,"DIST",_xlfn.XLOOKUP(CARTERA_2026[[#This Row],[VENDEDOR]],dimensiones!$C$21:$C$28,dimensiones!$D$21:$D$28,"")) -> ATEL | J10: =_xlfn.XLOOKUP(CARTERA_2026[[#This Row],[REGION]],dimensiones!C:C,dimensiones!D:D,"") -> Región de La Araucanía
A11: 79186929 | B11: MANUEL EDUARDO VIDAL BARRIA | D11: 8 | E11: ATENCION TELEFONICA | F11: CN7918692 | I11: =IF(CARTERA_2026[[#This Row],[RUT]]=774097899,"DIST",_xlfn.XLOOKUP(CARTERA_2026[[#This Row],[VENDEDOR]],dimensiones!$C$21:$C$28,dimensiones!$D$21:$D$28,"")) -> ATEL | J11: =_xlfn.XLOOKUP(CARTERA_2026[[#This Row],[REGION]],dimensiones!C:C,dimensiones!D:D,"") -> Región de Biobío
A12: 81818320 | B12: LEOCADIA GONZALEZ TORO | D12: 14 | E12: ATENCION TELEFONICA | F12: CN8181832 | I12: =IF(CARTERA_2026[[#This Row],[RUT]]=774097899,"DIST",_xlfn.XLOOKUP(CARTERA_2026[[#This Row],[VENDEDOR]],dimensiones!$C$21:$C$28,dimensiones!$D$21:$D$28,"")) -> ATEL | J12: =_xlfn.XLOOKUP(CARTERA_2026[[#This Row],[REGION]],dimensiones!C:C,dimensiones!D:D,"") -> Región de Los Ríos
A13: 81850291 | B13: ISABEL LEIVA FUENTEALBA | D13: 16 | E13: ATENCION TELEFONICA | F13: CN8185029 | I13: =IF(CARTERA_2026[[#This Row],[RUT]]=774097899,"DIST",_xlfn.XLOOKUP(CARTERA_2026[[#This Row],[VENDEDOR]],dimensiones!$C$21:$C$28,dimensiones!$D$21:$D$28,"")) -> ATEL | J13: =_xlfn.XLOOKUP(CARTERA_2026[[#This Row],[REGION]],dimensiones!C:C,dimensiones!D:D,"") -> Región de Ñuble
A14: 81853363 | B14: ARTURO GUTIERREZ RUBILAR | D14: 9 | E14: ATENCION TELEFONICA | F14: CN8185336 | I14: =IF(CARTERA_2026[[#This Row],[RUT]]=774097899,"DIST",_xlfn.XLOOKUP(CARTERA_2026[[#This Row],[VENDEDOR]],dimensiones!$C$21:$C$28,dimensiones!$D$21:$D$28,"")) -> ATEL | J14: =_xlfn.XLOOKUP(CARTERA_2026[[#This Row],[REGION]],dimensiones!C:C,dimensiones!D:D,"") -> Región de La Araucanía
A15: 88248228 | B15: ERIKA IVONNE CACERES PAVEZ | D15: 13 | E15: ATENCION TELEFONICA | F15: CN8824822 | I15: =IF(CARTERA_2026[[#This Row],[RUT]]=774097899,"DIST",_xlfn.XLOOKUP(CARTERA_2026[[#This Row],[VENDEDOR]],dimensiones!$C$21:$C$28,dimensiones!$D$21:$D$28,"")) -> ATEL | J15: =_xlfn.XLOOKUP(CARTERA_2026[[#This Row],[REGION]],dimensiones!C:C,dimensiones!D:D,"") -> Región de Metropolitana de Santiago
A16: 91511959 | B16: FRANCISCO JAVIER PARDO QUIROZ | D16: 13 | E16: ATENCION TELEFONICA | F16: CN9151195 | I16: =IF(CARTERA_2026[[#This Row],[RUT]]=774097899,"DIST",_xlfn.XLOOKUP(CARTERA_2026[[#This Row],[VENDEDOR]],dimensiones!$C$21:$C$28,dimensiones!$D$21:$D$28,"")) -> ATEL | J16: =_xlfn.XLOOKUP(CARTERA_2026[[#This Row],[REGION]],dimensiones!C:C,dimensiones!D:D,"") -> Región de Metropolitana de Santiago
... A19: 106711038 | B19: ROSA BURGOS DOMINGUEZ | D19: 3 | E19: ATENCION TELEFONICA | F19: CN10671103 | I19: =IF(CARTERA_2026[[#This Row],[RUT]]=774097899,"DIST",_xlfn.XLOOKUP(CARTERA_2026[[#This Row],[VENDEDOR]],dimensiones!$C$21:$C$28,dimensiones!$D$21:$D$28,"")) -> ATEL | J19: =_xlfn.XLOOKUP(CARTERA_2026[[#This Row],[REGION]],dimensiones!C:C,dimensiones!D:D,"") -> Región de Atacama
A20: 118464397 | B20: CARLOS IGNACIO ARANCIBIA BARRENECHEA | C20: SANTIAGO | D20: 13 | E20: ATENCION TELEFONICA | F20: CN11846439 | H20: PRIVADO | I20: =IF(CARTERA_2026[[#This Row],[RUT]]=774097899,"DIST",_xlfn.XLOOKUP(CARTERA_2026[[#This Row],[VENDEDOR]],dimensiones!$C$21:$C$28,dimensiones!$D$21:$D$28,"")) -> ATEL | J20: =_xlfn.XLOOKUP(CARTERA_2026[[#This Row],[REGION]],dimensiones!C:C,dimensiones!D:D,"") -> Región de Metropolitana de Santiago
A21: 118726197 | B21: PAULA ANDREA RIVERA BRUNET | D21: 8 | E21: ATENCION TELEFONICA | F21: CN11872619 | I21: =IF(CARTERA_2026[[#This Row],[RUT]]=774097899,"DIST",_xlfn.XLOOKUP(CARTERA_2026[[#This Row],[VENDEDOR]],dimensiones!$C$21:$C$28,dimensiones!$D$21:$D$28,"")) -> ATEL | J21: =_xlfn.XLOOKUP(CARTERA_2026[[#This Row],[REGION]],dimensiones!C:C,dimensiones!D:D,"") -> Región de Biobío
A22: 121317834 | B22: HECTOR CARRENO BAEZA | D22: 13 | E22: ATENCION TELEFONICA | F22: CN12131783 | I22: =IF(CARTERA_2026[[#This Row],[RUT]]=774097899,"DIST",_xlfn.XLOOKUP(CARTERA_2026[[#This Row],[VENDEDOR]],dimensiones!$C$21:$C$28,dimensiones!$D$21:$D$28,"")) -> ATEL | J22: =_xlfn.XLOOKUP(CARTERA_2026[[#This Row],[REGION]],dimensiones!C:C,dimensiones!D:D,"") -> Región de Metropolitana de Santiago
A23: 122836576 | B23: MARGARITA RAILEN | D23: 13 | E23: ATENCION TELEFONICA | F23: CN12283657 | I23: =IF(CARTERA_2026[[#This Row],[RUT]]=774097899,"DIST",_xlfn.XLOOKUP(CARTERA_2026[[#This Row],[VENDEDOR]],dimensiones!$C$21:$C$28,dimensiones!$D$21:$D$28,"")) -> ATEL | J23: =_xlfn.XLOOKUP(CARTERA_2026[[#This Row],[REGION]],dimensiones!C:C,dimensiones!D:D,"") -> Región de Metropolitana de Santiago
A24: 150855403 | B24: ANDRES REYES | D24: 5 | E24: ATENCION TELEFONICA | F24: CN15085540 | I24: =IF(CARTERA_2026[[#This Row],[RUT]]=774097899,"DIST",_xlfn.XLOOKUP(CARTERA_2026[[#This Row],[VENDEDOR]],dimensiones!$C$21:$C$28,dimensiones!$D$21:$D$28,"")) -> ATEL | J24: =_xlfn.XLOOKUP(CARTERA_2026[[#This Row],[REGION]],dimensiones!C:C,dimensiones!D:D,"") -> Región de Valparaíso
A25: 161447579 | B25: IVAN CARLOS CANDIA ALDAY | D25: 13 | E25: ATENCION TELEFONICA | F25: CN16144757 | I25: =IF(CARTERA_2026[[#This Row],[RUT]]=774097899,"DIST",_xlfn.XLOOKUP(CARTERA_2026[[#This Row],[VENDEDOR]],dimensiones!$C$21:$C$28,dimensiones!$D$21:$D$28,"")) -> ATEL | J25: =_xlfn.XLOOKUP(CARTERA_2026[[#This Row],[REGION]],dimensiones!C:C,dimensiones!D:D,"") -> Región de Metropolitana de Santiago
A26: 165289676 | B26: MARCO ANTONIO ALBORNOZ SOTO | D26: 6 | E26: ATENCION TELEFONICA | F26: CN16528967 | I26: =IF(CARTERA_2026[[#This Row],[RUT]]=774097899,"DIST",_xlfn.XLOOKUP(CARTERA_2026[[#This Row],[VENDEDOR]],dimensiones!$C$21:$C$28,dimensiones!$D$21:$D$28,"")) -> ATEL | J26: =_xlfn.XLOOKUP(CARTERA_2026[[#This Row],[REGION]],dimensiones!C:C,dimensiones!D:D,"") -> Región de Libertador General Bernardo O'Higgins
A27: 173054734 | B27: ANDREA LUPAYANTE LUPAYÀNTE | D27: 13 | E27: ATENCION TELEFONICA | F27: CN17305473 | I27: =IF(CARTERA_2026[[#This Row],[RUT]]=774097899,"DIST",_xlfn.XLOOKUP(CARTERA_2026[[#This Row],[VENDEDOR]],dimensiones!$C$21:$C$28,dimensiones!$D$21:$D$28,"")) -> ATEL | J27: =_xlfn.XLOOKUP(CARTERA_2026[[#This Row],[REGION]],dimensiones!C:C,dimensiones!D:D,"") -> Región de Metropolitana de Santiago
A28: 176056827 | B28: JUAN ANDRES DIAZ GOMEZ | D28: 8 | E28: ATENCION TELEFONICA | F28: CN17605682 | I28: =IF(CARTERA_2026[[#This Row],[RUT]]=774097899,"DIST",_xlfn.XLOOKUP(CARTERA_2026[[#This Row],[VENDEDOR]],dimensiones!$C$21:$C$28,dimensiones!$D$21:$D$28,"")) -> ATEL | J28: =_xlfn.XLOOKUP(CARTERA_2026[[#This Row],[REGION]],dimensiones!C:C,dimensiones!D:D,"") -> Región de Biobío
A29: 176445467 | B29: HUMBERTO MIERES MORALES | D29: 13 | E29: ATENCION TELEFONICA | F29: CN17644546 | I29: =IF(CARTERA_2026[[#This Row],[RUT]]=774097899,"DIST",_xlfn.XLOOKUP(CARTERA_2026[[#This Row],[VENDEDOR]],dimensiones!$C$21:$C$28,dimensiones!$D$21:$D$28,"")) -> ATEL | J29: =_xlfn.XLOOKUP(CARTERA_2026[[#This Row],[REGION]],dimensiones!C:C,dimensiones!D:D,"") -> Región de Metropolitana de Santiago
A30: 180567933 | B30: LEONARDO QUEZADA VERGARA | D30: 13 | E30: ATENCION TELEFONICA | F30: CN18056793 | I30: =IF(CARTERA_2026[[#This Row],[RUT]]=774097899,"DIST",_xlfn.XLOOKUP(CARTERA_2026[[#This Row],[VENDEDOR]],dimensiones!$C$21:$C$28,dimensiones!$D$21:$D$28,"")) -> ATEL | J30: =_xlfn.XLOOKUP(CARTERA_2026[[#This Row],[REGION]],dimensiones!C:C,dimensiones!D:D,"") -> Región de Metropolitana de Santiago
A31: 188563619 | B31: JAVIER EDUARDO FLORES GOMEZ | D31: 3 | E31: ATENCION TELEFONICA | F31: CN18856361 | I31: =IF(CARTERA_2026[[#This Row],[RUT]]=774097899,"DIST",_xlfn.XLOOKUP(CARTERA_2026[[#This Row],[VENDEDOR]],dimensiones!$C$21:$C$28,dimensiones!$D$21:$D$28,"")) -> ATEL | J31: =_xlfn.XLOOKUP(CARTERA_2026[[#This Row],[REGION]],dimensiones!C:C,dimensiones!D:D,"") -> Región de Atacama
A32: 236451461 | B32: ANA MARIA TICONA APANA | D32: 13 | E32: ATENCION TELEFONICA | F32: CN23645146 | I32: =IF(CARTERA_2026[[#This Row],[RUT]]=774097899,"DIST",_xlfn.XLOOKUP(CARTERA_2026[[#This Row],[VENDEDOR]],dimensiones!$C$21:$C$28,dimensiones!$D$21:$D$28,"")) -> ATEL | J32: =_xlfn.XLOOKUP(CARTERA_2026[[#This Row],[REGION]],dimensiones!C:C,dimensiones!D:D,"") -> Región de Metropolitana de Santiago
... A35: 601030004 | B35: SUBSECRETARIA DE SERVICIOS SOCIALES | D35: 13 | E35: ATENCION TELEFONICA | F35: CN60103000 | I35: =IF(CARTERA_2026[[#This Row],[RUT]]=774097899,"DIST",_xlfn.XLOOKUP(CARTERA_2026[[#This Row],[VENDEDOR]],dimensiones!$C$21:$C$28,dimensiones!$D$21:$D$28,"")) -> ATEL | J35: =_xlfn.XLOOKUP(CARTERA_2026[[#This Row],[REGION]],dimensiones!C:C,dimensiones!D:D,"") -> Región de Metropolitana de Santiago
A36: 602020002 | B36: CAMARA DE DIPUTADOS DE CHILE | C36: VALPARAÍSO | D36: 5 | E36: ATENCION TELEFONICA | F36: CN60202000 | H36: PÚBLICO | I36: =IF(CARTERA_2026[[#This Row],[RUT]]=774097899,"DIST",_xlfn.XLOOKUP(CARTERA_2026[[#This Row],[VENDEDOR]],dimensiones!$C$21:$C$28,dimensiones!$D$21:$D$28,"")) -> ATEL | J36: =_xlfn.XLOOKUP(CARTERA_2026[[#This Row],[REGION]],dimensiones!C:C,dimensiones!D:D,"") -> Región de Valparaíso
A37: 605060005 | B37: POLICIA DE INVESTIGACIONES DE CHILE | D37: 10 | E37: ATENCION TELEFONICA | F37: CN60506000 | I37: =IF(CARTERA_2026[[#This Row],[RUT]]=774097899,"DIST",_xlfn.XLOOKUP(CARTERA_2026[[#This Row],[VENDEDOR]],dimensiones!$C$21:$C$28,dimensiones!$D$21:$D$28,"")) -> ATEL | J37: =_xlfn.XLOOKUP(CARTERA_2026[[#This Row],[REGION]],dimensiones!C:C,dimensiones!D:D,"") -> Región de Los Lagos
A38: 605060129 | B38: ESCUELA DE INVESTIGACIONES POLICIALES (ESCIPOL) | D38: 13 | E38: ATENCION TELEFONICA | F38: CN60506012 | I38: =IF(CARTERA_2026[[#This Row],[RUT]]=774097899,"DIST",_xlfn.XLOOKUP(CARTERA_2026[[#This Row],[VENDEDOR]],dimensiones!$C$21:$C$28,dimensiones!$D$21:$D$28,"")) -> ATEL | J38: =_xlfn.XLOOKUP(CARTERA_2026[[#This Row],[REGION]],dimensiones!C:C,dimensiones!D:D,"") -> Región de Metropolitana de Santiago
A39: 605111300 | B39: INTENDENCIA REGION METROPOLITANA | D39: 13 | E39: ATENCION TELEFONICA | F39: CN60511130 | I39: =IF(CARTERA_2026[[#This Row],[RUT]]=774097899,"DIST",_xlfn.XLOOKUP(CARTERA_2026[[#This Row],[VENDEDOR]],dimensiones!$C$21:$C$28,dimensiones!$D$21:$D$28,"")) -> ATEL | J39: =_xlfn.XLOOKUP(CARTERA_2026[[#This Row],[REGION]],dimensiones!C:C,dimensiones!D:D,"") -> Región de Metropolitana de Santiago
A40: 609020636 | B40: ILUSTRE MUNICIPALIDAD DE LINARES | D40: 7 | E40: ATENCION TELEFONICA | F40: CN60902063 | I40: =IF(CARTERA_2026[[#This Row],[RUT]]=774097899,"DIST",_xlfn.XLOOKUP(CARTERA_2026[[#This Row],[VENDEDOR]],dimensiones!$C$21:$C$28,dimensiones!$D$21:$D$28,"")) -> ATEL | J40: =_xlfn.XLOOKUP(CARTERA_2026[[#This Row],[REGION]],dimensiones!C:C,dimensiones!D:D,"") -> Región de Maule
A41: 609050004 | B41: SERVICIO NACIONAL DEL PATRIMONIO CULTURAL | D41: 4 | E41: ATENCION TELEFONICA | F41: CN60905000 | I41: =IF(CARTERA_2026[[#This Row],[RUT]]=774097899,"DIST",_xlfn.XLOOKUP(CARTERA_2026[[#This Row],[VENDEDOR]],dimensiones!$C$21:$C$28,dimensiones!$D$21:$D$28,"")) -> ATEL | J41: =_xlfn.XLOOKUP(CARTERA_2026[[#This Row],[REGION]],dimensiones!C:C,dimensiones!D:D,"") -> Región de Coquimbo
A42: 609100478 | B42: UNIVERSIDAD METROPOLITANA DE CIENCIAS DE LA EDUCACION | D42: 13 | E42: ATENCION TELEFONICA | F42: CN60910047 | I42: =IF(CARTERA_2026[[#This Row],[RUT]]=774097899,"DIST",_xlfn.XLOOKUP(CARTERA_2026[[#This Row],[VENDEDOR]],dimensiones!$C$21:$C$28,dimensiones!$D$21:$D$28,"")) -> ATEL | J42: =_xlfn.XLOOKUP(CARTERA_2026[[#This Row],[REGION]],dimensiones!C:C,dimensiones!D:D,"") -> Región de Metropolitana de Santiago
A43: 609110066 | B43: UNIVERSIDAD DEL BIO BIO | D43: 8 | E43: ATENCION TELEFONICA | F43: CN60911006 | I43: =IF(CARTERA_2026[[#This Row],[RUT]]=774097899,"DIST",_xlfn.XLOOKUP(CARTERA_2026[[#This Row],[VENDEDOR]],dimensiones!$C$21:$C$28,dimensiones!$D$21:$D$28,"")) -> ATEL | J43: =_xlfn.XLOOKUP(CARTERA_2026[[#This Row],[REGION]],dimensiones!C:C,dimensiones!D:D,"") -> Región de Biobío
A44: 610040071 | B44: DIRECCION REGIONAL DE GENDARMERIA - ANTOFAGASTA | D44: 2 | E44: ATENCION TELEFONICA | F44: CN61004007 | I44: =IF(CARTERA_2026[[#This Row],[RUT]]=774097899,"DIST",_xlfn.XLOOKUP(CARTERA_2026[[#This Row],[VENDEDOR]],dimensiones!$C$21:$C$28,dimensiones!$D$21:$D$28,"")) -> ATEL | J44: =_xlfn.XLOOKUP(CARTERA_2026[[#This Row],[REGION]],dimensiones!C:C,dimensiones!D:D,"") -> Región de Antofagasta
A45: 610040519 | B45: DIRECCION REGIONAL DE GENDARMERIA VII REGION DEL MAULE | D45: 7 | E45: ATENCION TELEFONICA | F45: CN61004051 | I45: =IF(CARTERA_2026[[#This Row],[RUT]]=774097899,"DIST",_xlfn.XLOOKUP(CARTERA_2026[[#This Row],[VENDEDOR]],dimensiones!$C$21:$C$28,dimensiones!$D$21:$D$28,"")) -> ATEL | J45: =_xlfn.XLOOKUP(CARTERA_2026[[#This Row],[REGION]],dimensiones!C:C,dimensiones!D:D,"") -> Región de Maule
A46: 611010176 | B46: ESCUELA MILITAR -ESCMIL | D46: 13 | E46: ATENCION TELEFONICA | F46: CN61101017 | I46: =IF(CARTERA_2026[[#This Row],[RUT]]=774097899,"DIST",_xlfn.XLOOKUP(CARTERA_2026[[#This Row],[VENDEDOR]],dimensiones!$C$21:$C$28,dimensiones!$D$21:$D$28,"")) -> ATEL | J46: =_xlfn.XLOOKUP(CARTERA_2026[[#This Row],[REGION]],dimensiones!C:C,dimensiones!D:D,"") -> Región de Metropolitana de Santiago
A47: 611021275 | B47: CENTRO DE INSTRUCCION Y CAPACITACION MARITIMA | C47: VALPARAÍSO | D47: 5 | E47: ATENCION TELEFONICA | F47: CN61102127 | H47: PRIVADO | I47: =IF(CARTERA_2026[[#This Row],[RUT]]=774097899,"DIST",_xlfn.XLOOKUP(CARTERA_2026[[#This Row],[VENDEDOR]],dimensiones!$C$21:$C$28,dimensiones!$D$21:$D$28,"")) -> ATEL | J47: =_xlfn.XLOOKUP(CARTERA_2026[[#This Row],[REGION]],dimensiones!C:C,dimensiones!D:D,"") -> Región de Valparaíso
A48: 611030207 | B48: FUERZA AEREA DE CHILE | D48: 10 | E48: ATENCION TELEFONICA | F48: CN61103020 | I48: =IF(CARTERA_2026[[#This Row],[RUT]]=774097899,"DIST",_xlfn.XLOOKUP(CARTERA_2026[[#This Row],[VENDEDOR]],dimensiones!$C$21:$C$28,dimensiones!$D$21:$D$28,"")) -> ATEL | J48: =_xlfn.XLOOKUP(CARTERA_2026[[#This Row],[REGION]],dimensiones!C:C,dimensiones!D:D,"") -> Región de Los Lagos
A49: 611030215 | B49: IVª BRIGADA AEREA | C49: PUNTA ARENAS | E49: ATENCION TELEFONICA | F49: CN61103021 | H49: PÚBLICO | I49: =IF(CARTERA_2026[[#This Row],[RUT]]=774097899,"DIST",_xlfn.XLOOKUP(CARTERA_2026[[#This Row],[VENDEDOR]],dimensiones!$C$21:$C$28,dimensiones!$D$21:$D$28,"")) -> ATEL | J49: =_xlfn.XLOOKUP(CARTERA_2026[[#This Row],[REGION]],dimensiones!C:C,dimensiones!D:D,"")
A50: 611030223 | B50: REGIMIENTO DE ARTILLERIA ANTIAEREA Y FUERZAS ESPECIALES | D50: 5 | E50: ATENCION TELEFONICA | F50: CN61103022 | I50: =IF(CARTERA_2026[[#This Row],[RUT]]=774097899,"DIST",_xlfn.XLOOKUP(CARTERA_2026[[#This Row],[VENDEDOR]],dimensiones!$C$21:$C$28,dimensiones!$D$21:$D$28,"")) -> ATEL | J50: =_xlfn.XLOOKUP(CARTERA_2026[[#This Row],[REGION]],dimensiones!C:C,dimensiones!D:D,"") -> Región de Valparaíso
A51: 611030231 | B51: 1A BRIGADA AEREA | D51: 1 | E51: ATENCION TELEFONICA | F51: CN61103023 | I51: =IF(CARTERA_2026[[#This Row],[RUT]]=774097899,"DIST",_xlfn.XLOOKUP(CARTERA_2026[[#This Row],[VENDEDOR]],dimensiones!$C$21:$C$28,dimensiones!$D$21:$D$28,"")) -> ATEL | J51: =_xlfn.XLOOKUP(CARTERA_2026[[#This Row],[REGION]],dimensiones!C:C,dimensiones!D:D,"") -> Región de Tarapacá
A52: 611030320 | B52: FUERZA AEREA DE CHILE COMANDANCIA EN JEFE COMANDO DE PERSONAL | D52: 13 | E52: ATENCION TELEFONICA | F52: CN61103032 | I52: =IF(CARTERA_2026[[#This Row],[RUT]]=774097899,"DIST",_xlfn.XLOOKUP(CARTERA_2026[[#This Row],[VENDEDOR]],dimensiones!$C$21:$C$28,dimensiones!$D$21:$D$28,"")) -> ATEL | J52: =_xlfn.XLOOKUP(CARTERA_2026[[#This Row],[REGION]],dimensiones!C:C,dimensiones!D:D,"") -> Región de Metropolitana de Santiago
A53: 611090005 | B53: DEFENSA CIVIL DE CHILE | D53: 13 | E53: ATENCION TELEFONICA | F53: CN61109000 | I53: =IF(CARTERA_2026[[#This Row],[RUT]]=774097899,"DIST",_xlfn.XLOOKUP(CARTERA_2026[[#This Row],[VENDEDOR]],dimensiones!$C$21:$C$28,dimensiones!$D$21:$D$28,"")) -> ATEL | J53: =_xlfn.XLOOKUP(CARTERA_2026[[#This Row],[REGION]],dimensiones!C:C,dimensiones!D:D,"") -> Región de Metropolitana de Santiago
A54: 612020000 | B54: MINISTERIO DE OBRAS PUBLICAS DIREC CION GRAL DE OO PP DCYF | D54: 13 | E54: ATENCION TELEFONICA | F54: CN61202000 | I54: =IF(CARTERA_2026[[#This Row],[RUT]]=774097899,"DIST",_xlfn.XLOOKUP(CARTERA_2026[[#This Row],[VENDEDOR]],dimensiones!$C$21:$C$28,dimensiones!$D$21:$D$28,"")) -> ATEL | J54: =_xlfn.XLOOKUP(CARTERA_2026[[#This Row],[REGION]],dimensiones!C:C,dimensiones!D:D,"") -> Región de Metropolitana de Santiago
A55: 615330000 | B55: INSTITUTO DE SEGURIDAD LABORAL | D55: 13 | E55: ATENCION TELEFONICA | F55: CN61533000 | I55: =IF(CARTERA_2026[[#This Row],[RUT]]=774097899,"DIST",_xlfn.XLOOKUP(CARTERA_2026[[#This Row],[VENDEDOR]],dimensiones!$C$21:$C$28,dimensiones!$D$21:$D$28,"")) -> ATEL | J55: =_xlfn.XLOOKUP(CARTERA_2026[[#This Row],[REGION]],dimensiones!C:C,dimensiones!D:D,"") -> Región de Metropolitana de Santiago
A56: 616050001 | B56: INSTITUTO DE SALUD PUBLICA | D56: 13 | E56: ATENCION TELEFONICA | F56: CN61605000 | I56: =IF(CARTERA_2026[[#This Row],[RUT]]=774097899,"DIST",_xlfn.XLOOKUP(CARTERA_2026[[#This Row],[VENDEDOR]],dimensiones!$C$21:$C$28,dimensiones!$D$21:$D$28,"")) -> ATEL | J56: =_xlfn.XLOOKUP(CARTERA_2026[[#This Row],[REGION]],dimensiones!C:C,dimensiones!D:D,"") -> Región de Metropolitana de Santiago
A57: 616074008 | B57: SERVICIO DE SALUD ARAUCANIA SUR | D57: 9 | E57: ATENCION TELEFONICA | F57: CN61607400 | I57: =IF(CARTERA_2026[[#This Row],[RUT]]=774097899,"DIST",_xlfn.XLOOKUP(CARTERA_2026[[#This Row],[VENDEDOR]],dimensiones!$C$21:$C$28,dimensiones!$D$21:$D$28,"")) -> ATEL | J57: =_xlfn.XLOOKUP(CARTERA_2026[[#This Row],[REGION]],dimensiones!C:C,dimensiones!D:D,"") -> Región de La Araucanía
A58: 616080008 | B58: SERVICIO DE SALUD METROPOLITANO NORTE | D58: 13 | E58: ATENCION TELEFONICA | F58: CN61608000 | I58: =IF(CARTERA_2026[[#This Row],[RUT]]=774097899,"DIST",_xlfn.XLOOKUP(CARTERA_2026[[#This Row],[VENDEDOR]],dimensiones!$C$21:$C$28,dimensiones!$D$21:$D$28,"")) -> ATEL | J58: =_xlfn.XLOOKUP(CARTERA_2026[[#This Row],[REGION]],dimensiones!C:C,dimensiones!D:D,"") -> Región de Metropolitana de Santiago
A59: 618210006 | B59: SERVIU IX REGION | D59: 9 | E59: ATENCION TELEFONICA | F59: CN61821000 | I59: =IF(CARTERA_2026[[#This Row],[RUT]]=774097899,"DIST",_xlfn.XLOOKUP(CARTERA_2026[[#This Row],[VENDEDOR]],dimensiones!$C$21:$C$28,dimensiones!$D$21:$D$28,"")) -> ATEL | J59: =_xlfn.XLOOKUP(CARTERA_2026[[#This Row],[REGION]],dimensiones!C:C,dimensiones!D:D,"") -> Región de La Araucanía
A60: 619232003 | B60: GOBIERNO REGIONAL METROPOLITANO DE SANTIAGO | D60: 13 | E60: ATENCION TELEFONICA | F60: CN61923200 | I60: =IF(CARTERA_2026[[#This Row],[RUT]]=774097899,"DIST",_xlfn.XLOOKUP(CARTERA_2026[[#This Row],[VENDEDOR]],dimensiones!$C$21:$C$28,dimensiones!$D$21:$D$28,"")) -> ATEL | J60: =_xlfn.XLOOKUP(CARTERA_2026[[#This Row],[REGION]],dimensiones!C:C,dimensiones!D:D,"") -> Región de Metropolitana de Santiago
A61: 619551001 | B61: SERVICIO DE SALUD ARAUCANIA NORTE | D61: 9 | E61: ATENCION TELEFONICA | F61: CN61955100 | I61: =IF(CARTERA_2026[[#This Row],[RUT]]=774097899,"DIST",_xlfn.XLOOKUP(CARTERA_2026[[#This Row],[VENDEDOR]],dimensiones!$C$21:$C$28,dimensiones!$D$21:$D$28,"")) -> ATEL | J61: =_xlfn.XLOOKUP(CARTERA_2026[[#This Row],[REGION]],dimensiones!C:C,dimensiones!D:D,"") -> Región de La Araucanía
... A68: 619991605 | B68: EJERCITO DE CHILE | D68: 1 | E68: ATENCION TELEFONICA | F68: CN61999160 | I68: =IF(CARTERA_2026[[#This Row],[RUT]]=774097899,"DIST",_xlfn.XLOOKUP(CARTERA_2026[[#This Row],[VENDEDOR]],dimensiones!$C$21:$C$28,dimensiones!$D$21:$D$28,"")) -> ATEL | J68: =_xlfn.XLOOKUP(CARTERA_2026[[#This Row],[REGION]],dimensiones!C:C,dimensiones!D:D,"") -> Región de Tarapacá
A69: 619992806 | B69: CENTRO DE FORMACION TECNICA DE LA REGION DE COQUIMBO | C69: COQUIMBO | D69: 4 | E69: ATENCION TELEFONICA | F69: CN61999280 | H69: PRIVADO | I69: =IF(CARTERA_2026[[#This Row],[RUT]]=774097899,"DIST",_xlfn.XLOOKUP(CARTERA_2026[[#This Row],[VENDEDOR]],dimensiones!$C$21:$C$28,dimensiones!$D$21:$D$28,"")) -> ATEL | J69: =_xlfn.XLOOKUP(CARTERA_2026[[#This Row],[REGION]],dimensiones!C:C,dimensiones!D:D,"") -> Región de Coquimbo
A70: 619993306 | B70: SERVICIO LOCAL DE EDUCACION PUBLICA DE HUASCO | D70: 3 | E70: ATENCION TELEFONICA | F70: CN61999330 | I70: =IF(CARTERA_2026[[#This Row],[RUT]]=774097899,"DIST",_xlfn.XLOOKUP(CARTERA_2026[[#This Row],[VENDEDOR]],dimensiones!$C$21:$C$28,dimensiones!$D$21:$D$28,"")) -> ATEL | J70: =_xlfn.XLOOKUP(CARTERA_2026[[#This Row],[REGION]],dimensiones!C:C,dimensiones!D:D,"") -> Región de Atacama
A71: 620008001 | B71: SERVICIO LOCAL DE EDUCACION PUBLICA DE LLANQUIHUE | D71: 10 | E71: ATENCION TELEFONICA | F71: CN62000800 | I71: =IF(CARTERA_2026[[#This Row],[RUT]]=774097899,"DIST",_xlfn.XLOOKUP(CARTERA_2026[[#This Row],[VENDEDOR]],dimensiones!$C$21:$C$28,dimensiones!$D$21:$D$28,"")) -> ATEL | J71: =_xlfn.XLOOKUP(CARTERA_2026[[#This Row],[REGION]],dimensiones!C:C,dimensiones!D:D,"") -> Región de Los Lagos
A72: 620008907 | B72: SERVICIO NACIONAL DE PROTECCION ESPECIALIZADA A LA NIÑEZ Y ADOLESCENCI | C72: CONCEPCIÓN | E72: ATENCION TELEFONICA | F72: CN62000890 | H72: PÚBLICO | I72: =IF(CARTERA_2026[[#This Row],[RUT]]=774097899,"DIST",_xlfn.XLOOKUP(CARTERA_2026[[#This Row],[VENDEDOR]],dimensiones!$C$21:$C$28,dimensiones!$D$21:$D$28,"")) -> ATEL | J72: =_xlfn.XLOOKUP(CARTERA_2026[[#This Row],[REGION]],dimensiones!C:C,dimensiones!D:D,"")
A73: 650778332 | B73: ASOCIACION DE MUNICIPALIDADES NAHUELBUTA | D73: 9 | E73: ATENCION TELEFONICA | F73: CN65077833 | I73: =IF(CARTERA_2026[[#This Row],[RUT]]=774097899,"DIST",_xlfn.XLOOKUP(CARTERA_2026[[#This Row],[VENDEDOR]],dimensiones!$C$21:$C$28,dimensiones!$D$21:$D$28,"")) -> ATEL | J73: =_xlfn.XLOOKUP(CARTERA_2026[[#This Row],[REGION]],dimensiones!C:C,dimensiones!D:D,"") -> Región de La Araucanía
A74: 651429811 | B74: CORPORACION EDUCACIONAL JESUS ANGEL GAZO | D74: 13 | E74: ATENCION TELEFONICA | F74: CN65142981 | I74: =IF(CARTERA_2026[[#This Row],[RUT]]=774097899,"DIST",_xlfn.XLOOKUP(CARTERA_2026[[#This Row],[VENDEDOR]],dimensiones!$C$21:$C$28,dimensiones!$D$21:$D$28,"")) -> ATEL | J74: =_xlfn.XLOOKUP(CARTERA_2026[[#This Row],[REGION]],dimensiones!C:C,dimensiones!D:D,"") -> Región de Metropolitana de Santiago
A75: 651455669 | B75: COLEGIO AMERICANO CE | C75: LA SERENA | D75: 4 | E75: ATENCION TELEFONICA | F75: CN65145566 | H75: PRIVADO | I75: =IF(CARTERA_2026[[#This Row],[RUT]]=774097899,"DIST",_xlfn.XLOOKUP(CARTERA_2026[[#This Row],[VENDEDOR]],dimensiones!$C$21:$C$28,dimensiones!$D$21:$D$28,"")) -> ATEL | J75: =_xlfn.XLOOKUP(CARTERA_2026[[#This Row],[REGION]],dimensiones!C:C,dimensiones!D:D,"") -> Región de Coquimbo
A76: 651536049 | B76: FUNDACION EDUCACIONAL MARGNOL | D76: 8 | E76: ATENCION TELEFONICA | F76: CN65153604 | I76: =IF(CARTERA_2026[[#This Row],[RUT]]=774097899,"DIST",_xlfn.XLOOKUP(CARTERA_2026[[#This Row],[VENDEDOR]],dimensiones!$C$21:$C$28,dimensiones!$D$21:$D$28,"")) -> ATEL | J76: =_xlfn.XLOOKUP(CARTERA_2026[[#This Row],[REGION]],dimensiones!C:C,dimensiones!D:D,"") -> Región de Biobío
A77: 651543983 | B77: CENTRO DE FORMACION TECNICA DE LA REGION DE TARAPA | C77: IQUIQUE | D77: 1 | E77: ATENCION TELEFONICA | F77: CN65154398 | H77: PRIVADO | I77: =IF(CARTERA_2026[[#This Row],[RUT]]=774097899,"DIST",_xlfn.XLOOKUP(CARTERA_2026[[#This Row],[VENDEDOR]],dimensiones!$C$21:$C$28,dimensiones!$D$21:$D$28,"")) -> ATEL | J77: =_xlfn.XLOOKUP(CARTERA_2026[[#This Row],[REGION]],dimensiones!C:C,dimensiones!D:D,"") -> Región de Tarapacá
A78: 651643511 | B78: FUNDACION BIEN COMUN | D78: 15 | E78: ATENCION TELEFONICA | F78: CN65164351 | I78: =IF(CARTERA_2026[[#This Row],[RUT]]=774097899,"DIST",_xlfn.XLOOKUP(CARTERA_2026[[#This Row],[VENDEDOR]],dimensiones!$C$21:$C$28,dimensiones!$D$21:$D$28,"")) -> ATEL | J78: =_xlfn.XLOOKUP(CARTERA_2026[[#This Row],[REGION]],dimensiones!C:C,dimensiones!D:D,"") -> Región de Arica y Parinacota
A79: 651654114 | B79: CENTRO DE FORMACION TECNICA ESTATAL DE LA REGION DE VALPARAISO | C79: VIÑA DEL MAR | D79: 5 | E79: ATENCION TELEFONICA | F79: CN65165411 | H79: PÚBLICO | I79: =IF(CARTERA_2026[[#This Row],[RUT]]=774097899,"DIST",_xlfn.XLOOKUP(CARTERA_2026[[#This Row],[VENDEDOR]],dimensiones!$C$21:$C$28,dimensiones!$D$21:$D$28,"")) -> ATEL | J79: =_xlfn.XLOOKUP(CARTERA_2026[[#This Row],[REGION]],dimensiones!C:C,dimensiones!D:D,"") -> Región de Valparaíso
A80: 654556504 | B80: EJERCITO DE CHILE | C80: ANTOFAGASTA | E80: ATENCION TELEFONICA | F80: CN65455650 | H80: PÚBLICO | I80: =IF(CARTERA_2026[[#This Row],[RUT]]=774097899,"DIST",_xlfn.XLOOKUP(CARTERA_2026[[#This Row],[VENDEDOR]],dimensiones!$C$21:$C$28,dimensiones!$D$21:$D$28,"")) -> ATEL | J80: =_xlfn.XLOOKUP(CARTERA_2026[[#This Row],[REGION]],dimensiones!C:C,dimensiones!D:D,"")
A81: 655525408 | B81: JUZGADO DE FAMILIA DE VILLA ALEMANA | D81: 5 | E81: ATENCION TELEFONICA | F81: CN65552540 | I81: =IF(CARTERA_2026[[#This Row],[RUT]]=774097899,"DIST",_xlfn.XLOOKUP(CARTERA_2026[[#This Row],[VENDEDOR]],dimensiones!$C$21:$C$28,dimensiones!$D$21:$D$28,"")) -> ATEL | J81: =_xlfn.XLOOKUP(CARTERA_2026[[#This Row],[REGION]],dimensiones!C:C,dimensiones!D:D,"") -> Región de Valparaíso
A82: 690702002 | B82: I MUNICIPALIDAD DE CONCHALI | D82: 13 | E82: ATENCION TELEFONICA | F82: CN69070200 | I82: =IF(CARTERA_2026[[#This Row],[RUT]]=774097899,"DIST",_xlfn.XLOOKUP(CARTERA_2026[[#This Row],[VENDEDOR]],dimensiones!$C$21:$C$28,dimensiones!$D$21:$D$28,"")) -> ATEL | J82: =_xlfn.XLOOKUP(CARTERA_2026[[#This Row],[REGION]],dimensiones!C:C,dimensiones!D:D,"") -> Región de Metropolitana de Santiago
A83: 690703009 | B83: I MUNICIPALIDAD DE PROVIDENCIA | D83: 13 | E83: ATENCION TELEFONICA | F83: CN69070300 | I83: =IF(CARTERA_2026[[#This Row],[RUT]]=774097899,"DIST",_xlfn.XLOOKUP(CARTERA_2026[[#This Row],[VENDEDOR]],dimensiones!$C$21:$C$28,dimensiones!$D$21:$D$28,"")) -> ATEL | J83: =_xlfn.XLOOKUP(CARTERA_2026[[#This Row],[REGION]],dimensiones!C:C,dimensiones!D:D,"") -> Región de Metropolitana de Santiago
A84: 690711001 | B84: ILUSTRE MUNICIPALIDAD DE PUDAHUEL | D84: 13 | E84: ATENCION TELEFONICA | F84: CN69071100 | I84: =IF(CARTERA_2026[[#This Row],[RUT]]=774097899,"DIST",_xlfn.XLOOKUP(CARTERA_2026[[#This Row],[VENDEDOR]],dimensiones!$C$21:$C$28,dimensiones!$D$21:$D$28,"")) -> ATEL | J84: =_xlfn.XLOOKUP(CARTERA_2026[[#This Row],[REGION]],dimensiones!C:C,dimensiones!D:D,"") -> Región de Metropolitana de Santiago
A85: 690718014 | B85: CORPORACION MUNIC DE EDUC SALUD ATENCION | D85: 13 | E85: ATENCION TELEFONICA | F85: CN69071801 | I85: =IF(CARTERA_2026[[#This Row],[RUT]]=774097899,"DIST",_xlfn.XLOOKUP(CARTERA_2026[[#This Row],[VENDEDOR]],dimensiones!$C$21:$C$28,dimensiones!$D$21:$D$28,"")) -> ATEL | J85: =_xlfn.XLOOKUP(CARTERA_2026[[#This Row],[REGION]],dimensiones!C:C,dimensiones!D:D,"") -> Región de Metropolitana de Santiago
A86: 690729008 | B86: ILUSTRE MUNICIPALIDAD DE MELIPILLA | D86: 13 | E86: ATENCION TELEFONICA | F86: CN69072900 | I86: =IF(CARTERA_2026[[#This Row],[RUT]]=774097899,"DIST",_xlfn.XLOOKUP(CARTERA_2026[[#This Row],[VENDEDOR]],dimensiones!$C$21:$C$28,dimensiones!$D$21:$D$28,"")) -> ATEL | J86: =_xlfn.XLOOKUP(CARTERA_2026[[#This Row],[REGION]],dimensiones!C:C,dimensiones!D:D,"") -> Región de Metropolitana de Santiago
A87: 690739003 | B87: ILUSTRE MUNICIPALIDAD DE CURACAVI | D87: 13 | E87: ATENCION TELEFONICA | F87: CN69073900 | I87: =IF(CARTERA_2026[[#This Row],[RUT]]=774097899,"DIST",_xlfn.XLOOKUP(CARTERA_2026[[#This Row],[VENDEDOR]],dimensiones!$C$21:$C$28,dimensiones!$D$21:$D$28,"")) -> ATEL | J87: =_xlfn.XLOOKUP(CARTERA_2026[[#This Row],[REGION]],dimensiones!C:C,dimensiones!D:D,"") -> Región de Metropolitana de Santiago
A88: 690803003 | B88: I MUNICIPALIDAD DE GRANEROS | D88: 6 | E88: ATENCION TELEFONICA | F88: CN69080300 | I88: =IF(CARTERA_2026[[#This Row],[RUT]]=774097899,"DIST",_xlfn.XLOOKUP(CARTERA_2026[[#This Row],[VENDEDOR]],dimensiones!$C$21:$C$28,dimensiones!$D$21:$D$28,"")) -> ATEL | J88: =_xlfn.XLOOKUP(CARTERA_2026[[#This Row],[REGION]],dimensiones!C:C,dimensiones!D:D,"") -> Región de Libertador General Bernardo O'Higgins
A89: 690912015 | B89: ILUSTRE MUNICIPALIDAD DE PICHILEMU | D89: 6 | E89: ATENCION TELEFONICA | F89: CN69091201 | I89: =IF(CARTERA_2026[[#This Row],[RUT]]=774097899,"DIST",_xlfn.XLOOKUP(CARTERA_2026[[#This Row],[VENDEDOR]],dimensiones!$C$21:$C$28,dimensiones!$D$21:$D$28,"")) -> ATEL | J89: =_xlfn.XLOOKUP(CARTERA_2026[[#This Row],[REGION]],dimensiones!C:C,dimensiones!D:D,"") -> Región de Libertador General Bernardo O'Higgins
A90: 691407004 | B90: I. MUNICIPALIDAD DE SAN FABIAN | D90: 8 | E90: ATENCION TELEFONICA | F90: CN69140700 | I90: =IF(CARTERA_2026[[#This Row],[RUT]]=774097899,"DIST",_xlfn.XLOOKUP(CARTERA_2026[[#This Row],[VENDEDOR]],dimensiones!$C$21:$C$28,dimensiones!$D$21:$D$28,"")) -> ATEL | J90: =_xlfn.XLOOKUP(CARTERA_2026[[#This Row],[REGION]],dimensiones!C:C,dimensiones!D:D,"") -> Región de Biobío
A91: 691408000 | B91: ILUSTRE MUNICIPALIDAD DE SAN NICOLAS | D91: 16 | E91: ATENCION TELEFONICA | F91: CN69140800 | I91: =IF(CARTERA_2026[[#This Row],[RUT]]=774097899,"DIST",_xlfn.XLOOKUP(CARTERA_2026[[#This Row],[VENDEDOR]],dimensiones!$C$21:$C$28,dimensiones!$D$21:$D$28,"")) -> ATEL | J91: =_xlfn.XLOOKUP(CARTERA_2026[[#This Row],[REGION]],dimensiones!C:C,dimensiones!D:D,"") -> Región de Ñuble
A92: 691511022 | B92: ILUSTRE MUNICIPALIDAD DE SAN ROSENDO - SALUD | D92: 8 | E92: ATENCION TELEFONICA | F92: CN69151102 | I92: =IF(CARTERA_2026[[#This Row],[RUT]]=774097899,"DIST",_xlfn.XLOOKUP(CARTERA_2026[[#This Row],[VENDEDOR]],dimensiones!$C$21:$C$28,dimensiones!$D$21:$D$28,"")) -> ATEL | J92: =_xlfn.XLOOKUP(CARTERA_2026[[#This Row],[REGION]],dimensiones!C:C,dimensiones!D:D,"") -> Región de Biobío
... A95: 692403002 | B95: I MUNICIPALIDAD DE COYHAIQUE | D95: 11 | E95: ATENCION TELEFONICA | F95: CN69240300 | I95: =IF(CARTERA_2026[[#This Row],[RUT]]=774097899,"DIST",_xlfn.XLOOKUP(CARTERA_2026[[#This Row],[VENDEDOR]],dimensiones!$C$21:$C$28,dimensiones!$D$21:$D$28,"")) -> ATEL | J95: =_xlfn.XLOOKUP(CARTERA_2026[[#This Row],[REGION]],dimensiones!C:C,dimensiones!D:D,"") -> Región de Aysén del General Carlos Ibáñez del Campo
A96: 692532007 | B96: I MUNICIPALIDAD DE SIERRA GORDA | C96: SIERRA GORDA | E96: ATENCION TELEFONICA | F96: CN69253200 | H96: PÚBLICO | I96: =IF(CARTERA_2026[[#This Row],[RUT]]=774097899,"DIST",_xlfn.XLOOKUP(CARTERA_2026[[#This Row],[VENDEDOR]],dimensiones!$C$21:$C$28,dimensiones!$D$21:$D$28,"")) -> ATEL | J96: =_xlfn.XLOOKUP(CARTERA_2026[[#This Row],[REGION]],dimensiones!C:C,dimensiones!D:D,"")
A97: 707291001 | B97: UNIVERSIDAD TECNOLOGICA | D97: 13 | E97: ATENCION TELEFONICA | F97: CN70729100 | I97: =IF(CARTERA_2026[[#This Row],[RUT]]=774097899,"DIST",_xlfn.XLOOKUP(CARTERA_2026[[#This Row],[VENDEDOR]],dimensiones!$C$21:$C$28,dimensiones!$D$21:$D$28,"")) -> ATEL | J97: =_xlfn.XLOOKUP(CARTERA_2026[[#This Row],[REGION]],dimensiones!C:C,dimensiones!D:D,"") -> Región de Metropolitana de Santiago
A98: 707721006 | B98: UNIVERSIDAD DE LOS LAGOS | D98: 10 | E98: ATENCION TELEFONICA | F98: CN70772100 | I98: =IF(CARTERA_2026[[#This Row],[RUT]]=774097899,"DIST",_xlfn.XLOOKUP(CARTERA_2026[[#This Row],[VENDEDOR]],dimensiones!$C$21:$C$28,dimensiones!$D$21:$D$28,"")) -> ATEL | J98: =_xlfn.XLOOKUP(CARTERA_2026[[#This Row],[REGION]],dimensiones!C:C,dimensiones!D:D,"") -> Región de Los Lagos
A99: 712367008 | B99: UNIVERSIDAD DE ATACAMA | D99: 3 | E99: ATENCION TELEFONICA | F99: CN71236700 | I99: =IF(CARTERA_2026[[#This Row],[RUT]]=774097899,"DIST",_xlfn.XLOOKUP(CARTERA_2026[[#This Row],[VENDEDOR]],dimensiones!$C$21:$C$28,dimensiones!$D$21:$D$28,"")) -> ATEL | J99: =_xlfn.XLOOKUP(CARTERA_2026[[#This Row],[REGION]],dimensiones!C:C,dimensiones!D:D,"") -> Región de Atacama
A100: 713098000 | B100: CORPORACION MUNICIPAL DE SERVICIOS Y DESARROLLO MAIPU | D100: 13 | E100: ATENCION TELEFONICA | F100: CN71309800 | I100: =IF(CARTERA_2026[[#This Row],[RUT]]=774097899,"DIST",_xlfn.XLOOKUP(CARTERA_2026[[#This Row],[VENDEDOR]],dimensiones!$C$21:$C$28,dimensiones!$D$21:$D$28,"")) -> ATEL | J100: =_xlfn.XLOOKUP(CARTERA_2026[[#This Row],[REGION]],dimensiones!C:C,dimensiones!D:D,"") -> Región de Metropolitana de Santiago
A101: 723960002 | B101: CORP NACIONAL DE DESARROLLO INDIGENA | D101: 9 | E101: ATENCION TELEFONICA | F101: CN72396000 | I101: =IF(CARTERA_2026[[#This Row],[RUT]]=774097899,"DIST",_xlfn.XLOOKUP(CARTERA_2026[[#This Row],[VENDEDOR]],dimensiones!$C$21:$C$28,dimensiones!$D$21:$D$28,"")) -> ATEL | J101: =_xlfn.XLOOKUP(CARTERA_2026[[#This Row],[REGION]],dimensiones!C:C,dimensiones!D:D,"") -> Región de La Araucanía
A102: 739238005 | B102: ZONA BIENESTAR VALPARAISO" BIENESTAR SOCIAL" | D102: 8 | E102: ATENCION TELEFONICA | F102: CN73923800 | I102: =IF(CARTERA_2026[[#This Row],[RUT]]=774097899,"DIST",_xlfn.XLOOKUP(CARTERA_2026[[#This Row],[VENDEDOR]],dimensiones!$C$21:$C$28,dimensiones!$D$21:$D$28,"")) -> ATEL | J102: =_xlfn.XLOOKUP(CARTERA_2026[[#This Row],[REGION]],dimensiones!C:C,dimensiones!D:D,"") -> Región de Biobío
A103: 748229000 | B103: FUND CENTRO DE EDUCACION Y CAPACITACION DE LA UCN | D103: 4 | E103: ATENCION TELEFONICA | F103: CN74822900 | I103: =IF(CARTERA_2026[[#This Row],[RUT]]=774097899,"DIST",_xlfn.XLOOKUP(CARTERA_2026[[#This Row],[VENDEDOR]],dimensiones!$C$21:$C$28,dimensiones!$D$21:$D$28,"")) -> ATEL | J103: =_xlfn.XLOOKUP(CARTERA_2026[[#This Row],[REGION]],dimensiones!C:C,dimensiones!D:D,"") -> Región de Coquimbo
A104: 760163058 | B104: SOCIEDAD RADIOLOGICA CHILLAN S.A. | D104: 16 | E104: ATENCION TELEFONICA | F104: CN76016305 | I104: =IF(CARTERA_2026[[#This Row],[RUT]]=774097899,"DIST",_xlfn.XLOOKUP(CARTERA_2026[[#This Row],[VENDEDOR]],dimensiones!$C$21:$C$28,dimensiones!$D$21:$D$28,"")) -> ATEL | J104: =_xlfn.XLOOKUP(CARTERA_2026[[#This Row],[REGION]],dimensiones!C:C,dimensiones!D:D,"") -> Región de Ñuble
A105: 760286885 | B105: LOGISCARGO CHILE ALEJANDRO SAN MARTIN CARRASCO E.I.R.L | D105: 13 | E105: ATENCION TELEFONICA | F105: CN76028688 | I105: =IF(CARTERA_2026[[#This Row],[RUT]]=774097899,"DIST",_xlfn.XLOOKUP(CARTERA_2026[[#This Row],[VENDEDOR]],dimensiones!$C$21:$C$28,dimensiones!$D$21:$D$28,"")) -> ATEL | J105: =_xlfn.XLOOKUP(CARTERA_2026[[#This Row],[REGION]],dimensiones!C:C,dimensiones!D:D,"") -> Región de Metropolitana de Santiago
A106: 760449598 | B106: ARLAB S.A. | D106: 13 | E106: ATENCION TELEFONICA | F106: CN76044959 | I106: =IF(CARTERA_2026[[#This Row],[RUT]]=774097899,"DIST",_xlfn.XLOOKUP(CARTERA_2026[[#This Row],[VENDEDOR]],dimensiones!$C$21:$C$28,dimensiones!$D$21:$D$28,"")) -> ATEL | J106: =_xlfn.XLOOKUP(CARTERA_2026[[#This Row],[REGION]],dimensiones!C:C,dimensiones!D:D,"") -> Región de Metropolitana de Santiago
A107: 760700339 | B107: ARAMA NATURAL PRODUCTS DISTRIBUIDORA LIMITADA | D107: 13 | E107: ATENCION TELEFONICA | F107: CN76070033 | I107: =IF(CARTERA_2026[[#This Row],[RUT]]=774097899,"DIST",_xlfn.XLOOKUP(CARTERA_2026[[#This Row],[VENDEDOR]],dimensiones!$C$21:$C$28,dimensiones!$D$21:$D$28,"")) -> ATEL | J107: =_xlfn.XLOOKUP(CARTERA_2026[[#This Row],[REGION]],dimensiones!C:C,dimensiones!D:D,"") -> Región de Metropolitana de Santiago
A108: 760742163 | B108: RESONANCIA MAGNETICA DEL NORTE S.A. | D108: 4 | E108: ATENCION TELEFONICA | F108: CN76074216 | I108: =IF(CARTERA_2026[[#This Row],[RUT]]=774097899,"DIST",_xlfn.XLOOKUP(CARTERA_2026[[#This Row],[VENDEDOR]],dimensiones!$C$21:$C$28,dimensiones!$D$21:$D$28,"")) -> ATEL | J108: =_xlfn.XLOOKUP(CARTERA_2026[[#This Row],[REGION]],dimensiones!C:C,dimensiones!D:D,"") -> Región de Coquimbo
... A111: 761108921 | B111: JORGE SEPULVEDA GONZAÑEZ DD, E.I.R.L | D111: 13 | E111: ATENCION TELEFONICA | F111: CN76110892 | I111: =IF(CARTERA_2026[[#This Row],[RUT]]=774097899,"DIST",_xlfn.XLOOKUP(CARTERA_2026[[#This Row],[VENDEDOR]],dimensiones!$C$21:$C$28,dimensiones!$D$21:$D$28,"")) -> ATEL | J111: =_xlfn.XLOOKUP(CARTERA_2026[[#This Row],[REGION]],dimensiones!C:C,dimensiones!D:D,"") -> Región de Metropolitana de Santiago
A112: 761111132 | B112: CLINICAL MARKET S.A | C112: SANTIAGO | D112: 13 | E112: ATENCION TELEFONICA | F112: CN76111113 | H112: PRIVADO | I112: =IF(CARTERA_2026[[#This Row],[RUT]]=774097899,"DIST",_xlfn.XLOOKUP(CARTERA_2026[[#This Row],[VENDEDOR]],dimensiones!$C$21:$C$28,dimensiones!$D$21:$D$28,"")) -> ATEL | J112: =_xlfn.XLOOKUP(CARTERA_2026[[#This Row],[REGION]],dimensiones!C:C,dimensiones!D:D,"") -> Región de Metropolitana de Santiago
A113: 761162209 | B113: BARRIA Y CONTRERAS LTDA | D113: 10 | E113: ATENCION TELEFONICA | F113: CN76116220 | I113: =IF(CARTERA_2026[[#This Row],[RUT]]=774097899,"DIST",_xlfn.XLOOKUP(CARTERA_2026[[#This Row],[VENDEDOR]],dimensiones!$C$21:$C$28,dimensiones!$D$21:$D$28,"")) -> ATEL | J113: =_xlfn.XLOOKUP(CARTERA_2026[[#This Row],[REGION]],dimensiones!C:C,dimensiones!D:D,"") -> Región de Los Lagos
A114: 761175971 | B114: SERVICIOS MEDICOS OFTALMOLOGICOS CEOLA VIÑA DEL MAR S.A. | D114: 5 | E114: ATENCION TELEFONICA | F114: CN76117597 | I114: =IF(CARTERA_2026[[#This Row],[RUT]]=774097899,"DIST",_xlfn.XLOOKUP(CARTERA_2026[[#This Row],[VENDEDOR]],dimensiones!$C$21:$C$28,dimensiones!$D$21:$D$28,"")) -> ATEL | J114: =_xlfn.XLOOKUP(CARTERA_2026[[#This Row],[REGION]],dimensiones!C:C,dimensiones!D:D,"") -> Región de Valparaíso
...

Sheet cnb
C1: Rut Facturador | D1: k | G1: Código SN | H1: Nombre SN | I1: Número de identificación fiscal | L1: 61602040-4
C2: 61602212-1 | D2: =_xlfn.XLOOKUP(C2,I:I,G:G,"") -> CN61602212 | G2: CN69110400 | H2: I MUNICIPALIDAD DE TALCA | I2: 69110400-1
C3: 61602236-9 | D3: =_xlfn.XLOOKUP(C3,I:I,G:G,"") -> CN61602236 | G3: CN69051000 | H3: I MUNICIPALIDAD DE SANTA MARIA | I3: 69051000-6
C4: 61606404-5 | D4: =_xlfn.XLOOKUP(C4,I:I,G:G,"") -> CN61606404 | G4: CN69254900 | H4: I. MUNICIPALIDAD PEDRO AGUIRRE CERDA | I4: 69254900-7
C5: 61606913-6 | D5: =_xlfn.XLOOKUP(C5,I:I,G:G,"") -> CN61606913 | G5: CN69100200 | H5: MUNICIPALIDAD ROMERAL | I5: 69100200-4
C6: 62000830-3 | D6: =_xlfn.XLOOKUP(C6,I:I,G:G,"") -> CN62000830 | G6: CN61602312 | H6: HOSPITAL ALTO PALENA | I6: 61602312-8
C7: 69010100-9 | D7: =_xlfn.XLOOKUP(C7,I:I,G:G,"") -> CN69010100 | G7: CN69220800 | H7: ILUSTRE MUNICIPALIDAD DE LOS MUERMOS | I7: 69220800-5
C8: 69141300-4 | D8: =_xlfn.XLOOKUP(C8,I:I,G:G,"") -> CN69141300 | G8: CN69170402 | H8: I. MUNICIPALIDAD QUILLECO | I8: 69170402-5
C9: 69141300-4 | D9: =_xlfn.XLOOKUP(C9,I:I,G:G,"") -> CN69141300 | G9: CN69110700 | H9: ILUSTRE MUNICIPALIDAD DE RIO CLARO | I9: 69110700-0
C10: 69150502-2 | D10: =_xlfn.XLOOKUP(C10,I:I,G:G,"") -> CN69150502 | G10: CN61602224 | H10: HOSPITAL PUREN | I10: 61602224-5
C11: 69254800-0 | D11: =_xlfn.XLOOKUP(C11,I:I,G:G,"") -> CN69254800 | G11: PN97023000 | H11: BANCO ITAU CHILE | I11: 97023000-9
C12: 69255300-4 | D12: =_xlfn.XLOOKUP(C12,I:I,G:G,"") -> CN69255300 | G12: CN69050800 | H12: I MUNICIPALIDAD DE PANQUEHUE | I12: 69050800-1
C13: 69261400-3 | D13: =_xlfn.XLOOKUP(C13,I:I,G:G,"") -> CN69261400 | G13: CN53335808 | H13: CONS EXTERNO VALDIVIA | I13: 53335808-K
... C83: 62000830-3 | D83: =_xlfn.XLOOKUP(C83,I:I,G:G,"") -> CN62000830 | G83: CN61606402 | H83: HOSPITAL LA SERENA | I83: 61606402-9
G84: CN69260400 | H84: MUNIC QUILLOTA DPTO SALUD | I84: 69260400-8
G85: CN70983600 | H85: CORP.MUNICIPAL PARA DES.SOCIAL-V.ALEMANA | I85: 70983600-5
G86: CN61606905 | H86: HOSPITAL LICANTEN | I86: 61606905-5
G87: CN61602248 | H87: HOSPITAL VILLARRICA | I87: 61602248-2
G88: CN69191200 | H88: ILUSTRE MUNICIPALIDAD DE GORBEA | I88: 69191200-0
G89: CN61606911 | H89: HOSPITAL DE CONSTITUCION | I89: 61606911-K
G90: CN69200300 | H90: MUNIC LANCO | I90: 69200300-4
G91: CN69060200 | H91: I MUNICIPALIDAD DE LA CRUZ | I91: 69060200-8
G92: CN61606915 | H92: HOSPITAL CHANCO | I92: 61606915-2
G93: CN65311270 | H93: CENTRO CLINICO MILITAR CONCEPCION | I93: 65311270-K
G94: CN77223544 | H94: COMERCIALIZADORA Y DISTRIBUIDORA VASSAN LTDA | I94: 77223544-5
G95: BH4524354 | H95: GERMAN DEL FIERRO MERY | I95: 4524354-0
... G335: CN61602262 | H335: HOSPITAL RIO NEGRO | I335: 61602262-8
G336: EM154270272 | H336: MARCELO ALEXIS RUIZ RUIZ | I336: 154270272
G337: CN69151100 | H337: MUNICIPALIDAD SAN ROSENDO | I337: 69151100-6
G338: CN61606907 | H338: HOSPITAL TENO | I338: 61606907-1
G339: CN69151400 | H339: MUNICIPALIDAD SANTA JUANA | I339: 69151400-5
G340: CN69190700 | H340: MUNICIPALIDAD DE TEMUCO | I340: 69190700-7
G341: CN70933700 | H341: CORP MUNICIPAL DE EDUC SALUD CULTURA Y RECREACION DE LA FLORIDA | I341: 70933700-9
G342: CN69151202 | H342: I MUNICIPALIDAD DE CORONEL DPTO ADMINIST | I342: 69151202-9
G343: CN61607508 | H343: HOSPITAL RIO BUENO | I343: 61607508-K
G344: CN61602198 | H344: HOSPITAL DE PENCO | I344: 61602198-2
G345: EM25343424 | H345: YELISMAR ARLEIDY CHACON | I345: 25343424-4
G346: CN69080400 | H346: ILUSTRE MUNICIPALIDAD DE CODEGUA | I346: 69080400-K
G347: CN69030300 | H347: I MUNICIPALIDAD DE CALDERA | I347: 69030300-0
G348: CN69170300 | H348: MUNICIPALIDAD LAJA | I348: 69170300-2
... G366: CN69190600 | H366: I MUNICIPALIDAD DE SAAVEDRA | I366: 69190600-0
G367: BH267722250 | H367: RUBEN DARIO BRACHO | I367: 267722250
G368: CN61602299 | H368: HOSPITAL PUERTO SAAVEDRA | I368: 61602299-7
G369: CN61602126 | H369: HOSPITAL CLAUDIO VICUÑA | I369: 61602126-5
G370: CN96598850 | H370: CLINICA IQUIQUE S.A. | I370: 96598850-5
G371: CN69191100 | H371: ILUSTRE MUNICIPALIDAD DE LONCOCHE | I371: 69191100-4
G372: CN61606917 | H372: HOSPITAL LINARES | I372: 61606917-9
G373: CN69191300 | H373: I MUNICIPALIDAD DE PITRUFQUEN | I373: 69191300-7
G374: CN61606204 | H374: HOSPITAL DE TALTAL | I374: 61606204-2
G375: CN76562618 | H375: SOCIEDAD COMERCIAL NORFARMA LIMITADA | I375: 76562618-8
G376: CN69200100 | H376: I MUNICIPALIDAD VALDIVIA | I376: 69200100-1
G377: CN70859400 | H377: CORPORACION MUNICIPAL VALPARAISO | I377: 70859400-8
G378: CN69200500 | H378: MUNIC.MAFIL | I378: 69200500-7
G379: CN69200600 | H379: I MUNICIPALIDAD DE LOS LAGOS | I379: 69200600-3
... G834: PN96910280 | H834: BIOCLIN S.A. | I834: 96910280-3
G835: EM20670772 | H835: RODRIGO CRUZ | I835: 206707720
G836: CN77439330 | H836: FARMACIA SETOP PHARMA LTDA | I836: 77439330-7
G837: CN77439686 | H837: PATIPERROS PET SPA | I837: 77439686-1
G838: BH26710447 | H838: PIERINA LOAYZA RAMIREZ | I838: 26710447-6
G839: CN77444879 | H839: EXCELMED SPA | I839: 77444879-9
G840: CN77483197 | H840: CLINICA ALONSO DE CORDOVA SPA | I840: 77483197-5
G841: CN77488919 | H841: SERVICIOS DE SALUD CAROLINA PANZA E.I.R.L | I841: 77488919-1
G842: CN77490090 | H842: SERVICIOS MEDICOS REDMEDICA LTDA. | I842: 77490090-K
G843: CN77501379 | H843: INSUMEDICAL SPA | I843: 77501379-6
G844: CN77504681 | H844: COMERCIAL CARANDAY SPA | I844: 77504681-3
G845: CN61602238 | H845: HOSPITAL PITRUFQUEN | I845: 61602238-5
G846: CN77518471 | H846: SERVICIOS CASTILLO CASTILLO LIMITADA | I846: 77518471-K
G847: CN61602270 | H847: HOSPITAL DE FRUTILLAR | I847: 61602270-9
... G985: CN96613220 | H985: CORPORACION MEDICA DE ARICA S.A. | I985: 96613220-5
G986: EM260414356 | H986: ANAIS MILAGROS CHAVEZ | I986: 260414356
G987: PN96806980 | H987: ENTEL PCS TELECOMUNICACIONES S A | I987: 96806980-2
G988: PN77971250 | H988: CUC ETIQUETAS Y EQUIPOS DE CODIGOS DE BARRA Y TRANSPORTE LIMITADA | I988: 77971250-8
G989: CN76057904 | H989: HOSPITAL CLINICO DEL SUR | I989: 76057904-1
G990: CN77619085 | H990: SERVICIOS E INSUMOS MEDICOS SPA | I990: 77619085-3
G991: CN76882794 | H991: COMERCIALIZADORA Y SERVICIOS INTEGRALES MARCO ANTONIO HENRIQUEZ BUSTAMANTE E.I.R.L. | I991: 76882794-k
G992: CN96982520 | H992: CENTRO AVANZADO DE TRATAMIENTO DE HERIDAS SA | I992: 96982520-1
G993: CN76977045 | H993: ORANGE RETAIL SPA | I993: 76977045-3
G994: CN69190100 | H994: I MUNICIPALIDAD DE LAUTARO | I994: 69190100-9
G995: EM18695828 | H995: BETZABE ANDREA TORO | I995: 18695828-4
G996: CN61608107 | H996: HOSPITAL EL PINO | I996: 61608107-1
G997: EM19884240 | H997: JAVIERA IGNACIA GACITUA | I997: 19884240-0
G998: EM21002291 | H998: PATRICIA NALLELY TOLOZA | I998: 21002291-0
... G1325: PN77379090 | H1325: ROHLIG TRANSPORTES INTERNACIONALES CHILE LIMITADA | I1325: 77379090-6

Sheet dimensiones
C2: Region | D2: Nombre Región | I2: RUT
C3: 1 | D3: Región de Tarapacá | I3: 616084038
C4: 2 | D4: Región de Antofagasta | I4: 616084070
C5: 3 | D5: Región de Atacama | I5: 616084089
C6: 4 | D6: Región de Coquimbo | I6: 619794508
C7: 5 | D7: Región de Valparaíso | I7: 703774008
C8: 6 | D8: Región de Libertador General Bernardo O'Higgins | I8: 780405201
C9: 7 | D9: Región de Maule | I9: 907530000
C10: 8 | D10: Región de Biobío | I10: 61608402K
C11: 9 | D11: Región de La Araucanía | I11: 616021389
C12: 10 | D12: Región de Los Lagos | I12: 709057006
C13: 11 | D13: Región de Aysén del General Carlos Ibáñez del Campo | I13: 710142009
C14: 12 | D14: Región de Magallanes y de la Antártica Chilena | I14: 966624507
C15: 13 | D15: Región de Metropolitana de Santiago | I15: 782302302
C16: 14 | D16: Región de Los Ríos | I16: 789182906
C17: 15 | D17: Región de Arica y Parinacota | I17: 616069179
C18: 16 | D18: Región de Ñuble | I18: 691104001
I19: 691303012
I20: 616069039
C21: VENDEDOR | D21: CARTERA | I21: 616069012
C22: ATENCION TELEFONICA | D22: ATEL | I22: 768426007
C23: MAURICIO RAMOS MORENO | D23: SANT2 | I23: 691001008
C24: GIANCARLO MANNESCHI GALLARDO | D24: SANT1 | I24: 967591904
C25: CONSTANZA VALENZUELA | D25: NOR1 | I25: 616086057
C26: RICARDO ENRIQUE ARAYA GONZÁLEZ | D26: SUR1 | I26: 616081055
C27: MARCELO RUIZ | D27: SUR2 | I27: 766862357
C28: MARCO MARINAO | D28: SANT3 | I28: 708352004
I29: 616021451
I30: 713286001

Sheet Hoja1
A1: RUT | B1: RAZON | C1: COMUNA | D1: REGION | E1: VENDEDOR | F1: COD CLIENTE | G1: INDUSTRIA | H1: SECTOR
A2: 107123016 | B2: TATIANA ANDREA HERNANDEZ GALLARDO | C2: HUECHURABA | D2: 13 | E2: ATENCION TELEFONICA | F2: CN10712301 | G2: DISTRIBUIDORES | H2: PRIVADO
A3: 119907985 | B3: HECTOR ENRIQUE ALTAMIRANO CRUZ | C3: PUDAHUEL | D3: 13 | E3: ATENCION TELEFONICA | F3: CN11990798 | G3: DISTRIBUIDORES | H3: PRIVADO
A4: 124106559 | B4: RAUL SALVADOR QUEZADA BILBAO | C4: LA REINA | D4: 13 | E4: ATENCION TELEFONICA | F4: CN12410655 | G4: DISTRIBUIDORES | H4: PRIVADO
A5: 128624430 | B5: ERWIN ACUÑA ROMAN | C5: CALERA DE TANGO | D5: 13 | E5: ATENCION TELEFONICA | F5: CN12862443 | G5: VETERINARIAS | H5: PRIVADO
A6: 130628583 | B6: ISAAC ALEJANDRO QUERO VALLEJOS | C6: VALDIVIA | D6: 14 | E6: ATENCION TELEFONICA | F6: CN13062858 | G6: CLINICAS | H6: PRIVADO
A7: 137714132 | B7: EVELYN ARANDA ARANDA | C7: MACUL | D7: 13 | E7: ATENCION TELEFONICA | F7: CN13771413 | G7: DISTRIBUIDORES | H7: PRIVADO
A8: 138177564 | B8: MARIA JOSE ROSAS | C8: VALDIVIA | D8: 14 | E8: ATENCION TELEFONICA | F8: CN13817756 | G8: DISTRIBUIDORES | H8: PRIVADO
A9: 143751368 | B9: MARCO ANTONIO SALDIAS ESCOBAR | C9: CHIGUAYANTE | D9: 8 | E9: ATENCION TELEFONICA | F9: CN14375136 | G9: DISTRIBUIDORES | H9: PRIVADO
A10: 150603439 | B10: MARIA JOSE MENDEZ VALENZUELA | C10: LOS ANDES | D10: 5 | E10: ATENCION TELEFONICA | F10: CN15060343 | G10: DISTRIBUIDORES | H10: PRIVADO
A11: 159017230 | B11: MIGUEL EDUARDO PEÑA PARRA | C11: LA SERENA | D11: 4 | E11: ATENCION TELEFONICA | F11: CN15901723 | G11: DISTRIBUIDORES | H11: PRIVADO
A12: 164793079 | B12: DANIEL ALEJANDRO PINO MARTINEZ | C12: PEDRO AGUIRRE CERDA | D12: 13 | E12: ATENCION TELEFONICA | F12: CN16479307 | G12: DISTRIBUIDORES | H12: PRIVADO
A13: 167985769 | B13: DIEGO ALONSO CADAGAN RUIZ | C13: QUILICURA | D13: 13 | E13: DAVID TOLEDO | F13: CN16798576 | H13: PRIVADO
A14: 176010681 | B14: JAVIERA LUCIA FUENTES VILLALOBOS | C14: LA PINTANA | D14: 13 | E14: ATENCION TELEFONICA | F14: CN17601068 | G14: VETERINARIAS | H14: PRIVADO
A15: 17777412K | B15: ANAHI FRANCISCA ROJAS HERNANDEZ | C15: HUECHURABA | D15: 13 | E15: ATENCION TELEFONICA | F15: CN17777412 | G15: DISTRIBUIDORES | H15: PRIVADO
A16: 193613578 | B16: JUAN BASTIAN GUERRERO VILLAGRA | C16: PICHILEMU | D16: 6 | E16: ATENCION TELEFONICA | F16: CN19361357 | G16: DISTRIBUIDORES | H16: PRIVADO
A17: 236443140 | B17: JUAN LUIS FERNANDEZ | C17: RECOLETA | D17: 13 | E17: ATENCION TELEFONICA | F17: CN23644314 | G17: DISTRIBUIDORES | H17: PRIVADO
A18: 267104476 | B18: PIERINA EVELIDA LOAYZA RAMIREZ | C18: RECOLETA | D18: 13 | E18: ATENCION TELEFONICA | F18: CN26710447 | G18: DISTRIBUIDORES | H18: PRIVADO
A19: 531258509 | B19: COMUNIDAD HOSPITAL DEL PROFESOR | C19: ESTACIÓN CENTRAL | D19: 13 | E19: MAURICIO RAMOS MORENO | F19: CN53125850 | G19: CLINICAS | H19: PRIVADO
A20: 53335808K | B20: CONS EXTERNO VALDIVIA | C20: VALDIVIA | D20: 14 | E20: MARCELO RUIZ | F20: CN53335808 | G20: CLINICAS | H20: PÚBLICO
A21: 58921203 | B21: GERMAN BEHNKE GUTIERREZ | C21: PUDAHUEL | D21: 13 | E21: ATENCION TELEFONICA | F21: CN5892120 | G21: DISTRIBUIDORES | H21: PRIVADO
A22: 59106780K | B22: GLOBAL HEALTHCARE CHILE LP | C22: SAN BERNARDO | D22: 13 | E22: ATENCION TELEFONICA | F22: CN59106780 | G22: DISTRIBUIDORES | H22: PRIVADO
A23: 605055230 | B23: XIV ZONA DE CARABINEROS LOS RIOS | C23: VALDIVIA | D23: 14 | E23: ATENCION TELEFONICA | F23: CN60505523 | G23: INST PUBLICAS | H23: PÚBLICO
A24: 605057233 | B24: HOSPITAL DE CARABINEROS | C24: ÑUÑOA | D24: 13 | E24: GIANCARLO MANNESCHI GALLARDO | F24: CN60505723 | G24: HOSPITALES | H24: PÚBLICO
A25: 605060110 | B25: JEFATURA DE BIENESTAR POLICÍA DE INVESTIGACIONES DE CHILE | C25: INDEPENDENCIA | D25: 13 | E25: ATENCION TELEFONICA | F25: CN60506011 | G25: INST PUBLICAS | H25: PÚBLICO
A26: 605140009 | B26: FONDOS PARA HOSPITALES DE CARABINEROS DE CHILE | C26: Ñuñoa | D26: 13 | E26: GIANCARLO MANNESCHI GALLARDO | F26: CN60514000 | G26: INST PUBLICAS | H26: PÚBLICO
A27: 608040072 | B27: DIRECCION REGIONAL DE LA ADUANA DE LOS ANDES | C27: LOS ANDES | D27: 5 | E27: ATENCION TELEFONICA | F27: CN60804007 | G27: INST PUBLICAS | H27: PÚBLICO
A28: 609100001 | B28: UNIVERSIDAD DE CHILE | C28: INDEPENDENCIA | D28: 13 | E28: MAURICIO RAMOS MORENO | F28: CN60910000 | G28: UNIVERSIDADES | H28: PÚBLICO
A29: 609110007 | B29: UNIVERSIDAD DE SANTIAGO DE CHILE | C29: ESTACIÓN CENTRAL | D29: 13 | E29: ATENCION TELEFONICA | F29: CN60911000 | G29: UNIVERSIDADES | H29: PÚBLICO
A30: 609210001 | B30: UNIVERSIDAD DE VALPARAISO | C30: VIÑA DEL MAR | D30: 5 | E30: ATENCION TELEFONICA | F30: CN60921000 | G30: UNIVERSIDADES | H30: PÚBLICO
A31: 610040004 | B31: GENDARMERIA DE CHILE | C31: SANTIAGO | D31: 13 | E31: ATENCION TELEFONICA | F31: CN61004000 | G31: INST PUBLICAS | H31: PÚBLICO
A32: 610040101 | B32: GENDARMERIA DE CHILE DIRECCION REGIONAL COPIAPO | C32: COPIAPÓ | D32: 3 | E32: ATENCION TELEFONICA | F32: CN61004010 | G32: INST PUBLICAS | H32: PÚBLICO
A33: 610040128 | B33: GENDARMERIA DE CHILE DIRECCION REGIONAL DE COQUIMBO | C33: LA SERENA | D33: 4 | E33: ATENCION TELEFONICA | F33: CN61004012 | G33: INST PUBLICAS | H33: PÚBLICO
A34: 610040241 | B34: DIRECCION REGIONAL DE GENDARMERIA - VALPARAISO | C34: VALPARAÍSO | D34: 5 | E34: ATENCION TELEFONICA | F34: CN61004024 | G34: INST PUBLICAS | H34: PÚBLICO
A35: 61004042K | B35: GENDARMERIA DE CHILE VI DIRECCION REGIONAL RANCAGUA | C35: RANCAGUA | D35: 6 | E35: ATENCION TELEFONICA | F35: CN61004042 | G35: INST PUBLICAS | H35: PÚBLICO
A36: 610040683 | B36: GENDARMERIA DE CHILE DIRECCION REGIONAL CONCEPCION | C36: CONCEPCIÓN | D36: 8 | E36: ATENCION TELEFONICA | F36: CN61004068 | G36: INST PUBLICAS | H36: PÚBLICO
A37: 610040985 | B37: GENDARMERIA DE CHILE DIRECCION REGIONAL PUERTO MONTT | C37: OSORNO | D37: 10 | E37: ATENCION TELEFONICA | F37: CN61004098 | G37: INST PUBLICAS | H37: PÚBLICO
A38: 610080006 | B38: SERVICIO NACIONAL DE MENORES | C38: CONCEPCIÓN | D38: 8 | E38: ATENCION TELEFONICA | F38: CN61008000 | G38: INST PUBLICAS | H38: PÚBLICO
A39: 611010303 | B39: HOSPITAL MILITAR DE SANTIAGO | C39: LA REINA | D39: 13 | E39: GIANCARLO MANNESCHI GALLARDO | F39: CN61101030 | G39: HOSPITALES | H39: PÚBLICO
A40: 611010311 | B40: CENTRAL ODONTOLOGICA DEL EJERCITO - COE | C40: SANTIAGO | D40: 13 | E40: ATENCION TELEFONICA | F40: CN61101031 | G40: INST PUBLICAS | H40: PÚBLICO
A41: 611010826 | B41: CENTRO CLINICO MILITAR ARICA | C41: ARICA | D41: 15 | E41: ATENCION TELEFONICA | F41: CN61101082 | G41: INST PUBLICAS | H41: PÚBLICO
A42: 611010869 | B42: HOSPITAL MILITAR DEL NORTE | C42: ANTOFAGASTA | D42: 2 | E42: ATENCION TELEFONICA | F42: CN61101086 | G42: HOSPITALES | H42: PÚBLICO
A43: 611020171 | B43: HOSPITAL NAVAL ALMIRANTE NEF | C43: VIÑA DEL MAR | D43: 5 | E43: CONSTANZA VALENZUELA | F43: CN61102017 | G43: HOSPITALES | H43: PÚBLICO
A44: 611020252 | B44: HOSPITAL NAVAL TALCAHUANO A.A. | C44: TALCAHUANO | D44: 8 | E44: RICARDO ENRIQUE ARAYA GONZÁLEZ | F44: CN61102025 | G44: HOSPITALES | H44: PÚBLICO
A45: 611020295 | B45: HOSPITAL NAVAL CIRUJANO GUZMAN DE MAGALLANES | C45: PUNTA ARENAS | D45: 12 | E45: ATENCION TELEFONICA | F45: CN61102029 | G45: HOSPITALES | H45: PÚBLICO
A46: 611020678 | B46: CENTRAL ODONTOLOGICA IIA ZONA NAVAL | C46: TALCAHUANO | D46: 8 | E46: ATENCION TELEFONICA | F46: CN61102067 | G46: INST PUBLICAS | H46: PÚBLICO
A47: 611030061 | B47: DIVISION DE BIENESTAR SOCIAL DE LA FUERZA AEREA DE CHILE | C47: IQUIQUE | D47: 1 | E47: MAURICIO RAMOS MORENO | F47: CN61103006 | G47: DISTRIBUIDORES | H47: PÚBLICO
A48: 61103007K | B48: HOSPITAL CLINICO GENERAL DR. RAUL YAZIGI J. | C48: LAS CONDES | D48: 13 | E48: GIANCARLO MANNESCHI GALLARDO | F48: CN61103007 | G48: HOSPITALES | H48: PÚBLICO
A49: 611030193 | B49: ALA BASE N.1 | C49: ANTOFAGASTA | D49: 2 | E49: ATENCION TELEFONICA | F49: CN61103019 | G49: INST PUBLICAS | H49: PÚBLICO
A50: 611030355 | B50: FUERZA AEREA DE CHILE COMANDO LOGISTICO | C50: EL BOSQUE | D50: 13 | E50: ATENCION TELEFONICA | F50: CN61103035 | G50: INST PUBLICAS | H50: PÚBLICO
A51: 611070004 | B51: INSTITUTO NACIONAL DE DEPORTES DE CHILE | C51: PROVIDENCIA | D51: 13 | E51: ATENCION TELEFONICA | F51: CN61107000 | G51: INST PUBLICAS | H51: PÚBLICO
A52: 61108000K | B52: CAJA DE PREVISION DE LA DEFENSA NACIONAL | C52: Santiago | D52: 13 | E52: ATENCION TELEFONICA | F52: CN61108000 | G52: INST PUBLICAS | H52: PÚBLICO
A53: 613080007 | B53: SERVICIO AGRICOLA Y GANADERO | C53: COPIAPÓ | D53: 3 | E53: ATENCION TELEFONICA | F53: CN61308000 | G53: INST PUBLICAS | H53: PÚBLICO
A54: 613130004 | B54: CORP NACIONAL FORESTAL | C54: LA UNIÓN | D54: 14 | E54: ATENCION TELEFONICA | F54: CN61313000 | G54: CORPORACIONES | H54: PÚBLICO
A55: 615130036 | B55: FONDOS PARA HOSPITALES DE CARABINEROS DE CHILE | C55: LAS CONDES | D55: 13 | E55: GIANCARLO MANNESCHI GALLARDO | F55: CN61513003 | G55: INST PUBLICAS | H55: PÚBLICO
A56: 61601000K | B56: SUBSECRETARIA DE SALUD PUBLICA | C56: VALPARAÍSO | D56: 4 | E56: ATENCION TELEFONICA | F56: CN61601000 | G56: INST PUBLICAS | H56: PÚBLICO
A57: 616020366 | B57: HOSPITAL SAN JUAN DE DIOS DE LOS ANDES | C57: LOS ANDES | D57: 5 | E57: CONSTANZA VALENZUELA | F57: CN61602036 | G57: HOSPITALES | H57: PÚBLICO
A58: 616020382 | B58: HOSPITAL SAN CAMILO DE SAN FELIPE | C58: SAN FELIPE | D58: 5 | E58: CONSTANZA VALENZUELA | F58: CN61602038 | G58: HOSPITALES | H58: PÚBLICO
A59: 616020404 | B59: HOSPITAL PSIQUIATRICO DR. PHILIPPE PINEL PUTAENDO | C59: PUTAENDO | D59: 5 | E59: ATENCION TELEFONICA | F59: CN61602040 | G59: HOSPITALES | H59: PÚBLICO
A60: 616020420 | B60: HOSPITAL SAN FRANCISCO DE LLAY LLAY | C60: LLAY-LLAY | D60: 5 | E60: ATENCION TELEFONICA | F60: CN61602042 | G60: HOSPITALES | H60: PÚBLICO
A61: 616020544 | B61: HOSPITAL CARLOS VAN BUREN | C61: VALPARAÍSO | D61: 5 | E61: CONSTANZA VALENZUELA | F61: CN61602054 | G61: HOSPITALES | H61: PÚBLICO
A62: 616020579 | B62: HOSPITAL EDUARDO PEREIRA | C62: VALPARAÍSO | D62: 5 | E62: CONSTANZA VALENZUELA | F62: CN61602057 | G62: HOSPITALES | H62: PÚBLICO
A63: 616020676 | B63: HOSPITAL SAN JOSE CASABLANCA | C63: CASABLANCA | D63: 5 | E63: ATENCION TELEFONICA | F63: CN61602067 | G63: HOSPITALES | H63: PÚBLICO
A64: 616021176 | B64: INSTITUTO NAC. DE REHABILITACION PEDRO AGUIRRE | C64: PEÑALOLÉN | D64: 13 | E64: ATENCION TELEFONICA | F64: CN61602117 | G64: INST PUBLICAS | H64: PÚBLICO
A65: 616021214 | B65: HOSPITAL DE PEÑAFLOR | C65: PEÑAFLOR | D65: 13 | E65: ATENCION TELEFONICA | F65: CN61602121 | G65: HOSPITALES | H65: PÚBLICO
A66: 616021222 | B66: HOSPITAL DE TALAGANTE | C66: TALAGANTE | D66: 13 | E66: ATENCION TELEFONICA | F66: CN61602122 | G66: HOSPITALES | H66: PÚBLICO
A67: 616021230 | B67: HOSPITAL DE MELIPILLA | C67: MELIPILLA | D67: 13 | E67: GIANCARLO MANNESCHI GALLARDO | F67: CN61602123 | G67: HOSPITALES | H67: PÚBLICO
A68: 616021257 | B68: HOSPITAL DE CURACAVI | C68: CURACAVÍ | D68: 13 | E68: ATENCION TELEFONICA | F68: CN61602125 | G68: HOSPITALES | H68: PÚBLICO
A69: 616021265 | B69: HOSPITAL CLAUDIO VICUÑA | C69: SAN ANTONIO | D69: 5 | E69: CONSTANZA VALENZUELA | F69: CN61602126 | G69: HOSPITALES | H69: PÚBLICO
A70: 61602132K | B70: HOSPITAL SANTA FILOMENA DE GRANEROS | C70: GRANEROS | D70: 6 | E70: ATENCION TELEFONICA | F70: CN61602132 | G70: HOSPITALES | H70: PÚBLICO
A71: 616021346 | B71: HOSPITAL COINCO | C71: COINCO | D71: 6 | E71: ATENCION TELEFONICA | F71: CN61602134 | G71: HOSPITALES | H71: PÚBLICO
A72: 616021389 | B72: HOSPITAL REGIONAL RANCAGUA | C72: RANCAGUA | D72: 6 | E72: MARCO MARINAO | F72: CN61602138 | G72: HOSPITALES | H72: PÚBLICO
A73: 616021400 | B73: HOSPITAL DE RENGO | C73: RENGO | D73: 6 | E73: ATENCION TELEFONICA | F73: CN61602140 | G73: HOSPITALES | H73: PÚBLICO
A74: 616021419 | B74: HOSPITAL DE SAN VICENTE DE TAGUA TAGUA | C74: SAN VICENTE | D74: 6 | E74: ATENCION TELEFONICA | F74: CN61602141 | G74: HOSPITALES | H74: PÚBLICO
A75: 616021427 | B75: HOSPITAL DE PEUMO | C75: PEUMO | D75: 6 | E75: ATENCION TELEFONICA | F75: CN61602142 | G75: HOSPITALES | H75: PÚBLICO
A76: 616021435 | B76: HOSPITAL DE PICHIDEGUA | C76: PICHIDEGUA | D76: 6 | E76: ATENCION TELEFONICA | F76: CN61602143 | G76: HOSPITALES | H76: PÚBLICO
A77: 616021451 | B77: HOSPITAL DE SAN FERNANDO | C77: SAN FERNANDO | D77: 6 | E77: MARCO MARINAO | F77: CN61602145 | G77: HOSPITALES | H77: PÚBLICO
A78: 61602146K | B78: HOSPITAL DE CHIMBARONGO | C78: CHIMBARONGO | D78: 6 | E78: ATENCION TELEFONICA | F78: CN61602146 | G78: HOSPITALES | H78: PÚBLICO
A79: 616021478 | B79: HOSPITAL DE NANCAGUA | C79: NANCAGUA | D79: 6 | E79: ATENCION TELEFONICA | F79: CN61602147 | G79: HOSPITALES | H79: PÚBLICO
A80: 616021486 | B80: HOSPITAL DE SANTA CRUZ | C80: SANTA CRUZ | D80: 6 | E80: ATENCION TELEFONICA | F80: CN61602148 | G80: HOSPITALES | H80: PÚBLICO
A81: 616021508 | B81: HOSPITAL LOLOL | C81: LOLOL | D81: 6 | E81: ATENCION TELEFONICA | F81: CN61602150 | G81: HOSPITALES | H81: PÚBLICO
A82: 616021516 | B82: HOSPITAL DE MARCHIGUE | C82: MARCHIHUE | D82: 6 | E82: ATENCION TELEFONICA | F82: CN61602151 | G82: HOSPITALES | H82: PÚBLICO
A83: 616021524 | B83: HOSPITAL LITUECHE | C83: LITUECHE | D83: 6 | E83: ATENCION TELEFONICA | F83: CN61602152 | G83: HOSPITALES | H83: PÚBLICO
A84: 616021532 | B84: HOSPITAL PICHILEMU | C84: PICHILEMU | D84: 6 | E84: ATENCION TELEFONICA | F84: CN61602153 | G84: HOSPITALES | H84: PÚBLICO
A85: 616021893 | B85: HOSPITAL GUILLERMO GRANT BENAVENTE | C85: CONCEPCIÓN | D85: 8 | E85: RICARDO ENRIQUE ARAYA GONZÁLEZ | F85: CN61602189 | G85: HOSPITALES | H85: PÚBLICO
A86: 61602194K | B86: HOSPITAL DE COELEMU | C86: COELEMU | D86: 16 | E86: ATENCION TELEFONICA | F86: CN61602194 | G86: HOSPITALES | H86: PÚBLICO
A87: 616021982 | B87: HOSPITAL DE PENCO | C87: PENCO | D87: 8 | E87: RICARDO ENRIQUE ARAYA GONZÁLEZ | F87: CN61602198 | G87: HOSPITALES | H87: PÚBLICO
A88: 616021990 | B88: HOSPITAL FLORIDA | C88: FLORIDA | D88: 8 | E88: ATENCION TELEFONICA | F88: CN61602199 | G88: HOSPITALES | H88: PÚBLICO
A89: 616022016 | B89: HOSPITAL SAN JOSE DE CORONEL | C89: CORONEL | D89: 8 | E89: RICARDO ENRIQUE ARAYA GONZÁLEZ | F89: CN61602201 | G89: HOSPITALES | H89: PÚBLICO
A90: 616022032 | B90: HOSPITAL LOTA | C90: LOTA | D90: 8 | E90: RICARDO ENRIQUE ARAYA GONZÁLEZ | F90: CN61602203 | G90: HOSPITALES | H90: PÚBLICO
A91: 616022040 | B91: HOSPITAL SANTA JUANA | C91: SANTA JUANA | D91: 8 | E91: ATENCION TELEFONICA | F91: CN61602204 | G91: HOSPITALES | H91: PÚBLICO
A92: 616022091 | B92: HOSPITAL ARAUCO | C92: ARAUCO | D92: 8 | E92: ATENCION TELEFONICA | F92: CN61602209 | G92: HOSPITALES | H92: PÚBLICO
A93: 616022113 | B93: HOSPITAL DE CURANILAHUE | C93: CURANILAHUE | D93: 8 | E93: RICARDO ENRIQUE ARAYA GONZÁLEZ | F93: CN61602211 | G93: HOSPITALES | H93: PÚBLICO
A94: 616022121 | B94: HOSPITAL LEBU | C94: LEBU | D94: 8 | E94: RICARDO ENRIQUE ARAYA GONZÁLEZ | F94: CN61602212 | G94: HOSPITALES | H94: PÚBLICO
A95: 61602213K | B95: HOSPITAL CAÑETE | C95: Cañete | D95: 8 | E95: RICARDO ENRIQUE ARAYA GONZÁLEZ | F95: CN61602213 | G95: HOSPITALES | H95: PÚBLICO
A96: 616022202 | B96: HOSPITAL NACIMIENTO | C96: NACIMIENTO | D96: 8 | E96: ATENCION TELEFONICA | F96: CN61602220 | G96: HOSPITALES | H96: PÚBLICO
A97: 616022229 | B97: HOSPITAL ANGOL | C97: ANGOL | D97: 9 | E97: RICARDO ENRIQUE ARAYA GONZÁLEZ | F97: CN61602222 | G97: HOSPITALES | H97: PÚBLICO
A98: 616022237 | B98: HOSPITAL COLLIPULLI | C98: COLLIPULLI | D98: 9 | E98: ATENCION TELEFONICA | F98: CN61602223 | G98: HOSPITALES | H98: PÚBLICO
A99: 616022245 | B99: HOSPITAL PUREN | C99: PURÉN | D99: 9 | E99: ATENCION TELEFONICA | F99: CN61602224 | G99: HOSPITALES | H99: PÚBLICO
A100: 616022261 | B100: HOSPITAL DE TRAIGUEN | C100: TRAIGUÉN | D100: 9 | E100: ATENCION TELEFONICA | F100: CN61602226 | G100: HOSPITALES | H100: PÚBLICO
...

Sheet sell
A1: TANDA | B1: MARCA | C1: MODELO | D1: SERIE | E1: RUT | F1: UBICACIÓN | G1: ESTADO | H1: COMENTARIO | I1: Actualización Solicitada | J1: informe consumo | K1: FECHA INICIO | L1: rutt | M1: namee | N1: SD
A2: 3 | B2: STERIVIC | C2: MY100C | D2: C235003 | E2: 820318005 | F2: HOSPITAL PARROQUIAL DE SAN BERNARDO SANTIAGO | G2: COMODATO | H2: En prestamo por cerrar acuerdo comercial Giancarlo | I2: solicitado | K2: 45444 | L2: 820318005 | M2: HOSPITAL PARROQUIAL DE SAN BERNARDO SANTIAGO | N2: =IF(L2=E2,"ok", "nooo") -> ok
A3: 1 | B3: STERIVIC | C3: MY100C | D3: C231012 | E3: 61103007K | F3: HOSPITAL FUERZA AEREA DE CHILE YAZIGI LAS CONDES | G3: COMODATO | I3: solicitado | K3: 45047 | L3: 61103007K | M3: HOSPITAL FUERZA AEREA DE CHILE YAZIGI LAS CONDES | N3: =IF(L3=E3,"ok", "nooo") -> ok
A4: 4 | B4: STERIVIC | C4: MY100C | D4: C23B003 | E4: 762152606 | F4: NEMO | G4: BODEGA | H4: RICARDO LA TIENE EN SU PODER PARA CORONEL | K4: 45536 | L4: 691512029 | N4: =IF(L4=E4,"ok", "nooo") -> nooo
A5: 3 | B5: STERIVIC | C5: MY100C | D5: C235006 | E5: 61103007K | F5: HOSPITAL FUERZA AEREA DE CHILE YAZIGI LAS CONDES | G5: COMODATO | I5: solicitado | K5: 45047 | L5: 61103007K | M5: HOSPITAL FUERZA AEREA DE CHILE YAZIGI LAS CONDES | N5: =IF(L5=E5,"ok", "nooo") -> ok
A6: 2 | B6: STERIVIC | C6: MY100C | D6: C233013 | E6: 616021230 | F6: HOSPITAL DE MELIPILLA | G6: COMODATO | I6: solicitado | K6: 45306 | L6: 616021230 | M6: HOSPITAL DE MELIPILLA | N6: =IF(L6=E6,"ok", "nooo") -> ok
A7: 2 | B7: STERIVIC | C7: MY100C | D7: C233012 | E7: 616021982 | F7: HOSPITAL DE PENCO LIRQUEN CONCEPCION | G7: COMODATO | H7: SE ESTA MEJORANDO LAS COMPRAS HUBO REUNION | I7: solicitado | J7: enviado a vendedor y cliente | K7: 45096 | L7: 616021982 | M7: HOSPITAL DE PENCO LIRQUEN CONCEPCION | N7: =IF(L7=E7,"ok", "nooo") -> ok
A8: 2 | B8: STERIVIC | C8: MY100C | D8: C233016 | E8: 616021982 | F8: HOSPITAL DE PENCO LIRQUEN CONCEPCION | G8: COMODATO | H8: SE ESTA MEJORANDO LAS COMPRAS HUBO REUNION | I8: solicitado | J8: enviado a vendedor y cliente | K8: 45147 | L8: 616021982 | M8: HOSPITAL DE PENCO LIRQUEN CONCEPCION | N8: =IF(L8=E8,"ok", "nooo") -> ok
A9: 3 | B9: STERIVIC | C9: MY100C | D9: C235004 | E9: 616021982 | F9: HOSPITAL DE PENCO LIRQUEN CONCEPCION | G9: COMODATO | H9: SE ESTA MEJORANDO LAS COMPRAS HUBO REUNION | I9: solicitado | J9: enviado a vendedor y cliente | K9: 45514 | L9: 616021982 | M9: HOSPITAL DE PENCO LIRQUEN CONCEPCION | N9: =IF(L9=E9,"ok", "nooo") -> ok
A10: 1 | B10: STERIVIC | C10: MY100C | D10: C231009 | E10: 616066080 | F10: HOSPITAL BIPROVINCIAL QUILLOTA PETORCA | G10: COMODATO | I10: solicitado | J10: enviado a vendedor y cliente | K10: 44924 | L10: 616066005 | M10: HOSPITAL BIPROVINCIAL QUILLOTA PETORCA | N10: =IF(L10=E10,"ok", "nooo") -> nooo
A11: 2 | B11: STERIVIC | C11: MY100C | D11: C233018 | E11: 616066080 | F11: HOSPITAL BIPROVINCIAL QUILLOTA PETORCA | G11: COMODATO | I11: solicitado | J11: enviado a vendedor y cliente | K11: 44983 | L11: 616066005 | M11: HOSPITAL BIPROVINCIAL QUILLOTA PETORCA | N11: =IF(L11=E11,"ok", "nooo") -> nooo
A12: 5 | B12: STERIVIC | C12: MY100C | D12: C246011 | E12: 616066080 | F12: HOSPITAL BIPROVINCIAL QUILLOTA PETORCA | G12: COMODATO | H12: SE LLEVA ANEXO CON TODAS LAS SELALDORAS | K12: 45580 | L12: 616066005 | M12: HOSPITAL BIPROVINCIAL QUILLOTA PETORCA | N12: =IF(L12=E12,"ok", "nooo") -> nooo
A13: 2 | B13: STERIVIC | C13: MY100C | D13: C233017 | E13: 691508005 | F13: DAS CESFAM DE TALCAHUANO | G13: COMODATO | H13: 691508005 | I13: solicitado | K13: 45408 | L13: 616072005 | M13: DAS CESFAM DE TALCAHUANO | N13: =IF(L13=E13,"ok", "nooo") -> nooo
A14: 4 | B14: STERIVIC | C14: MY100C | D14: C23B004 | E14: 61608402K | F14: HOSPITAL DEL TORAX SANTIAGO | G14: COMODATO | H14: MARCO MARINAO PEDIRA DOCUMENTO | I14: solicitado | K14: 45414 | L14: 61608402K | M14: HOSPITAL DEL TORAX SANTIAGO | N14: =IF(L14=E14,"ok", "nooo") -> ok
A15: 2 | B15: STERIVIC | C15: MY100C | D15: C233020 | E15: 762152606 | F15: NEMO | G15: FALLA | H15: A LA ESPERA DE FIRMA INCLUIRAN UNA SELLADORA MÁS | I15: solicitado | J15: enviado a vendedor y cliente | K15: 45049 | L15: 65061030k | M15: CENTRO REFERENCIA DE SALUD CRS MAIPU SANTIAGO | N15: =IF(L15=E15,"ok", "nooo") -> nooo
A16: 2 | B16: STERIVIC | C16: MY100C | D16: C233015 | E16: 691501027 | F16: DAS CESFAM TOME CONCEPCION | G16: COMODATO | H16: DIRECCION DE SALUD MUNI. | I16: solicitado | K16: 45184 | L16: 691501027 | M16: DAS CESFAM TOME CONCEPCION | N16: =IF(L16=E16,"ok", "nooo") -> ok
A17: 4 | B17: STERIVIC | C17: MY100C | D17: C23B006 | E17: 61602244k | F17: HOSPITAL DE CUNCO TEMUCO | G17: LICITACION ADJUDICADA | H17: 2067-12-LE24 | K17: 45441 | L17: 61602244k | M17: HOSPITAL DE CUNCO TEMUCO | N17: =IF(L17=E17,"ok", "nooo") -> ok
A18: 4 | B18: STERIVIC | C18: MY100C | D18: C23B007 | E18: 61602244k | F18: HOSPITAL DE CUNCO TEMUCO | G18: LICITACION ADJUDICADA | H18: 2067-12-LE24 | K18: 45441 | L18: 61602244k | M18: HOSPITAL DE CUNCO TEMUCO | N18: =IF(L18=E18,"ok", "nooo") -> ok
A19: 3 | B19: STERIVIC | C19: MY100C | D19: C235009 | E19: 691501027 | F19: DAS CESFAM TOME CONCEPCION | G19: COMODATO | I19: solicitado | K19: 45184 | L19: 691501027 | M19: DAS CESFAM TOME CONCEPCION | N19: =IF(L19=E19,"ok", "nooo") -> ok
A20: 4 | B20: STERIVIC | C20: MY100C | D20: C23B009 | E20: 692569008 | F20: DAS CESFAM PEDRO DE VALDIVIA CONCEPCION | G20: COMODATO | I20: solicitado | K20: 45434 | L20: 692569008 | M20: DAS CESFAM PEDRO DE VALDIVIA CONCEPCION | N20: =IF(L20=E20,"ok", "nooo") -> ok
A21: 4 | B21: STERIVIC | C21: MY100C | D21: C23B008 | E21: 692569008 | F21: DAS CESFAM TUCAPEL CONCEPCION | G21: COMODATO | I21: solicitado | K21: 45434 | L21: 692569008 | M21: DAS CESFAM TUCAPEL CONCEPCION | N21: =IF(L21=E21,"ok", "nooo") -> ok
A22: 3 | B22: STERIVIC | C22: MY100C | D22: C235007 | E22: 742696006 | F22: DAS CESFAM DE SAN PEDRO DE LA PAZ CONCEPCION | G22: COMODATO | I22: solicitado | K22: 45093 | L22: 742696006 | M22: DAS CESFAM DE SAN PEDRO DE LA PAZ CONCEPCION | N22: =IF(L22=E22,"ok", "nooo") -> ok
A23: 5 | B23: STERIVIC | C23: MY100C | D23: C246008 | E23: 605057233 | F23: HOSCAR HOSPITAL DE CARABINEROS | G23: PRESTAMO | H23: SE DESPACHO Y MARCELO INSTALO RECIEN | J23: EN PRESTAMO HASTA EL 30 OCT 2024 | K23: 45573 | L23: 605057233 | M23: HOSCAR HOSPITAL DE CARABINEROS | N23: =IF(L23=E23,"ok", "nooo") -> ok
A24: 3 | B24: STERIVIC | C24: MY100C | D24: C235008 | E24: 742696006 | F24: DAS CESFAM DE SAN PEDRO DE LA PAZ CONCEPCION | G24: COMODATO | I24: solicitado | K24: 45093 | L24: 742696006 | M24: DAS CESFAM DE SAN PEDRO DE LA PAZ CONCEPCION | N24: =IF(L24=E24,"ok", "nooo") -> ok
A25: 2 | B25: STERIVIC | C25: MY100C | D25: C233014 | E25: 616020579 | F25: HOSPITAL EDUARDO PEREIRA VALPARAISO | G25: LICITACION ADJUDICADA | H25: 875646-18-LQ24 | I25: solicitado | J25: enviado a vendedor y cliente | K25: 45063 | L25: 616020579 | M25: HOSPITAL EDUARDO PEREIRA VALPARAISO | N25: =IF(L25=E25,"ok", "nooo") -> ok
A26: 2 | B26: STERIVIC | C26: MY100C | D26: C233022 | E26: 616020579 | F26: HOSPITAL EDUARDO PEREIRA VALPARAISO | G26: LICITACION ADJUDICADA | H26: 875646-18-LQ24 | J26: enviado a vendedor y cliente | K26: 45542 | L26: 616020579 | M26: HOSPITAL EDUARDO PEREIRA VALPARAISO | N26: =IF(L26=E26,"ok", "nooo") -> ok
A27: 3 | B27: STERIVIC | C27: MY100C | D27: C235014 | E27: 742696006 | F27: DAS CESFAM DE SAN PEDRO DE LA PAZ CONCEPCION | G27: COMODATO | I27: solicitado | K27: 45184 | L27: 742696006 | M27: DAS CESFAM DE SAN PEDRO DE LA PAZ CONCEPCION | N27: =IF(L27=E27,"ok", "nooo") -> ok
A28: 5 | B28: STERIVIC | C28: MY100C | D28: C246010 | E28: 760579041 | F28: HOSPITAL CLINICO DEL SUR CONCEPCION | G28: COMODATO | H28: CLIENTE INFORMO QUE ESTABA LISTA FIRMA | I28: retirará ricardo | K28: 45518 | L28: 760579041 | M28: HOSPITAL CLINICO DEL SUR CONCEPCION | N28: =IF(L28=E28,"ok", "nooo") -> ok
A29: 3 | B29: STERIVIC | C29: MY100C | D29: C235010 | E29: 616072021 | F29: HOSPITAL HIGUERAS TALCAHUANO | G29: LICITACION ADJUDICADA | H29: 1057544-325-LE24 | K29: 45112 | L29: 616072021 | M29: HOSPITAL HIGUERAS TALCAHUANO | N29: =IF(L29=E29,"ok", "nooo") -> ok
A30: 3 | B30: STERIVIC | C30: MY100C | D30: C235013 | E30: 616072021 | F30: HOSPITAL HIGUERAS TALCAHUANO | G30: LICITACION ADJUDICADA | H30: 1057544-325-LE24 | K30: 45112 | L30: 616072021 | M30: HOSPITAL HIGUERAS TALCAHUANO | N30: =IF(L30=E30,"ok", "nooo") -> ok
A31: 4 | B31: STERIVIC | C31: MY100C | D31: C23B001 | E31: 616072021 | F31: HOSPITAL HIGUERAS TALCAHUANO | G31: LICITACION ADJUDICADA | H31: 1057544-325-LE24 | K31: 45112 | L31: 616072021 | M31: HOSPITAL HIGUERAS TALCAHUANO | N31: =IF(L31=E31,"ok", "nooo") -> ok
A32: 4 | B32: STERIVIC | C32: MY100C | D32: C23B002 | E32: 616072021 | F32: HOSPITAL HIGUERAS TALCAHUANO | G32: LICITACION ADJUDICADA | H32: 1057544-325-LE24 | K32: 45112 | L32: 616072021 | M32: HOSPITAL HIGUERAS TALCAHUANO | N32: =IF(L32=E32,"ok", "nooo") -> ok
A33: 4 | B33: STERIVIC | C33: MY100C | D33: C23B005 | E33: 616072021 | F33: HOSPITAL HIGUERAS TALCAHUANO | G33: LICITACION ADJUDICADA | H33: 1057544-325-LE24 | K33: 45112 | L33: 616072021 | M33: HOSPITAL HIGUERAS TALCAHUANO | N33: =IF(L33=E33,"ok", "nooo") -> ok
A34: 2 | B34: STERIVIC | C34: MY100C | D34: C233021 | E34: 616060015 | F34: HOSPITAL JUAN NOE CREVANI ARICA | G34: LICITACION ADJUDICADA | H34: 1075963-322-LE24 | K34: 45496 | L34: 616060015 | M34: HOSPITAL JUAN NOE CREVANI ARICA | N34: =IF(L34=E34,"ok", "nooo") -> ok
A35: 3 | B35: STERIVIC | C35: MY100C | D35: C235012 | E35: 616060015 | F35: HOSPITAL JUAN NOE CREVANI ARICA | G35: LICITACION ADJUDICADA | H35: 1075963-322-LE24 | K35: 45496 | L35: 616060015 | M35: HOSPITAL JUAN NOE CREVANI ARICA | N35: =IF(L35=E35,"ok", "nooo") -> ok
A36: 5 | B36: STERIVIC | C36: MY100C | D36: C246009 | E36: 611020252 | F36: HOSPITAL NAVAL TALCAHUANO | G36: PRESTAMO | H36: SE ESTA TRAMITANDO COMPRAS, SE ENVIO DE MUESTRAS | J36: EN PRESTAMO HASTA EL 30 OCT 2024 | K36: 45576 | L36: 691512029 | M36: DAS CORONEL | N36: =IF(L36=E36,"ok", "nooo") -> nooo
A37: 1 | B37: STERIVIC | C37: MY100C | D37: C231013 | E37: 780353902 | F37: CLINICA SAN ANTONIO | G37: COMODATO | I37: solicitado | J37: enviado a vendedor y cliente | K37: 45217 | L37: 780353902 | M37: CLINICA SAN ANTONIO | N37: =IF(L37=E37,"ok", "nooo") -> ok
A38: 2 | B38: STERIVIC | C38: MY100C | D38: C233019 | E38: 69081000K | F38: CESFAM TAGUA TAGUA | G38: COMODATO | H38: 69081000K | I38: solicitado | K38: 45510 | L38: 69081000K | M38: CESFAM TAGUA TAGUA | N38: =IF(L38=E38,"ok", "nooo") -> ok
A39: 5 | B39: STERIVIC | C39: MY100C | D39: C246012 | E39: 762152606 | F39: NEMO | G39: FALLA | H39: SE PASARÁ A CRS MAIPU SANTIAGO | L39: 65061030k | M39: CENTRO REFERENCIA DE SALUD CRS MAIPU SANTIAGO | N39: =IF(L39=E39,"ok", "nooo") -> nooo
A40: 5 | B40: STERIVIC | C40: MY100C | D40: C246013 | E40: 616075020 | F40: SERVICIO SALUD VALDIVIA HOSPITAL BASE DE VALDIVIA | G40: LICITACION ADJUDICADA | L40: 616075020 | M40: SERVICIO SALUD VALDIVIA HOSPITAL BASE DE VALDIVIA | N40: =IF(L40=E40,"ok", "nooo") -> ok
A41: 5 | B41: STERIVIC | C41: MY100C | D41: C246014 | E41: 616021419 | F41: HOSPITAL SAN VICENTE DE TAGUA TAGUA | G41: COMODATO | L41: 616021419 | M41: HOSPITAL SAN VICENTE DE TAGUA TAGUA | N41: =IF(L41=E41,"ok", "nooo") -> ok
A42: 5 | B42: STERIVIC | C42: MY100C | D42: C246015 | E42: 616075020 | F42: SERVICIO SALUD VALDIVIA HOSPITAL BASE DE VALDIVIA | G42: LICITACION ADJUDICADA | L42: 616075020 | M42: SERVICIO SALUD VALDIVIA HOSPITAL BASE DE VALDIVIA | N42: =IF(L42=E42,"ok", "nooo") -> ok
A43: 5 | B43: STERIVIC | C43: MY100C | D43: C246016 | E43: 616086022 | F43: HOSPITAL DE URGENCIA ASISTENCIA PUBLICA DR ALEJANDRO DEL RIO | G43: LICITACION ADJUDICADA | L43: 616086022 | M43: HOSPITAL DE URGENCIA ASISTENCIA PUBLICA DR ALEJANDRO DEL RIO | N43: =IF(L43=E43,"ok", "nooo") -> ok
A44: 5 | B44: STERIVIC | C44: MY100C | D44: C246017 | E44: 762152606 | F44: NEMO | G44: BODEGA | L44: 762152606 | M44: DISPONIBLE | N44: =IF(L44=E44,"ok", "nooo") -> ok
A45: 5 | B45: STERIVIC | C45: MY100C | D45: C246018 | E45: 616086022 | F45: HOSPITAL DE URGENCIA ASISTENCIA PUBLICA DR ALEJANDRO DEL RIO | G45: LICITACION ADJUDICADA | L45: 616086022 | M45: HOSPITAL DE URGENCIA ASISTENCIA PUBLICA DR ALEJANDRO DEL RIO | N45: =IF(L45=E45,"ok", "nooo") -> ok
A46: 5 | B46: STERIVIC | C46: MY100C | D46: C246019 | E46: 762152606 | F46: NEMO | G46: BODEGA | L46: 762152606 | M46: DISPONIBLE | N46: =IF(L46=E46,"ok", "nooo") -> ok
A47: 5 | B47: STERIVIC | C47: MY100C | D47: C246021 | E47: 65061030K | F47: CRS MAIPU | G47: COMODATO | L47: 65061030k | M47: CRS DE MAIPU SE INSTALA HOY 7 ENERO OTRAS DOS EN MANTENCION | N47: =IF(L47=E47,"ok", "nooo") -> ok
A48: 5 | B48: STERIVIC | C48: MY100C | D48: C246022 | E48: 692569008 | F48: NEMO | G48: COMODATO | L48: 692569008 | M48: DAS CESFAM JUAN SOTO FERNANDEZ DAS CONCEPCION | N48: =IF(L48=E48,"ok", "nooo") -> ok
A49: 6 | B49: STERIVIC | C49: MY100D | D49: D244003 | E49: 616086022 | F49: POSTA CENTRAL | G49: LICITACION ADJUDICADA | L49: 616086022 | M49: HOSPITAL ASISTENCIA PUBLICA POSTA CENTRAL | N49: =IF(L49=E49,"ok", "nooo") -> ok
A50: 6 | B50: STERIVIC | C50: MY100D | D50: D244004 | E50: 605057233 | F50: HOSPITAL HOSCAR | G50: PRESTAMO | L50: 605057233 | M50: HOSPITAL DE CARABINEROS | N50: =IF(L50=E50,"ok", "nooo") -> ok
A51: 7 | B51: HAWO | C51: HD 680 DE | D51: 521633 | E51: 762152606 | F51: PRODUCCION EINSTEIN | G51: PRODUCCION | L51: 0 | M51: PRODUCCION EINSTEIN | N51: =IF(L51=E51,"ok", "nooo") -> nooo
A52: 7 | B52: HAWO | C52: HD 680 DE | D52: 535847 | E52: 762152606 | F52: PRODUCCION EINSTEIN | G52: PRODUCCION | L52: 0 | M52: PRODUCCION EINSTEIN | N52: =IF(L52=E52,"ok", "nooo") -> nooo
A53: 8 | B53: STERIVIC | C53: MY100B | D53: B22B001 | E53: 762152606 | F53: PRODUCCION EINSTEIN | G53: PRODUCCION | L53: 0 | M53: PRODUCCION EINSTEIN | N53: =IF(L53=E53,"ok", "nooo") -> nooo
A54: 8 | B54: STERIVIC | C54: MY100B | D54: B22B002 | E54: 762152606 | F54: PRODUCCION EINSTEIN | G54: PRODUCCION | L54: 0 | M54: PRODUCCION EINSTEIN | N54: =IF(L54=E54,"ok", "nooo") -> nooo
A55: 8 | B55: STERIVIC | C55: MY100B | D55: B22B003 | E55: 762152606 | F55: PRODUCCION EINSTEIN | G55: PRODUCCION | L55: 0 | M55: PRODUCCION EINSTEIN | N55: =IF(L55=E55,"ok", "nooo") -> nooo
A56: 8 | B56: STERIVIC | C56: MY100B | D56: B22B004 | E56: 762152606 | F56: PRODUCCION EINSTEIN | G56: PRODUCCION | L56: 0 | M56: PRODUCCION EINSTEIN | N56: =IF(L56=E56,"ok", "nooo") -> nooo
A57: 8 | B57: STERIVIC | C57: MY100B | D57: B22B005 | E57: 762152606 | F57: PRODUCCION EINSTEIN | G57: PRODUCCION | L57: 0 | M57: PRODUCCION EINSTEIN | N57: =IF(L57=E57,"ok", "nooo") -> nooo
A58: 8 | B58: STERIVIC | C58: MY100B | D58: B22B006 | E58: 762152606 | F58: PRODUCCION EINSTEIN | G58: PRODUCCION | L58: 0 | M58: PRODUCCION EINSTEIN | N58: =IF(L58=E58,"ok", "nooo") -> nooo
A59: 1 | B59: STERIVIC | C59: MY100C | D59: C23B010 | E59: 762152606 | F59: PRODUCCION EINSTEIN | G59: PRODUCCION | L59: 0 | M59: PRODUCCION EINSTEIN | N59: =IF(L59=E59,"ok", "nooo") -> nooo
A60: 3 | B60: STERIVIC | C60: MY100C | D60: C235005 | E60: 762152606 | F60: PRODUCCION EINSTEIN | G60: PRODUCCION | L60: 0 | M60: PRODUCCION EINSTEIN | N60: =IF(L60=E60,"ok", "nooo") -> nooo
A61: 1 | B61: STERIVIC | C61: MY100C | D61: C231010 | E61: 762152606 | F61: PRODUCCION EINSTEIN | G61: PRODUCCION | H61: PRESTAMO PRODUCCION | J61: PRODUCCION | L61: 0 | M61: SAN JOSE | N61: =IF(L61=E61,"ok", "nooo") -> nooo
A62: 3 | B62: STERIVIC | C62: MY100C | D62: C235011 | E62: 762152606 | F62: PRODUCCION EINSTEIN (CASA TICONA) | G62: PRODUCCION | L62: 0 | M62: PRODUCCION EINSTEIN (CASA TICONA) | N62: =IF(L62=E62,"ok", "nooo") -> nooo
